Workbook

Sheet output>

Sheet 集計
C2: メルマガ登録→審査フォーム回答率 | D2: 審査フォーム→個別相談予約率 | E2: メルマガ登録→個別相談予約率
B3: 全体 | C3: =D16/C16 -> 0.28642659 | D3: =E16/D16 -> 0.7098646 | E3: =E16/C16 -> 0.2033241
B4: 20258月 | C4: =D17/C17 -> 0.27619048 | D4: =E17/D17 -> 0.8045977 | E4: =E17/C17 -> 0.22222222
B5: 20259月 | C5: =D18/C18 -> 0.22509225 | D5: =E18/D18 -> 0.95081967 | E5: =E18/C18 -> 0.21402214
B6: 202510月 | C6: =D19/C19 -> 0.27986348 | D6: =E19/D19 -> 0.57317073 | E6: =E19/C19 -> 0.16040956
B7: 202511月 | C7: =D20/C20 -> 0.33986928 | D7: =E20/D20 -> 0.63461538 | E7: =E20/C20 -> 0.21568627
B8: 202512月 | C8: =D21/C21 -> 0.62195122 | D8: =E21/D21 -> 0.58823529 | E8: =E21/C21 -> 0.36585366
B9: 20261月 | C9: =D22/C22 -> 0.18072289 | D9: =E22/D22 -> 0.8 | E9: =E22/C22 -> 0.14457831
B10: 20258-9月 | C10: =D23/C23 -> 0.26254376 | D10: =E23/D23 -> 0.67555556 | E10: =E23/C23 -> 0.17736289
B11: 202510-11月 | C11: =D24/C24 -> 0.29228687 | D11: =E24/D24 -> 0.58796296 | E11: =E24/C24 -> 0.17185386
B12: 202512-20261月 | C12: =D25/C25 -> 0.43829787 | D12: =E25/D25 -> 0.61165049 | E12: =E25/C25 -> 0.26808511
C15: メルマガ登録数 | D15: 審査フォーム回答数 | E15: 個別相談予約数
B16: 全体 | C16: =COUNTA(_xlfn.ANCHORARRAY(全体!E3)) -> 1805 | D16: =COUNTA(_xlfn.ANCHORARRAY(全体!L3)) -> 517 | E16: =COUNTA(_xlfn.ANCHORARRAY(全体!S3)) -> 367
B17: 20258月 | C17: =COUNTA('20258月'!B3:B632) -> 630 | D17: =COUNTA('20258月'!E3:E176) -> 174 | E17: =COUNTA('20258月'!H3:H142) -> 140
B18: 20259月 | C18: =COUNTA('20259月'!B3:B273) -> 271 | D18: =COUNTA('20259月'!E3:E63) -> 61 | E18: =COUNTA('20259月'!H3:H60) -> 58
B19: 202510月 | C19: =COUNTA('202510月'!B3:B588) -> 586 | D19: =COUNTA('202510月'!E3:E166) -> 164 | E19: =COUNTA('202510月'!H3:H96) -> 94
B20: 202511月 | C20: =COUNTA('202511月'!B3:B155) -> 153 | D20: =COUNTA('202511月'!E3:E54) -> 52 | E20: =COUNTA('202511月'!H3:H35) -> 33
B21: 202512月 | C21: =COUNTA('202512月'!B3:B84) -> 82 | D21: =COUNTA('202512月'!E3:E53) -> 51 | E21: =COUNTA('202512月'!H3:H32) -> 30
B22: 20261月 | C22: =COUNTA('20261月'!B3:B85) -> 83 | D22: =COUNTA('20261月'!E3:E17) -> 15 | E22: =COUNTA('20261月'!H3:H14) -> 12
B23: 20259-10月 | C23: =C18+C19 -> 857 | D23: =D18+D19 -> 225 | E23: =E18+E19 -> 152
B24: 202510-11月 | C24: =C19+C20 -> 739 | D24: =D19+D20 -> 216 | E24: =E19+E20 -> 127
B25: 202511-12月 | C25: =C20+C21 -> 235 | D25: =D20+D21 -> 103 | E25: =E20+E21 -> 63
B26: 202512-20261月 | C26: =C21+C22 -> 165 | D26: =D21+D22 -> 66 | E26: =E21+E22 -> 42

Sheet >process

Sheet 全体
B2: メルマガ登録者 | C2: 登録日時 | E2: メルマガ登録者(重複なし) | F2: 登録日時 | I2: 審査フォーム回答者 | J2: 登録日時 | L2: 審査フォーム回答者(重複なし) | M2: 登録日時 | P2: 個別相談予約者 | Q2: 登録日時 | S2: 個別相談予約者(重複なし) | T2: 登録日時
B3: rn010240@gmail.com | C3: 45876.933 | E3: {=_xlfn.UNIQUE(B3:B2213)} -> rn010240@gmail.com | F3: =_xlfn.XLOOKUP(E3,B:B,C:C) -> 45876.933 | I3: ty11055yoshi@gmail.com | J3: 45884.795 | L3: {=_xlfn.UNIQUE(I3:I753)} -> ty11055yoshi@gmail.com | M3: =_xlfn.XLOOKUP(L3,I:I,J:J) -> 45884.795 | P3: private@jun-otsu.com | Q3: 45874.959 | S3: {=_xlfn.UNIQUE(P3:P391)} -> private@jun-otsu.com | T3: =_xlfn.XLOOKUP(S3,P:P,Q:Q) -> 45874.959
B4: jin.hitoshi@gmail.com | C4: 45877.814 | E4: jin.hitoshi@gmail.com | F4: =_xlfn.XLOOKUP(E4,B:B,C:C) -> 45877.814 | I4: take.mas1969@gmail.com | J4: 45884.795 | L4: take.mas1969@gmail.com | M4: =_xlfn.XLOOKUP(L4,I:I,J:J) -> 45884.795 | P4: w.rainey-0840@kuf.biglobe.ne.jp | Q4: 45885.816 | S4: w.rainey-0840@kuf.biglobe.ne.jp | T4: =_xlfn.XLOOKUP(S4,P:P,Q:Q) -> 45885.816
B5: akikoko0110@yahoo.co.jp | C5: 45877.814 | E5: akikoko0110@yahoo.co.jp | F5: =_xlfn.XLOOKUP(E5,B:B,C:C) -> 45877.814 | I5: fujiwara.katsuya@gmail.com | J5: 45884.796 | L5: fujiwara.katsuya@gmail.com | M5: =_xlfn.XLOOKUP(L5,I:I,J:J) -> 45884.796 | P5: take.mas1969@gmail.com | Q5: 45885.816 | S5: take.mas1969@gmail.com | T5: =_xlfn.XLOOKUP(S5,P:P,Q:Q) -> 45885.816
B6: y.itagaki0528@gmail.com | C6: 45877.814 | E6: y.itagaki0528@gmail.com | F6: =_xlfn.XLOOKUP(E6,B:B,C:C) -> 45877.814 | I6: mymtystk@gmail.com | J6: 45884.796 | L6: mymtystk@gmail.com | M6: =_xlfn.XLOOKUP(L6,I:I,J:J) -> 45884.796 | P6: 99jastnet@gmail.com | Q6: 45885.816 | S6: 99jastnet@gmail.com | T6: =_xlfn.XLOOKUP(S6,P:P,Q:Q) -> 45885.816
B7: bellevie3253@gmail.com | C7: 45877.814 | E7: bellevie3253@gmail.com | F7: =_xlfn.XLOOKUP(E7,B:B,C:C) -> 45877.814 | I7: nao394d@gmail.com | J7: 45884.796 | L7: nao394d@gmail.com | M7: =_xlfn.XLOOKUP(L7,I:I,J:J) -> 45884.796 | P7: daisuke0776@gmail.com | Q7: 45885.816 | S7: daisuke0776@gmail.com | T7: =_xlfn.XLOOKUP(S7,P:P,Q:Q) -> 45885.816
B8: hiroshi.fujinawa@gmail.com | C8: 45877.814 | E8: hiroshi.fujinawa@gmail.com | F8: =_xlfn.XLOOKUP(E8,B:B,C:C) -> 45877.814 | I8: shizumemakiko@gmail.com | J8: 45884.798 | L8: shizumemakiko@gmail.com | M8: =_xlfn.XLOOKUP(L8,I:I,J:J) -> 45884.798 | P8: mymtystk@gmail.com | Q8: 45885.817 | S8: mymtystk@gmail.com | T8: =_xlfn.XLOOKUP(S8,P:P,Q:Q) -> 45885.817
B9: hiroya_95@yahoo.co.jp | C9: 45877.814 | E9: hiroya_95@yahoo.co.jp | F9: =_xlfn.XLOOKUP(E9,B:B,C:C) -> 45877.814 | I9: mmizuma@gmail.com | J9: 45884.8 | L9: mmizuma@gmail.com | M9: =_xlfn.XLOOKUP(L9,I:I,J:J) -> 45884.8 | P9: smile.jack317@docomo.ne.jp | Q9: 45885.819 | S9: smile.jack317@docomo.ne.jp | T9: =_xlfn.XLOOKUP(S9,P:P,Q:Q) -> 45885.819
B10: shoko2221@gmail.com | C10: 45877.814 | E10: shoko2221@gmail.com | F10: =_xlfn.XLOOKUP(E10,B:B,C:C) -> 45877.814 | I10: millenniumstar8@gmail.com | J10: 45884.802 | L10: millenniumstar8@gmail.com | M10: =_xlfn.XLOOKUP(L10,I:I,J:J) -> 45884.802 | P10: yamasaki.4s@icloud.com | Q10: 45885.821 | S10: yamasaki.4s@icloud.com | T10: =_xlfn.XLOOKUP(S10,P:P,Q:Q) -> 45885.821
B11: toshiki.1120.sawahata@gmail.com | C11: 45877.814 | E11: toshiki.1120.sawahata@gmail.com | F11: =_xlfn.XLOOKUP(E11,B:B,C:C) -> 45877.814 | I11: yamayu0462@gmail.com | J11: 45884.802 | L11: yamayu0462@gmail.com | M11: =_xlfn.XLOOKUP(L11,I:I,J:J) -> 45884.802 | P11: adachi.yoshinaga.4241@gmail.com | Q11: 45885.824 | S11: adachi.yoshinaga.4241@gmail.com | T11: =_xlfn.XLOOKUP(S11,P:P,Q:Q) -> 45885.824
B12: kenyoshioka888@gmail.com | C12: 45877.814 | E12: kenyoshioka888@gmail.com | F12: =_xlfn.XLOOKUP(E12,B:B,C:C) -> 45877.814 | I12: smile.jack317@docomo.ne.jp | J12: 45884.803 | L12: smile.jack317@docomo.ne.jp | M12: =_xlfn.XLOOKUP(L12,I:I,J:J) -> 45884.803 | P12: millenniumstar8@gmail.com | Q12: 45885.825 | S12: millenniumstar8@gmail.com | T12: =_xlfn.XLOOKUP(S12,P:P,Q:Q) -> 45885.825
B13: mmizuma@gmail.com | C13: 45877.814 | E13: mmizuma@gmail.com | F13: =_xlfn.XLOOKUP(E13,B:B,C:C) -> 45877.814 | I13: s.takeda000@icloud.com | J13: 45884.805 | L13: s.takeda000@icloud.com | M13: =_xlfn.XLOOKUP(L13,I:I,J:J) -> 45884.805 | P13: kmd249yamaji@gmail.com | Q13: 45885.826 | S13: kmd249yamaji@gmail.com | T13: =_xlfn.XLOOKUP(S13,P:P,Q:Q) -> 45885.826
B14: okudera.mit@gmail.com | C14: 45877.815 | E14: okudera.mit@gmail.com | F14: =_xlfn.XLOOKUP(E14,B:B,C:C) -> 45877.815 | I14: ganbamonta@gmail.com | J14: 45884.805 | L14: ganbamonta@gmail.com | M14: =_xlfn.XLOOKUP(L14,I:I,J:J) -> 45884.805 | P14: 39@aramaa.net | Q14: 45885.826 | S14: 39@aramaa.net | T14: =_xlfn.XLOOKUP(S14,P:P,Q:Q) -> 45885.826
B15: y6649851@gmail.com | C15: 45877.815 | E15: y6649851@gmail.com | F15: =_xlfn.XLOOKUP(E15,B:B,C:C) -> 45877.815 | I15: heckel371@yahoo.co.jp | J15: 45884.807 | L15: heckel371@yahoo.co.jp | M15: =_xlfn.XLOOKUP(L15,I:I,J:J) -> 45884.807 | P15: tkiku62@gmail.com | Q15: 45885.827 | S15: tkiku62@gmail.com | T15: =_xlfn.XLOOKUP(S15,P:P,Q:Q) -> 45885.827
... B369: miuratomoya@ymail.ne.jp | C369: 45881.41 | E369: 467tombi@gmail.com | F369: =_xlfn.XLOOKUP(E369,B:B,C:C) -> 45881.429 | I369: welcome4524@yahoo.co.jp | J369: 45945.643 | L369: yjomr.0619@gmail.com | M369: =_xlfn.XLOOKUP(L369,I:I,J:J) -> 45950.87 | P369: masakiyokyoumisa@ozzio.jp | Q369: 46013.122 | S369: takec3.1824@gmail.com | T369: =_xlfn.XLOOKUP(S369,P:P,Q:Q) -> 46038.849
B370: 467tombi@gmail.com | C370: 45881.429 | E370: masamikrt82@gmail.com | F370: =_xlfn.XLOOKUP(E370,B:B,C:C) -> 45881.44 | I370: a.mizoguchi.hyg@gmail.com | J370: 45945.739 | L370: u3w1qz2ni12bbyb2f2mb@rakumail.jp | M370: =_xlfn.XLOOKUP(L370,I:I,J:J) -> 45950.966 | P370: sanssjp006@gmail.com | Q370: 46013.923
B371: masamikrt82@gmail.com | C371: 45881.44 | E371: Akiko1k@hotmail.com | F371: =_xlfn.XLOOKUP(E371,B:B,C:C) -> 45881.463 | I371: zippopo510@gmail.com | J371: 45945.771 | L371: osushi.karma@gmail.com | M371: =_xlfn.XLOOKUP(L371,I:I,J:J) -> 45951.133 | P371: kinoshita.oka@gmail.com | Q371: 46013.95
B372: Akiko1k@hotmail.com | C372: 45881.463 | E372: hiromi0701suzu@gmail.com | F372: =_xlfn.XLOOKUP(E372,B:B,C:C) -> 45881.472 | I372: fujisanfujisanfujisan@gmail.com | J372: 45945.836 | L372: jamaica-reggae-kanchan-0701@docomo.ne.jp | M372: =_xlfn.XLOOKUP(L372,I:I,J:J) -> 45951.378 | P372: sena.k1017@icloud.com | Q372: 46014.653
B373: hiromi0701suzu@gmail.com | C373: 45881.472 | E373: yuki.kawamura0707@gmail.com | F373: =_xlfn.XLOOKUP(E373,B:B,C:C) -> 45881.477 | I373: nariaki.tada@icloud.com | J373: 45945.866 | L373: nobuaki24@yahoo.ne.jp | M373: =_xlfn.XLOOKUP(L373,I:I,J:J) -> 45951.634 | P373: ohtsuka@spre-ad.co.jp | Q373: 46015.587
B374: yuki.kawamura0707@gmail.com | C374: 45881.477 | E374: mase.mase.masse@gmail.com | F374: =_xlfn.XLOOKUP(E374,B:B,C:C) -> 45881.484 | I374: changeon9@gmail.com | J374: 45945.952 | L374: shinya_okada66@yahoo.co.jp | M374: =_xlfn.XLOOKUP(L374,I:I,J:J) -> 45951.927 | P374: avs0522@gmail.com | Q374: 46015.943
B375: mase.mase.masse@gmail.com | C375: 45881.484 | E375: soukon555@gmail.com | F375: =_xlfn.XLOOKUP(E375,B:B,C:C) -> 45881.514 | I375: kuge2311@yahoo.co.jp | J375: 45945.995 | L375: karintou3224@gmail.com | M375: =_xlfn.XLOOKUP(L375,I:I,J:J) -> 45951.957 | P375: w2022128124w@icloud.com | Q375: 46016.335
B376: soukon555@gmail.com | C376: 45881.514 | E376: asao3313@gmail.com | F376: =_xlfn.XLOOKUP(E376,B:B,C:C) -> 45881.588 | I376: dsswingart@gmail.com | J376: 45946.069 | L376: goindia2025@hotmail.com | M376: =_xlfn.XLOOKUP(L376,I:I,J:J) -> 45952.683 | P376: akira.4537@gmail.com | Q376: 46019.525
B377: asao3313@gmail.com | C377: 45881.588 | E377: kibune27@yahoo.co.jp | F377: =_xlfn.XLOOKUP(E377,B:B,C:C) -> 45881.688 | I377: active2526@yahoo.co.jp | J377: 45946.36 | L377: gimii0620@gmail.com | M377: =_xlfn.XLOOKUP(L377,I:I,J:J) -> 45953.859 | P377: laneige1221@gmail.com | Q377: 46020.23
B378: kibune27@yahoo.co.jp | C378: 45881.688 | E378: skyworudwairudo@gmail.com | F378: =_xlfn.XLOOKUP(E378,B:B,C:C) -> 45881.703 | I378: airiharuhi@hotmail.com | J378: 45946.404 | L378: nyanta.jyajya@gmail.com | M378: =_xlfn.XLOOKUP(L378,I:I,J:J) -> 45953.929 | P378: karua1229@yahoo.co.jp | Q378: 46023.986
B379: skyworudwairudo@gmail.com | C379: 45881.703 | E379: shiratori358@gmail.com | F379: =_xlfn.XLOOKUP(E379,B:B,C:C) -> 45881.713 | I379: monkiti369@gmail.com | J379: 45946.515 | L379: kuro7096@okinawa.li | M379: =_xlfn.XLOOKUP(L379,I:I,J:J) -> 45953.967 | P379: youko405xx@gmail.com | Q379: 46025.958
B380: shiratori358@gmail.com | C380: 45881.713 | E380: wakatosa@yahoo.co.jp | F380: =_xlfn.XLOOKUP(E380,B:B,C:C) -> 45881.769 | I380: shinosjapan@yahoo.co.jp | J380: 45946.632 | L380: crptufnf@gmail.com | M380: =_xlfn.XLOOKUP(L380,I:I,J:J) -> 45953.999 | P380: goodfeeling.goodtiming@gmail.com | Q380: 46026.921
B381: wakatosa@yahoo.co.jp | C381: 45881.769 | E381: toto.oku19@outlook.jp | F381: =_xlfn.XLOOKUP(E381,B:B,C:C) -> 45881.798 | I381: masaki29601119@icloud.com | J381: 45946.829 | L381: wbr81kei@gmail.com | M381: =_xlfn.XLOOKUP(L381,I:I,J:J) -> 45954.329 | P381: a.mizoguchi.hyg@gmail.com | Q381: 46027.377
... B391: steelkan900517@gmail.com | C391: 45882.327 | E391: seminar@sevencolorsdream.com | F391: =_xlfn.XLOOKUP(E391,B:B,C:C) -> 45882.331 | I391: dsswingart@gmail.com | J391: 45947.927 | L391: s52ck93bb14t@kpa.biglobe.ne.jp | M391: =_xlfn.XLOOKUP(L391,I:I,J:J) -> 45957.571 | P391: takec3.1824@gmail.com | Q391: 46038.849
B392: seminar@sevencolorsdream.com | C392: 45882.331 | E392: toshiya3.soso@gmail.com | F392: =_xlfn.XLOOKUP(E392,B:B,C:C) -> 45882.831 | I392: Yumikomuramatsu1957@gmail.com | J392: 45948.824 | L392: risa1031@hotmail.com | M392: =_xlfn.XLOOKUP(L392,I:I,J:J) -> 45957.751
B393: toshiya3.soso@gmail.com | C393: 45882.831 | E393: kawasenoimaaki@yahoo.co.jp | F393: =_xlfn.XLOOKUP(E393,B:B,C:C) -> 45882.915 | I393: asp5247@yahoo.co.jp | J393: 45948.885 | L393: et.0408@docomo.ne.jp | M393: =_xlfn.XLOOKUP(L393,I:I,J:J) -> 45959.933
B394: kawasenoimaaki@yahoo.co.jp | C394: 45882.915 | E394: yk.ogawa0313@gmail.com | F394: =_xlfn.XLOOKUP(E394,B:B,C:C) -> 45883.199 | I394: r0y9o1w9sk@gmail.com | J394: 45948.891 | L394: l.grazie.naga@gmail.com | M394: =_xlfn.XLOOKUP(L394,I:I,J:J) -> 45960.03
B395: yk.ogawa0313@gmail.com | C395: 45883.199 | E395: wbr81kei@gmail.com | F395: =_xlfn.XLOOKUP(E395,B:B,C:C) -> 45883.635 | I395: dsswingart@gmail.com | J395: 45948.905 | L395: colorscheme.1215@gmail.com | M395: =_xlfn.XLOOKUP(L395,I:I,J:J) -> 45960.062
B396: wbr81kei@gmail.com | C396: 45883.635 | E396: n_88_grow@yahoo.co.jp | F396: =_xlfn.XLOOKUP(E396,B:B,C:C) -> 45883.803 | I396: miekodaisuki@gmail.com | J396: 45948.92 | L396: wpjp358@gmail.com | M396: =_xlfn.XLOOKUP(L396,I:I,J:J) -> 45960.178
B397: n_88_grow@yahoo.co.jp | C397: 45883.803 | E397: tymahalo8@gmail.com | F397: =_xlfn.XLOOKUP(E397,B:B,C:C) -> 45883.805 | I397: syamunekokubo@gmail.com | J397: 45948.986 | L397: seaman1192kiki@yahoo.co.jp | M397: =_xlfn.XLOOKUP(L397,I:I,J:J) -> 45960.499
B398: tymahalo8@gmail.com | C398: 45883.805 | E398: ken964fu@ezweb.ne.jp | F398: =_xlfn.XLOOKUP(E398,B:B,C:C) -> 45884.793 | I398: izumikawa0925@gmail.com | J398: 45949.029 | L398: swimming5150@gmail.com | M398: =_xlfn.XLOOKUP(L398,I:I,J:J) -> 45960.607
B399: ken964fu@ezweb.ne.jp | C399: 45884.793 | E399: minalf102263@gmail.com | F399: =_xlfn.XLOOKUP(E399,B:B,C:C) -> 45884.805 | I399: marrokuu11@gmail.com | J399: 45949.105 | L399: kkkeita_dayo@yahoo.co.jp | M399: =_xlfn.XLOOKUP(L399,I:I,J:J) -> 45960.872
B400: minalf102263@gmail.com | C400: 45884.805 | E400: yoshitakaoshima@gmail.com | F400: =_xlfn.XLOOKUP(E400,B:B,C:C) -> 45885.561 | I400: yukakunichika@yahoo.co.jp | J400: 45949.442 | L400: pcat6270@gmai,com | M400: =_xlfn.XLOOKUP(L400,I:I,J:J) -> 45961.477
B401: yoshitakaoshima@gmail.com | C401: 45885.561 | E401: takahiro.9.8.yamato@gmail.com | F401: =_xlfn.XLOOKUP(E401,B:B,C:C) -> 45885.848 | I401: fujihama.194@gmail.com | J401: 45949.444 | L401: kan.sentimental53@i.softbank.jp | M401: =_xlfn.XLOOKUP(L401,I:I,J:J) -> 45962.737
B402: takahiro.9.8.yamato@gmail.com | C402: 45885.848 | E402: gfm100taka@gmail.com | F402: =_xlfn.XLOOKUP(E402,B:B,C:C) -> 45885.854 | I402: asukachan0718@yahoo.co.jp | J402: 45949.562 | L402: cocoe0505@gmail.com | M402: =_xlfn.XLOOKUP(L402,I:I,J:J) -> 45963.753
B403: gfm100taka@gmail.com | C403: 45885.854 | E403: hatanotoshi@yahoo.co.jp | F403: =_xlfn.XLOOKUP(E403,B:B,C:C) -> 45885.92 | I403: okiraku8848@yahoo.co.jp | J403: 45949.657 | L403: yamada@ikkoo.info | M403: =_xlfn.XLOOKUP(L403,I:I,J:J) -> 45964.863
... B519: hdsb4386@gmail.com | C519: 45890.703 | E519: hiromarukye88@gmail.com | F519: =_xlfn.XLOOKUP(E519,B:B,C:C) -> 45891.639 | I519: shishiku2741@gmail.com | J519: 45990.961 | L519: rn010240@gmail.com | M519: =_xlfn.XLOOKUP(L519,I:I,J:J) -> 45887.863
B520: makoto0914azuma@yahoo.co.jp | C520: 45890.747 | E520: necogang@icloud.com | F520: =_xlfn.XLOOKUP(E520,B:B,C:C) -> 45891.795 | I520: dc433345_216_2@icloud.com | J520: 45991.933
B521: bagzy.1133@dccomo.ne.jp | C521: 45890.756 | E521: kazumikura@icloud.com | F521: =_xlfn.XLOOKUP(E521,B:B,C:C) -> 45891.824 | I521: discovery7247@gmail.com | J521: 45992.295
B522: bagzy.1133@dccomo.ne.jp | C522: 45890.758 | E522: chie240@gmail.com | F522: =_xlfn.XLOOKUP(E522,B:B,C:C) -> 45891.944 | I522: ahaba.300@gmail.com | J522: 45993.854
B523: bagzy.1133@dccomo.ne.jp | C523: 45890.76 | E523: mmck5749@gmail.com | F523: =_xlfn.XLOOKUP(E523,B:B,C:C) -> 45891.961 | I523: eririn2025@gmail.com | J523: 45994.118
B524: shu511119@gmail.com | C524: 45890.769 | E524: jun26-@ezweb.ne.jp | F524: =_xlfn.XLOOKUP(E524,B:B,C:C) -> 45891.971 | I524: reviewuser@yahoo.co.jp | J524: 45994.634
B525: nariaki.tada@icloud.com | C525: 45890.783 | E525: no.1hostda@gmail.com | F525: =_xlfn.XLOOKUP(E525,B:B,C:C) -> 45892.129 | I525: cocoweb50@gmail.com | J525: 45994.977
B526: gogatu1001@gmail.com | C526: 45891.039 | E526: koji0413m52@gmail.com | F526: =_xlfn.XLOOKUP(E526,B:B,C:C) -> 45892.258 | I526: seaman1192kiki@yahoo.co.jp | J526: 45995.099
B527: soma1021kusaba@gmail.com | C527: 45891.04 | E527: s.kondo@hotmail.com | F527: =_xlfn.XLOOKUP(E527,B:B,C:C) -> 45892.348 | I527: seaman1192kiki@yahoo.co.jp | J527: 45995.521
B528: seoritsuhime7@gmail.com | C528: 45891.212 | E528: takayama1098@gmail.com | F528: =_xlfn.XLOOKUP(E528,B:B,C:C) -> 45892.457 | I528: ahrm26912@gmail.com | J528: 45995.854
B529: jun.k17@icloud.com | C529: 45891.258 | E529: fumigakusyu@gmail.com | F529: =_xlfn.XLOOKUP(E529,B:B,C:C) -> 45892.459 | I529: laneige1221@gmail.com | J529: 45999.809
B530: dtw45068@gmail.com | C530: 45891.327 | E530: drsaka36@gmail.com | F530: =_xlfn.XLOOKUP(E530,B:B,C:C) -> 45892.478 | I530: avs0522@gmail.com | J530: 46000.767
B531: makkytomochan@icloud.com | C531: 45891.348 | E531: satou.bogii@gmail.com | F531: =_xlfn.XLOOKUP(E531,B:B,C:C) -> 45892.484 | I531: kitakan09@gmail.com | J531: 46000.893
... B753: y1020h0102@icloud.com | C753: 45910.736 | E753: aichikennniwagunn@yahoo.co.jp | F753: =_xlfn.XLOOKUP(E753,B:B,C:C) -> 45913.979 | I753: bc.usanou.358@gmail.com | J753: 45887.984
B754: mystery.of.wolf-1978@docomo.ne.jp | C754: 45910.747 | E754: nabe3582@gmail.com | F754: =_xlfn.XLOOKUP(E754,B:B,C:C) -> 45914.011
B755: rinotsumi1551@gmail.com | C755: 45910.816 | E755: moto77@ymail.be.jp | F755: =_xlfn.XLOOKUP(E755,B:B,C:C) -> 45914.052
B756: mizueotomo@yahoo.co.jp | C756: 45910.837 | E756: yuki2453@yahoo.co.jp | F756: =_xlfn.XLOOKUP(E756,B:B,C:C) -> 45914.077
B757: bhm35661@biglobe.ne.jp | C757: 45910.855 | E757: atsukobluebird@gmail.com | F757: =_xlfn.XLOOKUP(E757,B:B,C:C) -> 45914.112
B758: karintou230@gmail.com | C758: 45910.984 | E758: gold.6675@outlook.jp | F758: =_xlfn.XLOOKUP(E758,B:B,C:C) -> 45914.19
B759: aikawasadao1@gmail.com | C759: 45911.001 | E759: harem0013@yahoo.co.jp | F759: =_xlfn.XLOOKUP(E759,B:B,C:C) -> 45914.252
B760: acotarou@icloud.com | C760: 45911.077 | E760: shushushu77jp@yahoo.co.jp | F760: =_xlfn.XLOOKUP(E760,B:B,C:C) -> 45914.258
B761: shimacyoro@yahoo.co.jp | C761: 45911.267 | E761: yuiop2006@yahoo.co.jp | F761: =_xlfn.XLOOKUP(E761,B:B,C:C) -> 45914.326
B762: good.memory2004@gmail.com | C762: 45911.312 | E762: maezatoman421@gmail.com | F762: =_xlfn.XLOOKUP(E762,B:B,C:C) -> 45914.355
B763: laala.sunny@gmail.com | C763: 45911.375 | E763: moderation.to@gmail.com | F763: =_xlfn.XLOOKUP(E763,B:B,C:C) -> 45914.392
B764: aikafd7@yahoo.co.jp | C764: 45911.425 | E764: ambiru@me.com | F764: =_xlfn.XLOOKUP(E764,B:B,C:C) -> 45914.394
B765: nori648@gmail.com | C765: 45911.491 | E765: facata0807@outlook.jp | F765: =_xlfn.XLOOKUP(E765,B:B,C:C) -> 45914.444
... B1807: riku365bb@gmail.com | C1807: 45969.527 | E1807: sadamasa0119@gmail.com | F1807: =_xlfn.XLOOKUP(E1807,B:B,C:C) -> 46043.367
B1808: mstay.goldship47@gmail.com | C1808: 45969.718
B1809: contrail.intheblue@gmail.com | C1809: 45969.759
B1810: Shigerukamata@gmail.com | C1810: 45969.918
B1811: integral2006@yahoo.co.jp | C1811: 45970.312
B1812: seiko8255@gmail.com | C1812: 45970.387
B1813: seiko8255@gmail.com | C1813: 45970.438
B1814: seiko8255@gmail.com | C1814: 45970.454
B1815: yoshida_9518@yahoo.co.jp | C1815: 45970.492
B1816: nao.igu-.1536@docomo.ne.jp | C1816: 45970.846
B1817: takamatsu2608@gmail.com | C1817: 45970.919
B1818: hagi160160@gmail.com | C1818: 45970.969
B1819: mekealoha131@yahoo.co.jp | C1819: 45971.079
... B2213: sadamasa0119@gmail.com | C2213: 46043.367

Sheet 20258月
B2: メルマガ登録者(重複なし) | C2: 登録日時 | E2: 審査フォーム回答者(重複なし) | F2: 登録日時 | H2: 個別相談予約者(重複なし) | I2: 登録日時
B3: rn010240@gmail.com | C3: 45876.933 | E3: ty11055yoshi@gmail.com | F3: 45884.795 | H3: private@jun-otsu.com | I3: 45874.959
B4: jin.hitoshi@gmail.com | C4: 45877.814 | E4: take.mas1969@gmail.com | F4: 45884.795 | H4: w.rainey-0840@kuf.biglobe.ne.jp | I4: 45885.816
B5: akikoko0110@yahoo.co.jp | C5: 45877.814 | E5: fujiwara.katsuya@gmail.com | F5: 45884.796 | H5: take.mas1969@gmail.com | I5: 45885.816
B6: y.itagaki0528@gmail.com | C6: 45877.814 | E6: mymtystk@gmail.com | F6: 45884.796 | H6: 99jastnet@gmail.com | I6: 45885.816
B7: bellevie3253@gmail.com | C7: 45877.814 | E7: nao394d@gmail.com | F7: 45884.796 | H7: daisuke0776@gmail.com | I7: 45885.816
B8: hiroshi.fujinawa@gmail.com | C8: 45877.814 | E8: shizumemakiko@gmail.com | F8: 45884.798 | H8: mymtystk@gmail.com | I8: 45885.817
B9: hiroya_95@yahoo.co.jp | C9: 45877.814 | E9: mmizuma@gmail.com | F9: 45884.8 | H9: smile.jack317@docomo.ne.jp | I9: 45885.819
B10: shoko2221@gmail.com | C10: 45877.814 | E10: millenniumstar8@gmail.com | F10: 45884.802 | H10: yamasaki.4s@icloud.com | I10: 45885.821
B11: toshiki.1120.sawahata@gmail.com | C11: 45877.814 | E11: yamayu0462@gmail.com | F11: 45884.802 | H11: adachi.yoshinaga.4241@gmail.com | I11: 45885.824
B12: kenyoshioka888@gmail.com | C12: 45877.814 | E12: smile.jack317@docomo.ne.jp | F12: 45884.803 | H12: millenniumstar8@gmail.com | I12: 45885.825
B13: mmizuma@gmail.com | C13: 45877.814 | E13: s.takeda000@icloud.com | F13: 45884.805 | H13: kmd249yamaji@gmail.com | I13: 45885.826
B14: okudera.mit@gmail.com | C14: 45877.815 | E14: ganbamonta@gmail.com | F14: 45884.805 | H14: 39@aramaa.net | I14: 45885.826
... B142: yakisobapan0083@gmail.com | C142: 45878.299 | E142: kawanokaiji0412@yahoo.co.jp | F142: 45890.797 | H142: yuuzouka@yahoo.co.jp | I142: 45899.976
B143: shigetaka0427@gmail.com | C143: 45878.301 | E143: uusamat2018@gmail.com | F143: 45890.872
B144: dreamopen0001@gmail.com | C144: 45878.308 | E144: k.masashi.5520@gmail.com | F144: 45891.02
B145: ssfrst77@gmail.com | C145: 45878.313 | E145: cosmic4c@gmail.com | F145: 45891.429
B146: 0609maikumaiku@gmail.com | C146: 45878.317 | E146: kaminade@gmail.com | F146: 45891.599
B147: paribmw369@gmail.com | C147: 45878.322 | E147: yuuzouka@yahoo.co.jp | F147: 45891.662
B148: asatokj1202@gmail.com | C148: 45878.326 | E148: aoanela.aloha@gmail.com | F148: 45891.747
B149: yamayu0462@gmail.com | C149: 45878.348 | E149: kyonbokun0509@gmail.com | F149: 45893.017
B150: hagi425872@gmail.com | C150: 45878.349 | E150: koujimukasa@gmail.com | F150: 45893.923
B151: keigokawano5@gmail.com | C151: 45878.357 | E151: taichirokubo1@gmail.com | F151: 45893.927
B152: 99jastnet@gmail.com | C152: 45878.364 | E152: hdakzk@gmail.com | F152: 45894.008
B153: sato.mercari@gmail.com | C153: 45878.38 | E153: kolwiin55@gmail.com | F153: 45894.12
B154: 39@aramaa.net | C154: 45878.394 | E154: bhxjp197@gmail.com | F154: 45894.736
... B176: everyhappy358@gmail.com | C176: 45878.821 | E176: rn010240@gmail.com | F176: 45887.863
B177: ykowaki430@gmail.com | C177: 45878.826
B178: lagoon3629@gmail.com | C178: 45878.829
B179: 1907suganuma@gmail.com | C179: 45878.836
B180: ss250zukka@gmail.com | C180: 45878.836
B181: ms.9941@icloud.com | C181: 45878.836
B182: toyaman23-2525@docomo.ne.jp | C182: 45878.837
B183: klein_arc@yahoo.co.jp | C183: 45878.837
B184: yagutaka0927@gmail.com | C184: 45878.837
B185: tiko40tyan@gmail.com | C185: 45878.838
B186: valx347@gmail.com | C186: 45878.838
B187: ktkhs106@gmail.com | C187: 45878.838
B188: kou0494@gmail.com | C188: 45878.839
... B632: hjctf875@yahoo.co.jp | C632: 45900.942

Sheet 20259月
B2: メルマガ登録者(重複なし) | C2: 登録日時 | E2: 審査フォーム回答者(重複なし) | F2: 登録日時 | H2: 個別相談予約者(重複なし) | I2: 登録日時
B3: saeko-nishi168@nifty.com | C3: 45901.148 | E3: saeko-nishi168@nifty.com | F3: 45901.152 | H3: saeko-nishi168@nifty.com | I3: 45902.82
B4: trendfollower2013@gmail.com | C4: 45901.331 | E4: sakuboo85@gmail.com | F4: 45901.276 | H4: okada@nkeg.net | I4: 45901.603
B5: babibubeboddha@gmail.com | C5: 45901.339 | E5: emi.emi.honey@gmail.com | F5: 45901.925 | H5: harumir7@gmail.com | I5: 45901.797
B6: naopn.shiga.6619@gmail.com | C6: 45901.348 | E6: hi_standard_a_i_m_h_stay_gold@yahoo.co.jp | F6: 45902.061 | H6: hypocrite5843@gmail.com | I6: 45901.816
B7: arina.wada1@gmail.com | C7: 45901.401 | E7: hayato39ok@gmail.com | F7: 45902.768 | H7: kefu051204@outlook.jp | I7: 45902.596
B8: info@fishingclub.info | C8: 45901.475 | E8: yoshiro19801225@gmail.com | F8: 45903.985 | H8: emi.emi.honey@gmail.com | I8: 45902.883
B9: gypsy.666t@gmail.com | C9: 45901.492 | E9: armando.tomigusuku@gmail.com | F9: 45904.314 | H9: ken964fu@ezweb.ne.jp | I9: 45903.875
B10: katokatsu333@gmail.com | C10: 45901.523 | E10: hatamori_h@yahoo.co.jp | F10: 45904.82 | H10: miguel.akira.ota@gmail.com | I10: 45904.316
B11: kamikaze@sun.gmobb.jp | C11: 45901.596 | E11: nasutomato93@gmail.com | F11: 45904.927 | H11: yoshiro19801225@gmail.com | I11: 45904.888
B12: mtrskb4010@yahoo.co.jp | C12: 45901.745 | E12: mmyo.ja.akiko@gmail.com | F12: 45904.928 | H12: takuya.tsukada@icloud.com | I12: 45904.901
B13: kikit39@icloud.com | C13: 45901.856 | E13: hitomimakeup0130@icloud.com | F13: 45906.53 | H13: sakuboo85@gmail.con | I13: 45904.906
B14: tanioku.kazuo.4.8@gmail.com | C14: 45901.896 | E14: tomiguma@gmail.com | F14: 45906.807 | H14: hitomimakeup0130@icloud.com | I14: 45906.617
... B60: tutankhamen7656@gmail.com | C60: 45907.418 | E60: chaco.0114.sato@gmail.com | F60: 45929.73 | H60: kibishimodaira7306@gmail.com | I60: 45930.75
B61: koufuk0322@gmail.com | C61: 45907.445 | E61: kibishimodaira7306@gmail.com | F61: 45929.983
B62: konmaniwa725@gmail.com | C62: 45907.591 | E62: c.s7mybnesy61@gmail.com | F62: 45930.165
B63: kazoo529@gmail.com | C63: 45907.658 | E63: oreore.orz48@gmail.com | F63: 45930.932
B64: g4u373@gmail.com | C64: 45907.789
B65: yu.21_bad.endoftime@icloud.com | C65: 45907.843
B66: harley88088@yahoo.co.jp | C66: 45907.931
B67: takakoba30162@gmail.com | C67: 45907.936
B68: etakako21@yahoo.co.jp | C68: 45907.961
B69: skyhigh_tanney@yahoo.co.jp | C69: 45907.962
B70: genelsbass@gmail.com | C70: 45908.301
B71: arigatougozaimasu3byakumanben@gmail.com | C71: 45908.418
B72: tu19661121@gmail.com | C72: 45908.448
B73: kikurinn@yahoo.co.jp | C73: 45908.458
B74: legare.ueda@gmail.com | C74: 45908.58
B75: copymikako@gmail.com | C75: 45908.839
... B273: fromyuu2525@gmail.com | C273: 45930.963

Sheet 202510月
B2: メルマガ登録者(重複なし) | C2: 登録日時 | E2: 審査フォーム回答者(重複なし) | F2: 登録日時 | H2: 個別相談予約者(重複なし) | I2: 登録日時
B3: murakamijapon@gmail.com | C3: 45931.016 | E3: d.1986.com@gmail.com | F3: 45931.095 | H3: d.1986.com@gmail.com | I3: 45931.383
B4: aloha808hi@gmail.com | C4: 45931.045 | E4: kawatatsu52gg@gmail.com | F4: 45931.316 | H4: kawatatsu52gg@gmail.com | I4: 45931.473
B5: d.1986.com@gmail.com | C5: 45931.094 | E5: mitsunori1105ken@gmail.com | F5: 45931.407 | H5: mitz.ken.0826@yahoo.ne.jp | I5: 45931.506
B6: 1959hiroaki5963@gmail.com | C6: 45931.23 | E6: mitz.ken.0826@yahoo.ne.jp | F6: 45931.419 | H6: oreore.orz48@gmail.com | I6: 45931.575
B7: kawatatsu52gg@gmail.com | C7: 45931.309 | E7: rukou.ryukou@gmail.com | F7: 45931.691 | H7: rukou.ryukou@gmail.com | I7: 45931.803
B8: kubotada1122@gmail.com | C8: 45931.31 | E8: d9control@gmail.com | F8: 45931.778 | H8: morimori19720216@gmail.com | I8: 45932.91
B9: mitz.ken.0826@yahoo.ne.jp | C9: 45931.337 | E9: kawaihideharu55@gmail.com | F9: 45931.844 | H9: hukushima112028@gmail.com | I9: 45933.359
B10: kasadakai@gmail.com | C10: 45931.347 | E10: xoxo75tkd@yahoo.co.jp | F10: 45931.97 | H10: advance4world@gmail.com | I10: 45933.445
B11: hiroshi.sriracha@gmail.com | C11: 45931.373 | E11: morimori19720216@gmail.com | F11: 45932.28 | H11: ryutahirakawa@gmail.com | I11: 45933.447
B12: okachikaka@gmail.com | C12: 45931.389 | E12: 269fuku29niko25369@gmail.com | F12: 45932.546 | H12: supremus8880@gmail.com | I12: 45933.505
B13: tanemame@gmail.com | C13: 45931.39 | E13: smotokun0129@gmail.com | F13: 45932.551 | H13: marbow.mh@gmail.com | I13: 45933.772
B14: ndnz1045@gmail.com | C14: 45931.39 | E14: advance4world@gmail.com | F14: 45932.555 | H14: tomoya.773.235@gmail.com | I14: 45933.869
... B96: hiromax2022@gmail.com | C96: 45935.247 | E96: welcome4524@yahoo.co.jp | F96: 45945.643 | H96: seaman1192kiki@yahoo.co.jp | I96: 45961.848
B97: maeshima50@gmail.com | C97: 45935.298 | E97: a.mizoguchi.hyg@gmail.com | F97: 45945.739
B98: aamendokusei@gmail.com | C98: 45935.325 | E98: zippopo510@gmail.com | F98: 45945.771
B99: proton1130@gmail.com | C99: 45935.424 | E99: fujisanfujisanfujisan@gmail.com | F99: 45945.836
B100: hiromasa.m44@gmail.com | C100: 45935.443 | E100: nariaki.tada@icloud.com | F100: 45945.866
B101: samu3212@gmail.com | C101: 45935.445 | E101: changeon9@gmail.com | F101: 45945.952
B102: loveless8888@gmail.com | C102: 45935.522 | E102: kuge2311@yahoo.co.jp | F102: 45945.995
B103: inadom358@icloud.com | C103: 45935.546 | E103: dsswingart@gmail.com | F103: 45946.069
B104: mr.freelance011724@gmail.com | C104: 45935.548 | E104: active2526@yahoo.co.jp | F104: 45946.36
B105: yukiafrica@gmail.com | C105: 45935.581 | E105: airiharuhi@hotmail.com | F105: 45946.404
B106: yuka.pc.ado@gmail.com | C106: 45935.61 | E106: monkiti369@gmail.com | F106: 45946.515
B107: ricorico.060721@gmail.com | C107: 45935.642 | E107: shinosjapan@yahoo.co.jp | F107: 45946.632
B108: chi29510824@yahoo.co.jp | C108: 45935.795 | E108: masaki29601119@icloud.com | F108: 45946.829
... B166: pobbytodingan214@yahoo.co.jp | C166: 45939.163 | E166: pcat6270@gmai,com | F166: 45961.477
B167: got-11042012@i.softbank.jp | C167: 45939.214
B168: takahashi588@gmail.com | C168: 45939.243
B169: lovemiki43@gmail.com | C169: 45939.317
B170: jan5572001@yahoo.com.jp | C170: 45939.338
B171: mokohorii@yahoo.co.jp | C171: 45939.34
B172: osushi.karma@gmail.com | C172: 45939.343
B173: ashomi@icloud.com | C173: 45939.358
B174: ayumi.k538@gmail.com | C174: 45939.406
B175: sunsetkk3@gmail.com | C175: 45939.452
B176: mi.yakky.peace2525@gmail.com | C176: 45939.615
B177: macuro164@gmail.com | C177: 45939.627
B178: mihokomasato@gmail.com | C178: 45939.64
... B588: wellfly.pictures@gmail.com | C588: 45961.895

Sheet 202511月
B2: メルマガ登録者(重複なし) | C2: 登録日時 | E2: 審査フォーム回答者(重複なし) | F2: 登録日時 | H2: 個別相談予約者(重複なし) | I2: 登録日時
B3: dolphin-blue-2527@ezweb.ne.jp | C3: 45962.484 | E3: kan.sentimental53@i.softbank.jp | F3: 45962.737 | H3: dsswingart@gmail.com | I3: 45962.355
B4: kan.sentimental53@i.softbank.jp | C4: 45962.733 | E4: cocoe0505@gmail.com | F4: 45963.753 | H4: r0y9o1w9sk@gmail.com | I4: 45962.38
B5: yogetjp@yahoo.co.jp | C5: 45962.993 | E5: yamada@ikkoo.info | F5: 45964.863 | H5: wgjp358@gmail.com | I5: 45962.5
B6: Shigerukamata@gmail.com | C6: 45963.371 | E6: crash4405@gmail.com | F6: 45965.257 | H6: izumikawa0925@gmail.com | I6: 45963.71
B7: hideaki_takehisa@yahoo.co.jp | C7: 45963.676 | E7: seresuta8132@yahoo.co.jp | F7: 45966.002 | H7: cocoe0505@gmail.com | I7: 45963.853
B8: hirakawa59@gmail.com | C8: 45964.819 | E8: minoharry@gmail.com | F8: 45966.567 | H8: okumanchouja358@gmail.com | I8: 45963.921
B9: kmiyamoto537@gmail.com | C9: 45964.824 | E9: sayo.momo.saku@gmail.com | F9: 45966.661 | H9: rovestory0210@yahoo.co.jp | I9: 45965.958
B10: yamada@ikkoo.info | C10: 45964.828 | E10: sdcfx72@gmail.com | F10: 45966.926 | H10: sdcfx72@gmail.com | I10: 45967.115
B11: h_takino3@yahoo.co.jp | C11: 45964.87 | E11: anna.miyu@ezweb.ne.jp | F11: 45967.067 | H11: 4080000abc@gmail.com | I11: 45967.312
B12: rsato1113@gmail.com | C12: 45964.881 | E12: yajimaen8200@gmail.com | F12: 45967.862 | H12: minoharry@gmail.com | I12: 45967.39
B13: kalitakiya0205@gmail.com | C13: 45964.915 | E13: azaz02170217@yahoo.co.jp | F13: 45968.415 | H13: anna.miyu@ezweb.ne.jp | I13: 45967.515
B14: sszk4050@gmail.com | C14: 45964.92 | E14: hagi160160@gmail.com | F14: 45969.469 | H14: kotobukiclubjp@gmail.com | I14: 45969.494
... B35: tomomi_kujp@yahoo.co.jp | C35: 45968.306 | E35: firstman817@gmail.com | F35: 45979.51 | H35: kajigonn18@yahoo.co.jp | I35: 45991.344
B36: azaz02170217@yahoo.co.jp | C36: 45968.35 | E36: aa19890112@yahoo.co.jp | F36: 45979.68
B37: noaist7@gmail.com | C37: 45968.532 | E37: kajigonn18@yahoo.co.jp | F37: 45979.72
B38: hagi160160@gmail.com | C38: 45969.279 | E38: kinoshita.oka@gmail.com | F38: 45980.714
B39: muchi2p-chic_s-k@docomo.ne.jp | C39: 45969.426 | E39: ryo2good51@gmail.com | F39: 45981.377
B40: mstay.goldship47@gmail.com | C40: 45969.718 | E40: ykouzaki@ku.kumagaigumi.co.jp | F40: 45983.493
B41: contrail.intheblue@gmail.com | C41: 45969.759 | E41: umi2019.12.24@gmail.com | F41: 45983.8
B42: integral2006@yahoo.co.jp | C42: 45970.312 | E42: valx347@gmail.com | F42: 45983.841
B43: yoshida_9518@yahoo.co.jp | C43: 45970.492 | E43: yaya12250916@gmail.com | F43: 45984.137
B44: nao.igu-.1536@docomo.ne.jp | C44: 45970.846 | E44: aamms1480@gmail.com | F44: 45984.437
B45: ihouse8@icloud.com | C45: 45971.81 | E45: thomas_m.k.night@icloud.com | F45: 45984.909
B46: takasannet2005@gmail.com | C46: 45971.852 | E46: rising.life.0073@gmail.com | F46: 45984.915
B47: kamishi_jipang@yahoo.co.jp | C47: 45971.854 | E47: y_bottle_nose@hotmail.com | F47: 45985.845
... B54: gs3508899@gmail.com | C54: 45972.299 | E54: dc433345_216_2@icloud.com | F54: 45991.933
B55: manai8998@icloud.com | C55: 45972.357
B56: sekiyamatokou@icloud.com | C56: 45972.395
B57: kaz-_-428@i.softbank.jp | C57: 45972.395
B58: naoko19670516@gmail.com | C58: 45972.422
B59: mochan1118@gmail.com | C59: 45972.451
B60: sa.yama5522@gmail.com | C60: 45972.476
B61: ya.ma.san.go75@gmail.com | C61: 45972.656
B62: yyouko612@gmail.com | C62: 45972.735
B63: culin.1231@gmail.com | C63: 45972.765
B64: y_ichige@yahoo.co.jp | C64: 45972.781
B65: sana_ip13yj@yahoo.co.jp | C65: 45972.805
B66: takao.1017.0617@gmail.com | C66: 45972.808
... B155: cubay821@gmail.com | C155: 45991.935

Sheet 202512月
B2: メルマガ登録者(重複なし) | C2: 登録日時 | E2: 審査フォーム回答者(重複なし) | F2: 登録日時 | H2: 個別相談予約者(重複なし) | I2: 登録日時
B3: hikarinet2011@gmail.com | C3: 45992 | E3: discovery7247@gmail.com | F3: 45992.295 | H3: dc433345_216_2@icloud.com | I3: 45992.216
B4: nogan491@gmail.com | C4: 45992.085 | E4: ahaba.300@gmail.com | F4: 45993.854 | H4: winwinwin.egao@gmail.com | I4: 45992.761
B5: ahaba.300@gmail.com | C5: 45993.425 | E5: eririn2025@gmail.com | F5: 45994.118 | H5: pigmpooh@gmail.com | I5: 45995.466
B6: chibi91bisu1027@docomo.ne.jp | C6: 45993.721 | E6: reviewuser@yahoo.co.jp | F6: 45994.634 | H6: ahrm26912@gmail.com | I6: 45996.062
B7: tkf585855@gmail.com | C7: 45994.244 | E7: cocoweb50@gmail.com | F7: 45994.977 | H7: reviewuser@yahoo.co.jp | I7: 45996.518
B8: nre59754@gmail.com | C8: 45994.669 | E8: ahrm26912@gmail.com | F8: 45995.854 | H8: sonicbtob@gmail.com | I8: 45998.56
B9: rumi261303@gmail.com | C9: 45994.961 | E9: laneige1221@gmail.com | F9: 45999.809 | H9: kitakan09@gmail.com | I9: 46001.475
B10: cocoweb50@gmail.com | C10: 45994.975 | E10: kitakan09@gmail.com | F10: 46000.893 | H10: thomas_m.k.night@icloud.com | I10: 46001.717
B11: akihiro_1_takahashi@yahoo.co.jp | C11: 45995.227 | E11: isamu36323@gmail.com | F11: 46001.074 | H11: greenleaftwo7@gmail.com | I11: 46002.386
B12: ahrm26912@gmail.com | C12: 45995.82 | E12: subarattino@gmail.com | F12: 46001.322 | H12: info@contrail2022.com | I12: 46003.551
B13: gogatu026.01@gmail.com | C13: 45996.408 | E13: greenleaftwo7@gmail.com | F13: 46001.734 | H13: sakura.kougirou@icloud.com | I13: 46004.253
B14: hikaru414@gmail.com | C14: 45996.628 | E14: big.fishing.t.m@icloud.com | F14: 46002.754 | H14: subarattino@gmail.com | I14: 46004.403
... B32: joe.shibahara@iCloud.com | C32: 46006.026 | E32: udna224488@gmail.com | F32: 46009.912 | H32: laneige1221@gmail.com | I32: 46020.23
B33: rsg70208@gmail.com | C33: 46006.236 | E33: keichan.su.0716@gmail.com | F33: 46009.95
B34: yajimaen82000@gmail.com | C34: 46006.343 | E34: Torontolife.jp@gmail.com | F34: 46010.01
B35: hellochimi03@ymail.ne.jp | C35: 46006.359 | E35: kunitamagen0803@gmail.com | F35: 46010.368
B36: yorukiyo8@gmail.com | C36: 46006.491 | E36: miko171825@gmail.com | F36: 46010.669
B37: a7song7for7you@gmail.com | C37: 46006.509 | E37: keihiro7138@gmail.com | F37: 46011.449
B38: masato.world.7@gmail.com | C38: 46006.589 | E38: memekaibara721@gmail.com | F38: 46011.845
B39: k204149@yahoo.co.jp | C39: 46006.842 | E39: janne515@ozzio.jp | F39: 46012.584
B40: kanonpapa49@icloud.com | C40: 46007.449 | E40: satoshi.oj@gmail.com | F40: 46012.759
B41: w2022128124@gmail.com | C41: 46007.718 | E41: rmqwb771@gmail.com | F41: 46012.776
B42: amekuromk@gmail.com | C42: 46007.98 | E42: inainaemi@gmail.com | F42: 46013.05
B43: drmfs50@gmail.com | C43: 46008.294 | E43: follow_the_wind123@yahoo.co.jp | F43: 46013.273
B44: 3655hayashi884@gmail.com | C44: 46008.336 | E44: sunnys.tamada@gmail.com | F44: 46013.352
... B53: tt38mm@i.softbnk.jp | C53: 46010.627 | E53: y.tsumita@gmail.com | F53: 46019.8
B54: janne515@ozzio.jp | C54: 46010.963
B55: watanabe.naoki1111@i.softbank.jp | C55: 46011.803
B56: tintirorin3721@gmail.com | C56: 46012.228
B57: hirojp64@gmail.com | C57: 46012.462
B58: gennoji555@yahoo.co.jp | C58: 46012.558
B59: aincenote@gmail.com | C59: 46012.669
B60: 1st.sr400@gmail.com | C60: 46012.734
B61: follow_the_wind123@yahoo.co.jp | C61: 46012.886
B62: inainaemi@gmail.com | C62: 46012.995
B63: nakayamamitiohujio@gmail.com | C63: 46013.233
B64: ohtsuka@spre-ad.co.jp | C64: 46013.38
B65: kazu76698082@gmail.com | C65: 46013.497
... B84: rikiriki5188858@gmail.com | C84: 46022.92

Sheet 20261月
B2: メルマガ登録者(重複なし) | C2: 登録日時 | E2: 審査フォーム回答者(重複なし) | F2: 登録日時 | H2: 個別相談予約者(重複なし) | I2: 登録日時
B3: goodfeeling.goodtiming@gmail.com | C3: 46023.872 | E3: karua1229@yahoo.co.jp | F3: 46023.65 | H3: karua1229@yahoo.co.jp | I3: 46023.986
B4: seakaorulove@icloud.com | C4: 46024.907 | E4: rikiriki5188858@gmail.com | F4: 46023.897 | H4: youko405xx@gmail.com | I4: 46025.958
B5: hama_fuji888@icloud.com | C5: 46024.944 | E5: goodfeeling.goodtiming@gmail.com | F5: 46023.939 | H5: goodfeeling.goodtiming@gmail.com | I5: 46026.921
B6: hidejr1031@gmail.com | C6: 46024.948 | E6: wwkd2324@yahoo.co.jp | F6: 46025.173 | H6: ai_yasuda0806@icloud.com | I6: 46027.393
B7: dbxxhirokixxdb@yahoo.co.jp | C7: 46024.952 | E7: ai_yasuda0806@icloud.com | F7: 46025.707 | H7: unkotintindahhunda@icloud.com | I7: 46030.809
B8: taksfumi@gmail.com | C8: 46025.011 | E8: youko405xx@gmail.com | F8: 46025.863 | H8: keihiro7138@gmail.com | I8: 46032.594
B9: mirai2yume5050@gmail.com | C9: 46025.018 | E9: t16048857@gmail.com | F9: 46028.818 | H9: neoagile@gmail.com | I9: 46032.9
B10: noburinco1954@gmail.com | C10: 46025.078 | E10: unkotintindahhunda@icloud.com | F10: 46030.519 | H10: t16048857@gmail.com | I10: 46033.84
B11: michiaki0813@gmail.com | C11: 46025.1 | E11: eternalshallows@gmail.com | F11: 46032.402 | H11: cryptocurr1824@gmail.com | I11: 46035.077
B12: wwkd2324@yahoo.co.jp | C12: 46025.171 | E12: imay.103.fintx@gmail.com | F12: 46032.962 | H12: ronchi0527@gmail.com | I12: 46035.979
B13: marupappa@gmail.com | C13: 46025.243 | E13: uagq01ejh5edjw0p1kxe@docomo.ne.jp | F13: 46033.994 | H13: sundream715@yahoo.co.jp | I13: 46037.533
B14: beer.taka427@ezweb.ne.jp | C14: 46025.454 | E14: yatsutsuka@gmail.com | F14: 46034.632 | H14: takec3.1824@gmail.com | I14: 46038.849
B15: ai_yasuda0806@icloud.com | C15: 46025.668 | E15: ronchi0527@gmail.com | F15: 46035.851
B16: youko405xx@gmail.com | C16: 46025.833 | E16: sundream715@yahoo.co.jp | F16: 46036.365
B17: t16048857@gmail.com | C17: 46025.913 | E17: iesan.565622@gmail.com | F17: 46042.864
B18: yumeart369@gmail.com | C18: 46025.995
B19: n09046793594@docomo.ne.jp | C19: 46026.028
B20: mma71521@gmail.com | C20: 46026.387
B21: regalmente2008@gmail.com | C21: 46026.582
B22: noris216@yahoo.co.jp | C22: 46026.788
B23: buriburi43214321@gmail.com | C23: 46026.9
B24: hitomin104@kagi.be | C24: 46027.19
B25: djibril325@gmail.com | C25: 46027.321
B26: shigekof18255@yahoo.co.jp | C26: 46028.037
B27: imay.103.fintx@gmail.com | C27: 46028.512
B28: clover-wvw18870@ymobile.ne.jp | C28: 46028.58
B29: mickeyssatsuki@gmail.com | C29: 46028.681
... B85: sadamasa0119@gmail.com | C85: 46043.367

Sheet >input

Sheet メルマガ登録者
A1: 全シナリオ共通読者ID | B1: LINE友だちID | C1: アカウント共通LINE友だちID | D1: LINE登録名 | E1: 現在のメールアドレス | F1: 新しいメールアドレス | G1: 姓 | H1: 名 | I1: フリガナ | J1: 電話番号 | K1: 郵便番号 | L1: 都道府県 | M1: 市区町村 | N1: 番地 | O1: マンション名 部屋番号 | P1: イベント参加日 | Q1: 登録経路 | R1: 配信基準日時 | S1: 登録日時 | T1: 登録元ページ | U1: 登録元IP | V1: ステータス | W1: 解除日時
A2: CzcYUulM2Zfh | B2: fOgp49wHsqE3 | C2: 80aae274c808838ff103efb824f998ea | D2: noriko | R2: 45850.595 | S2: 45850.595 | V2: 購読中
A3: 0iQZuhwjutVu | B3: FnbVaYBg6jvh | C3: 5970373b205fbee54b7bf44b9fa6fafc | D3: nomura | R3: 45850.627 | S3: 45850.627 | V3: 購読中
A4: iCd22MGnlrXI | B4: TD4OblGmTsH6 | C4: 0d69f65fda673e09aa44d16daba64979 | D4: 藤田 ちなつ | R4: 45850.655 | S4: 45850.655 | V4: 購読中
A5: bOxbkHktQc6c | B5: 95wkYIgeb01u | C5: 6c6e980945313ec3c552e504601c1d13 | D5: 八津川ひとえ | R5: 45850.668 | S5: 45850.668 | V5: 購読中
A6: Pr807vBpKmyN | B6: Osj7rz79bsVe | C6: c80fe6531ee27d3d213337c3391d0f1c | D6: としちゃん | R6: 45850.718 | S6: 45850.718 | V6: 購読中
A7: TgU462j6OHqP | B7: ct4L283Bwb6h | C7: e9747267306322b465f5227e3b8cde0e | D7: K@Emori | R7: 45850.777 | S7: 45850.777 | V7: 購読中
A8: bi5BlC1VwExM | B8: P2XYdhRH216E | C8: 378a67c328c0c86a8c2cbe586554c5b2 | D8: 前川 | R8: 45850.827 | S8: 45850.827 | V8: 購読中
A9: PQ5iLiPE8cqN | B9: QGJJ0PKtkBr9 | C9: 40844f056850f7545e689f9484a4cefd | D9: 華 | R9: 45850.836 | S9: 45850.836 | V9: 購読中
A10: Enau0Jz0dvzn | B10: hJxtkcJGrn8v | C10: 92538f93cfc534b748fe26d8f671bfbe | D10: おぎけん | R10: 45850.845 | S10: 45850.845 | V10: 購読中
A11: R7qgvKa715Qy | B11: 8e1QswUwiL5o | C11: d5153f91eb9557820f053fbad50c3a35 | D11: 航央 | R11: 45850.85 | S11: 45850.85 | V11: 購読中
A12: hKNMu81dpfvn | B12: UiNEBvP67opx | C12: b008a6adaa3f17ebfe3313080ab43664 | D12: けら | R12: 45850.886 | S12: 45850.886 | V12: 購読中
A13: 9eWSXv7MNcFc | B13: hW8JGtn5oRTf | C13: 533502f7f8e7305167a797fca8a0c8ad | D13: Nori??Su | R13: 45850.891 | S13: 45850.891 | V13: 購読中
... A322: palYURKw1UYi | B322: brExFzg3W0Jk | C322: b5145a2976703a0c5e583b8b505416ee | D322: 岩井文好(LLC岩井工業) | R322: 45860.582 | S322: 45860.582 | V322: 購読中
A323: jg2nwYIJCAvi | B323: OckwDm0iX8V5 | C323: a9cc3d07f40855c2ba5865b6cb5f0866 | D323: 610 | R323: 45860.633 | S323: 45860.633 | V323: 購読中
A324: GkHGpO6QG7k8 | B324: iKZ3zCQTIo53 | C324: 64a9c7301fcbdf8c19619c74c8cbed4f | D324: Macha | R324: 45860.646 | S324: 45860.646 | V324: 購読中
A325: cOErZgm6uvJk | B325: HcgNavajifRT | C325: d3076467a505298c52ff48a05268a14b | D325: 剛志 | R325: 45860.723 | S325: 45860.723 | V325: 購読中
A326: BIZ8YNt2TiD9 | B326: XP6N8Pgu62et | C326: f6bf07533bb307ce3aae7da6959da2c5 | D326: 工藤 (藤岡 )久子 | R326: 45860.725 | S326: 45860.725 | V326: 購読中
A327: 1FU9oi4CavSr | B327: xyfwi6JMpdwD | C327: d314f3ba73759a6bd386e79db809feda | D327: 藤田 水産 | R327: 45860.746 | S327: 45860.746 | V327: 購読中
A328: g9CVWVCeYDqv | B328: lgPiBDHavLXu | C328: 3f65b37280977e74fb5af896ab83dfd6 | D328: akira nagahama | R328: 45860.792 | S328: 45860.792 | V328: 購読中
A329: fNBjDyrUcfK7 | B329: tNV9F5i0Of9n | C329: 693125590f6c279fe9c736d99db3fa8f | D329: 小櫻 辰秋 | R329: 45860.839 | S329: 45860.839 | V329: 購読中
A330: e3vZ0o2mrQ9a | B330: g9gYc7eAn4iM | C330: 9a6129d73b48c91050d780f4f9a015db | D330: 富樫学 | R330: 45860.89 | S330: 45860.89 | V330: 購読中
A331: lv17l2CfkYfB | B331: E9BTVETaTsPo | C331: d91b11de83958295d214832c8b805e86 | D331: suzuhigashi kota | R331: 45860.89 | S331: 45860.89 | V331: 購読中
A332: IT879s5HwsEE | B332: nh2xmjUs28Ky | C332: 497339e960c137ba6c54f124197502cb | D332: マッチ | R332: 45860.893 | S332: 45860.893 | V332: 購読中
A333: TvQQLPb0utJd | B333: bsZR9kVvoFOv | C333: 85a965967f1861ff6c739919ca9e8952 | D333: 松本直 | R333: 45860.896 | S333: 45860.896 | V333: 購読中
A334: YsD8NDElDfxi | B334: 2FmAtAe7RXrm | C334: f2356750b8ffb7e5da86f8f1059085a5 | D334: ぱにえ TORIKAGO | R334: 45860.905 | S334: 45860.905 | V334: 購読中
A335: UJ6rvdKOxheJ | B335: gCz5i55ha2N9 | C335: 2bd6de67291978d5a12c9f82465e10bc | D335: Nitta Keisuke | R335: 45860.91 | S335: 45860.91 | V335: 購読中
... A663: 7pyAhdAPw4ev | B663: V1o9wUy18pi5 | C663: b941820abbef9ffb85b10f1941bc2d8a | D663: Reina Tanaka | R663: 45876.932 | S663: 45876.932 | V663: 購読中
A664: k0jmAdN8UnTt | E664: 田中玲奈 | F664: rn010240@gmail.com | R664: 45876.933 | S664: 45876.933 | T664: https://sub.shirogakucho-web3.com/r/ohH4pKEyuKzr/register | U664: 221.248.180.22 | V664: 購読中
A665: hHyIemaa4N3k | B665: YRdfvCYuhyBF | C665: c0a25d2634b9e5e527fd29b79c31cf69 | D665: 神岡 阿修羅 | R665: 45877.025 | S665: 45877.025 | V665: 購読中
A666: 2E2uEmtCj85d | B666: mQk2C6lfwMSX | C666: 4290262199fadef62756dcd7e29c9a1a | D666: 佐藤亮二 | R666: 45877.204 | S666: 45877.204 | V666: 購読中
A667: UeOTOMndTaDB | B667: tVrW3iUNIPFj | C667: d1131a8db63c25f74a18694ce607a432 | D667: 杉川 Naoko | R667: 45877.324 | S667: 45877.324 | V667: 購読中
A668: RrmjpjFU0RsW | B668: NJXDQHV0rqiy | C668: 9ee050f1ea8d5b2be25ec7c005533690 | D668: momo? | R668: 45877.37 | S668: 45877.37 | V668: 購読中
A669: XfGwohOOfeSx | B669: FkQDKtl0TeOE | C669: d5a64957c7b4339a70fda0c889f3970a | D669: 孝広 | R669: 45877.392 | S669: 45877.392 | V669: 購読中
A670: XfGwohOOfeSx | B670: FkQDKtl0TeOE | C670: d5a64957c7b4339a70fda0c889f3970a | D670: 孝広 | R670: 45877.392 | S670: 45877.392 | V670: 購読中
A671: 5gZkrz4bZYPt | B671: AtL0rxv7YKB6 | C671: 57eb511242564abe28efe9283941a26c | D671: Y.I | R671: 45877.431 | S671: 45877.431 | V671: 購読中
A672: huAjRS8VkIMe | B672: OL6rQs3JZ7Es | C672: baafb13be0d44e762a9cf3d50b73a14c | D672: すがぬま こういち | R672: 45877.546 | S672: 45877.546 | V672: 購読中
A673: EcLlg86LMrO5 | B673: yOS7g0GPnhJE | C673: 85f5797ead026ea3a92ee5ed4930a924 | D673: 酒井 | R673: 45877.805 | S673: 45877.805 | V673: 購読中
A674: ogBJqzXNUnlr | E674: じん | F674: jin.hitoshi@gmail.com | R674: 45877.814 | S674: 45877.814 | T674: https://sub.shirogakucho-web3.com/r/ohH4pKEyuKzr/register | U674: 240b:c020:4d2:79f8:3c84:e717:6d98:4eb5 | V674: 購読中
A675: vvlJwuAKXSrh | E675: 松浦 | F675: akikoko0110@yahoo.co.jp | R675: 45877.814 | S675: 45877.814 | T675: https://sub.shirogakucho-web3.com/r/ohH4pKEyuKzr/register | U675: 2001:ce8:144:b55b:8d7a:e32b:e1d4:5d1a | V675: 購読中
A676: LxYPxXz5kZJ0 | E676: 板垣良雄 | F676: y.itagaki0528@gmail.com | R676: 45877.814 | S676: 45877.814 | T676: https://sub.shirogakucho-web3.com/r/ohH4pKEyuKzr/register | U676: 2400:2200:97c:f3b6:60de:865f:3e20:c0b7 | V676: 購読中
A677: UApfO3oDal1j | E677: 山本光子 | F677: bellevie3253@gmail.com | R677: 45877.814 | S677: 45877.814 | T677: https://sub.shirogakucho-web3.com/r/ohH4pKEyuKzr/register | U677: 1.21.51.195 | V677: 購読中
A678: kn6kIWJy6Swn | E678: 藤縄 大 | F678: hiroshi.fujinawa@gmail.com | R678: 45877.814 | S678: 45877.814 | T678: https://sub.shirogakucho-web3.com/r/ohH4pKEyuKzr/register | U678: 240b:12:21a2:1300:e8e0:4036:7bc4:c97e | V678: 購読中
A679: pDrA6BdOJhq2 | E679: よしひろひこうき | F679: hiroya_95@yahoo.co.jp | R679: 45877.814 | S679: 45877.814 | T679: https://sub.shirogakucho-web3.com/r/ohH4pKEyuKzr/register | U679: 2400:4153:69a4:3100:b953:569a:ef4f:afbb | V679: 購読中
A680: 6hYC7HAfmVgg | E680: S | F680: shoko2221@gmail.com | R680: 45877.814 | S680: 45877.814 | T680: https://sub.shirogakucho-web3.com/r/ohH4pKEyuKzr/register | U680: 2a09:bac3:4542:dc::16:1ea | V680: 解除済 | W680: 45890.959
A681: h0Errp9RSNFk | E681: 澤畑寿輝 | F681: toshiki.1120.sawahata@gmail.com | R681: 45877.814 | S681: 45877.814 | T681: https://sub.shirogakucho-web3.com/r/ohH4pKEyuKzr/register | U681: 2400:2200:401:26d8:e9fd:e452:4c63:c01e | V681: 購読中
A682: 34adDQhfCITs | B682: GCz0Gwl1VTJ4 | C682: 633ec21eb3f07dbd9ac5891002816999 | D682: Kouno | R682: 45877.814 | S682: 45877.814 | V682: 購読中
A683: kojxwf94T8zm | E683: 吉岡謙 | F683: kenyoshioka888@gmail.com | R683: 45877.814 | S683: 45877.814 | T683: https://sub.shirogakucho-web3.com/r/ohH4pKEyuKzr/register | U683: 2001:240:243c:2fa6:1986:c7e4:870f:41e9 | V683: 購読中
A684: tKPmkdgbmlBf | E684: 水間 | F684: mmizuma@gmail.com | R684: 45877.814 | S684: 45877.814 | T684: https://sub.shirogakucho-web3.com/r/ohH4pKEyuKzr/register | U684: 2400:4050:c164:1e00:7274:2037:1ced:f406 | V684: 購読中
A685: jiO0wuPFTTk1 | E685: okudera | F685: okudera.mit@gmail.com | R685: 45877.815 | S685: 45877.815 | T685: https://sub.shirogakucho-web3.com/r/ohH4pKEyuKzr/register | U685: 240a:61:5032:12f1:38c1:40c4:ee1c:2586 | V685: 解除済 | W685: 45885.904
A686: tuYOT8jetphp | E686: 原口優子 | F686: y6649851@gmail.com | R686: 45877.815 | S686: 45877.815 | T686: https://sub.shirogakucho-web3.com/r/ohH4pKEyuKzr/register | U686: 210.136.107.235 | V686: 解除済 | W686: 46002.793
A687: lcRMb61XXsgy | E687: 木村和美 | F687: millenniumstar8@gmail.com | R687: 45877.815 | S687: 45877.815 | T687: https://sub.shirogakucho-web3.com/r/ohH4pKEyuKzr/register | U687: 2603:800c:12f0:2030:df7:3546:9397:5991 | V687: 購読中
A688: YcBswZp9yhU2 | E688: 八巻孝勇 | F688: paochan115@gmail.com | R688: 45877.815 | S688: 45877.815 | T688: https://sub.shirogakucho-web3.com/r/ohH4pKEyuKzr/register | U688: 2400:2410:c3e2:c400:c4ff:b4ff:b66e:759e | V688: 購読中
A689: IZ8qaq43vIGl | E689: 加藤尋通 | F689: kouei-katou@biglobe.jp | R689: 45877.815 | S689: 45877.815 | T689: https://sub.shirogakucho-web3.com/r/ohH4pKEyuKzr/register | U689: 153.202.63.65 | V689: 購読中
A690: L4FYFRcMfzjR | E690: 松村博敏 | F690: yuntakuy@gmail.com | R690: 45877.815 | S690: 45877.815 | T690: https://sub.shirogakucho-web3.com/r/ohH4pKEyuKzr/register | U690: 126.23.225.125 | V690: 購読中
A691: wAWdMuqJCagT | E691: 高塚 義典 | F691: ytakatsuka0524@gmail.com | R691: 45877.815 | S691: 45877.815 | T691: https://sub.shirogakucho-web3.com/r/ohH4pKEyuKzr/register | U691: 2400:4051:c641:b500:9d45:793d:91e0:6925 | V691: 購読中
A692: L20iOvfRnadE | E692: おたぬ | F692: otanu0713@gmail.com | R692: 45877.816 | S692: 45877.816 | T692: https://sub.shirogakucho-web3.com/r/ohH4pKEyuKzr/register | U692: 2001:268:d2f1:38bd:991c:c9ad:d858:52b3 | V692: 購読中
A693: GWhHuYKw2ptl | E693: 中里大輔 | F693: da9662@icloud.com | R693: 45877.816 | S693: 45877.816 | T693: https://sub.shirogakucho-web3.com/r/ohH4pKEyuKzr/register | U693: 2400:2651:8080:e700:74ba:4e4b:6df4:9a67 | V693: 購読中/配信エラー
A694: oYVaRaYQpdGb | E694: 山本瞳 | F694: hitomimakeup0130@icloud.com | R694: 45877.817 | S694: 45877.817 | T694: https://sub.shirogakucho-web3.com/r/ohH4pKEyuKzr/register | U694: 111.188.184.25 | V694: 購読中/配信エラー
A695: VVQT0Uyw9eSo | E695: しげ | F695: shigeki.reo@gmail.com | R695: 45877.817 | S695: 45877.817 | T695: https://sub.shirogakucho-web3.com/r/ohH4pKEyuKzr/register | U695: 2001:4451:879f:3d00:b036:3e79:32a5:5f6a | V695: 解除済 | W695: 45888.49
A696: l0Efe5o8Ffza | E696: 松本貴子 | F696: kirrakirat@yahoo.co.jp | R696: 45877.818 | S696: 45877.818 | T696: https://sub.shirogakucho-web3.com/r/ohH4pKEyuKzr/register | U696: 2001:268:9b74:63ed:414b:d1a2:65fb:65e0 | V696: 購読中
A697: Fsn62cgztvl2 | E697: 坂本はるみ | F697: kotobukiclubjp@gmail.com | R697: 45877.818 | S697: 45877.818 | T697: https://sub.shirogakucho-web3.com/r/ohH4pKEyuKzr/register | U697: 115.69.5.203 | V697: 購読中
A698: t9VrsiUjpYZZ | E698: 湯塩里江子 | F698: sakura37mankai@gmail.com | R698: 45877.818 | S698: 45877.818 | T698: https://sub.shirogakucho-web3.com/r/ohH4pKEyuKzr/register | U698: 61.46.20.179 | V698: 購読中
A699: VhQ67Aap1As9 | E699: 西藤章恵 | F699: happy.win.1202@gmail.com | R699: 45877.819 | S699: 45877.819 | T699: https://sub.shirogakucho-web3.com/r/ohH4pKEyuKzr/register | U699: 60.88.224.118 | V699: 解除済 | W699: 45962.642
A700: HYfwfe7xQ0VC | E700: 安藤 宏明 | F700: beach-beach.co.jp@docomo.ne.jp | R700: 45877.819 | S700: 45877.819 | T700: https://sub.shirogakucho-web3.com/r/ohH4pKEyuKzr/register | U700: 240a:61:31f3:6acc:24f5:3472:c58d:8b2 | V700: 購読中
A701: iMSxQ5q87Ddi | E701: 鈴東 耕太 | F701: suzuhigashikota@gmail.com | R701: 45877.819 | S701: 45877.819 | T701: https://sub.shirogakucho-web3.com/r/ohH4pKEyuKzr/register | U701: 240a:61:1105:1a96:e4b7:1eff:fed3:3813 | V701: 購読中
A702: iqv8LegQC3uC | E702: 隅田 | F702: support@kansenkokufuku.com | R702: 45877.82 | S702: 45877.82 | T702: https://sub.shirogakucho-web3.com/r/ohH4pKEyuKzr/register | U702: 114.182.219.242 | V702: 購読中/配信エラー
A703: U38ceoPsyICC | E703: 亀甲勝仁 | F703: yosihiro884@gmail.com | R703: 45877.82 | S703: 45877.82 | T703: https://sub.shirogakucho-web3.com/r/ohH4pKEyuKzr/register | U703: 222.229.201.183 | V703: 購読中
A704: 96lS321yOdHT | E704: たか | F704: oreokotetsu11@gmail.com | R704: 45877.82 | S704: 45877.82 | T704: https://sub.shirogakucho-web3.com/r/ohH4pKEyuKzr/register | U704: 115.85.108.130 | V704: 購読中
A705: RzJCiYGv7AFu | E705: Hiroyuki C | F705: izaiyak@gmail.com | R705: 45877.82 | S705: 45877.82 | T705: https://sub.shirogakucho-web3.com/r/ohH4pKEyuKzr/register | U705: 125.26.173.184 | V705: 購読中
A706: SGHaAr8PBXUS | E706: ともちん | F706: jjto2no@gmail.com | R706: 45877.82 | S706: 45877.82 | T706: https://sub.shirogakucho-web3.com/r/ohH4pKEyuKzr/register | U706: 240b:c020:491:8efb:dd79:d496:9515:5fa7 | V706: 購読中
A707: mNWlrUnzR1zw | E707: 川津明日香 | F707: jamiko0705@yahoo.co.jp | R707: 45877.821 | S707: 45877.821 | T707: https://sub.shirogakucho-web3.com/r/ohH4pKEyuKzr/register | U707: 240f:51:f3d7:1:44e3:5c8:7e03:21cf | V707: 購読中
A708: CjGIoavCrj9x | E708: 小高和博 | F708: odaka_kazuhiro@yahoo.co.jp | R708: 45877.821 | S708: 45877.821 | T708: https://sub.shirogakucho-web3.com/r/ohH4pKEyuKzr/register | U708: 240b:c010:660:70a8:9542:7d45:1685:de6c | V708: 購読中
A709: 3eQtsk0lc4qL | E709: 木下良美 | F709: yotimi0419@gmail.com | R709: 45877.821 | S709: 45877.821 | T709: https://sub.shirogakucho-web3.com/r/ohH4pKEyuKzr/register | U709: 2400:4150:43a1:ad00:48be:f00:8624:d625 | V709: 購読中
A710: B27SMJcYaCeV | E710: 増山武彦 | F710: take.mas1969@gmail.com | R710: 45877.821 | S710: 45877.821 | T710: https://sub.shirogakucho-web3.com/r/ohH4pKEyuKzr/register | U710: 2404:7a85:4860:2f00:1613:5bfa:bfb4:7b16 | V710: 購読中
A711: N1Yz4A62KesI | E711: Z1030 | F711: usamat2018@gmail.com | R711: 45877.822 | S711: 45877.822 | T711: https://sub.shirogakucho-web3.com/r/ohH4pKEyuKzr/register | U711: 2001:268:942e:6641:817f:7fff:400a:365e | V711: 購読中
A712: O9ccybcZ1Edo | E712: 尼川 高 | F712: amataka2011@yahoo.co.jp | R712: 45877.822 | S712: 45877.822 | T712: https://sub.shirogakucho-web3.com/r/ohH4pKEyuKzr/register | U712: 240d:1e:4ba:5500:d95a:8384:211f:88ce | V712: 解除済 | W712: 45927.326
A713: r8rJSoC1vlje | E713: 浅井洋貴 | F713: flat6.6mt@gmail.com | R713: 45877.822 | S713: 45877.822 | T713: https://sub.shirogakucho-web3.com/r/ohH4pKEyuKzr/register | U713: 2001:268:7254:be19:70e0:d56a:5926:b0e5 | V713: 購読中
A714: l06drwLLquou | E714: おさ | F714: hal_data_solution@yahoo.co.jp | R714: 45877.822 | S714: 45877.822 | T714: https://sub.shirogakucho-web3.com/r/ohH4pKEyuKzr/register | U714: 2400:4150:7102:4600:55a3:5a66:bf33:db5b | V714: 購読中
A715: v63Uam7ZM2H2 | E715: 野口博史 | F715: hiroshi.n197891@gmail.com | R715: 45877.822 | S715: 45877.822 | T715: https://sub.shirogakucho-web3.com/r/ohH4pKEyuKzr/register | U715: 240b:c010:654:329:f9bd:3f6b:fe82:251d | V715: 購読中
A716: 7WdRwvY0cLGR | E716: 田中秀之 | F716: hidetana3110@gmail.com | R716: 45877.823 | S716: 45877.823 | T716: https://sub.shirogakucho-web3.com/r/ohH4pKEyuKzr/register | U716: 2001:f71:86e0:e00:29a6:ba6:f0ae:1ea5 | V716: 購読中
A717: r1a621LCENzB | E717: 杉川 | F717: sugikawa705@gmail.com | R717: 45877.823 | S717: 45877.823 | T717: https://sub.shirogakucho-web3.com/r/ohH4pKEyuKzr/register | U717: 156.59.26.134 | V717: 購読中
A718: rbQVtF2yevFP | E718: 與儀貴志 | F718: takashiyogi934@gmail.com | R718: 45877.823 | S718: 45877.823 | T718: https://sub.shirogakucho-web3.com/r/ohH4pKEyuKzr/register | U718: 2001:f76:9580:1e00:241c:f06c:2faf:afbb | V718: 購読中
A719: 5zvDM5Z0j7Lc | E719: 西澤 健一 | F719: nishiken83066@gmail.com | R719: 45877.824 | S719: 45877.824 | T719: https://sub.shirogakucho-web3.com/r/ohH4pKEyuKzr/register | U719: 126.166.168.81 | V719: 購読中/配信エラー
A720: m0GRoo3UwHr1 | E720: サム | F720: entrepreneurial.ueno@gmail.com | R720: 45877.825 | S720: 45877.825 | T720: https://sub.shirogakucho-web3.com/r/ohH4pKEyuKzr/register | U720: 36.255.206.42 | V720: 購読中
A721: WNl2U8C47fHO | E721: 廣田香苗 | F721: kanaeko2@gmail.com | R721: 45877.825 | S721: 45877.825 | T721: https://sub.shirogakucho-web3.com/r/ohH4pKEyuKzr/register | U721: 2400:2410:90e0:3a00:40d0:37d1:c696:49a5 | V721: 購読中
A722: LulDj8OdAGnx | E722: 北平一喜 | F722: kitakazu3333@icloud.com | R722: 45877.825 | S722: 45877.825 | T722: https://sub.shirogakucho-web3.com/r/ohH4pKEyuKzr/register | U722: 58.70.181.245 | V722: 購読中/配信エラー
A723: 3hXw29Fs1KgB | E723: 磯野伸一 | F723: 3j.happysurf.y303@gmail.com | R723: 45877.826 | S723: 45877.826 | T723: https://sub.shirogakucho-web3.com/r/ohH4pKEyuKzr/register | U723: 126.158.183.44 | V723: 購読中
A724: gbSPntvJKD8D | E724: 太郎 | F724: ryotaro1218@gmail.com | R724: 45877.826 | S724: 45877.826 | T724: https://sub.shirogakucho-web3.com/r/ohH4pKEyuKzr/register | U724: 2001:f70:35c0:a200:1126:a72a:351b:9b93 | V724: 購読中
... A731: Dg1JNuATp9lN | E731: 船元 | F731: kyonbokun0509@gmail.com | R731: 45877.831 | S731: 45877.831 | T731: https://sub.shirogakucho-web3.com/r/ohH4pKEyuKzr/register | U731: 122.30.2.230 | V731: 購読中
A732: 5ntXF2MOvFoP | E732: 丸山満男 | F732: dady152@gmail.com | R732: 45877.832 | S732: 45877.832 | T732: https://sub.shirogakucho-web3.com/r/ohH4pKEyuKzr/register | U732: 180.92.25.132 | V732: 解除済 | W732: 45878.436
A733: lFigd9be7kL9 | E733: 西村謙 | F733: kallzz0428@gmail.com | R733: 45877.833 | S733: 45877.833 | T733: https://sub.shirogakucho-web3.com/r/ohH4pKEyuKzr/register | U733: 2400:2200:583:9fa7:111b:bb98:ab21:76da | V733: 購読中
A734: UqxgmI4YixJu | E734: Sitei | F734: sitei2020@yahoo.co.jp | R734: 45877.833 | S734: 45877.833 | T734: https://sub.shirogakucho-web3.com/r/ohH4pKEyuKzr/register | U734: 2400:2412:6182:1700:f9e8:f51f:1752:685a | V734: 購読中
A735: aJLT2XdCOoWq | E735: タマ | F735: wamute62@yahoo.co.jp | R735: 45877.834 | S735: 45877.834 | T735: https://sub.shirogakucho-web3.com/r/ohH4pKEyuKzr/register | U735: 2404:7a83:9e1:4400:3150:c677:efe5:9c3b | V735: 購読中
A736: z7ruE91itlA4 | E736: yos | F736: yoshihiro.310@gmail.com | R736: 45877.834 | S736: 45877.834 | T736: https://sub.shirogakucho-web3.com/r/ohH4pKEyuKzr/register | U736: 240b:11:ea20:7600:5148:5868:6d0b:fb3d | V736: 購読中
A737: cXH3GhFj6OOp | E737: リク クニキ | F737: riku365bb@gmail.com | R737: 45877.836 | S737: 45877.836 | T737: https://sub.shirogakucho-web3.com/r/ohH4pKEyuKzr/register | U737: 153.239.21.3 | V737: 購読中
A738: 074TJNOungRW | E738: 小杉武雄 | F738: goodysoul5@gmail.com | R738: 45877.836 | S738: 45877.836 | T738: https://sub.shirogakucho-web3.com/r/ohH4pKEyuKzr/register | U738: 2400:2411:3e61:be00:7cf5:4661:61ee:b13e | V738: 購読中
A739: pgHGtuniPM85 | E739: ウエノタダシ | F739: ueno5959@i.softbank.jp | R739: 45877.836 | S739: 45877.836 | T739: https://sub.shirogakucho-web3.com/r/ohH4pKEyuKzr/register | U739: 2001:f72:3980:2000:581a:731a:1502:d6b9 | V739: 購読中
A740: You8IEDqFzZl | E740: Risa | F740: Lizrose258@gmail.com | R740: 45877.837 | S740: 45877.837 | T740: https://sub.shirogakucho-web3.com/r/ohH4pKEyuKzr/register | U740: 203.10.99.52 | V740: 購読中
A741: w9QG2So7DFMU | E741: さくらこ | F741: sakura.tatsu07@gmail.com | R741: 45877.84 | S741: 45877.84 | T741: https://sub.shirogakucho-web3.com/r/ohH4pKEyuKzr/register | U741: 2400:2653:180:5800:743a:850a:d437:a27f | V741: 購読中
...

Sheet 審査フォーム回答者①
A1: 全シナリオ共通読者ID | B1: LINE友だちID | C1: アカウント共通LINE友だちID | D1: LINE登録名 | E1: お名前 | F1: メールアドレス | G1: 姓 | H1: 名 | I1: フリガナ | J1: 電話番号 | K1: 郵便番号 | L1: 都道府県 | M1: 市区町村 | N1: 番地 | O1: マンション名 部屋番号 | P1: イベント参加日 | Q1: 現在の仮想通貨投資レベルを教えてください！ | R1: 現在の月収を教えてください！ | S1: 有料の「トレードスクール」に興味ありますか？ | T1: その他シロ学長へのメッセージ・聞きたいこと | U1: お名前 | V1: 面談で聞きたいこと・解決したいお悩みを教えてください！(選択式) | W1: 登録経路 | X1: 配信基準日時 | Y1: 登録日時 | Z1: 登録元ページ | AA1: 登録元IP | AB1: ステータス | AC1: 解除日時
A2: TllJMv4INfZr | E2: 吉田 隆 | F2: ty11055yoshi@gmail.com | Q2: 未経験 | R2: 50万くらい | S2: ある | T2: いつもYoutube楽しみいしてます。 | U2: 吉田隆 | X2: 45884.795 | Y2: 45884.795 | Z2: https://sub.shirogakucho-web3.com/p/jwf1rmhnKm4S | AA2: 240f:102:f60c:1:f86f:81f3:f7c8:ba9f | AB2: 解除済 | AC2: 45911.229
A3: OYgI3YxHf4x4 | E3: 増山 武彦 | F3: take.mas1969@gmail.com | Q3: 未経験 | R3: 50万円 | S3: ない | T3: 現在、天然ガスの投資に失敗して、損切した金額100万円を毎月返済しています。シロ学長が説明される内容を勉強したい。 | U3: 増山武彦 | X3: 45884.795 | Y3: 45884.795 | Z3: https://sub.shirogakucho-web3.com/p/jwf1rmhnKm4S | AA3: 2404:7a85:4860:2f00:b991:b57b:50d7:1b2 | AB3: 購読中
A4: XwUE3ZIRp5VH | E4: 藤原 克哉 | F4: fujiwara.katsuya@gmail.com | Q4: 経験あり | R4: 30万円程度 | S4: ある | T4: ｙ楽しみにしています！ | U4: 藤原克哉 | X4: 45884.796 | Y4: 45884.796 | Z4: https://sub.shirogakucho-web3.com/p/jwf1rmhnKm4S | AA4: 2404:7a84:3c60:e00:10ca:e8fd:80ef:4763 | AB4: 購読中
A5: Qnt4R4VPmu4R | E5: 宮本 義孝 | F5: mymtystk@gmail.com | Q5: 初心者 | R5: 50万程度 | S5: ある | T5: よろしくお願いします | U5: 宮本義孝 | X5: 45884.796 | Y5: 45884.796 | Z5: https://sub.shirogakucho-web3.com/p/jwf1rmhnKm4S | AA5: 58.70.182.228 | AB5: 購読中
A6: qYXDaYqfsb3E | E6: 櫛田 直 | F6: nao394d@gmail.com | Q6: 初心者 | R6: 50 | S6: ある | T6: 先ずは勉強したいです | U6: 櫛田直 | X6: 45884.796 | Y6: 45884.796 | Z6: https://sub.shirogakucho-web3.com/p/jwf1rmhnKm4S | AA6: 220.211.86.70 | AB6: 購読中
A7: HtYdsZVsKM2v | E7: 鎭目 真喜子 | F7: shizumemakiko@gmail.com | Q7: 初心者 | R7: 20万以下 | S7: ない | T7: シングルの母なので、自立してやっていける力をつけたいです。宜しくお願いします。 | U7: 鎭目 真喜子 | X7: 45884.798 | Y7: 45884.798 | Z7: https://sub.shirogakucho-web3.com/p/jwf1rmhnKm4S | AA7: 58.12.1.1 | AB7: 解除済 | AC7: 45889.756
A8: gTFnGp2CVJtw | E8: 水間 将誉 | F8: mmizuma@gmail.com | Q8: 初心者 | R8: 30万 | S8: ある | T8: 老後の資金を作りたい | U8: 水間将誉 | X8: 45884.8 | Y8: 45884.8 | Z8: https://sub.shirogakucho-web3.com/p/jwf1rmhnKm4S | AA8: 2400:4050:c164:1e00:1cdb:858a:30c:a787 | AB8: 購読中
A9: gwDgFYKmElzE | E9: 木村 和美 | F9: millenniumstar8@gmail.com | Q9: 初心者 | R9: 0 | S9: ない | T9: Youtube楽しく見ています。ハワイ在住です。私も昔300万円仮想通貨で消えました。住宅ローン早く返したいです。どうぞよろしくお願いします！ | U9: 木村和美 | X9: 45884.802 | Y9: 45884.802 | Z9: https://sub.shirogakucho-web3.com/p/jwf1rmhnKm4S | AA9: 2603:800c:12f0:2030:8d0e:a99c:a91b:37c7 | AB9: 購読中
A10: 5ZYHptx28VYZ | E10: 酒井 由美 | F10: yamayu0462@gmail.com | Q10: 中級位です | R10: 100前後 | S10: ある | T10: 仮想通貨の情報をワクワクしながらyou tubeで拝見しております。どうもありがとうございます。 | U10: 酒井由美 | X10: 45884.802 | Y10: 45884.802 | Z10: https://sub.shirogakucho-web3.com/p/jwf1rmhnKm4S | AA10: 114.48.188.145 | AB10: 解除済 | AC10: 45888.282
A11: Dh9hYNpEZJoJ | E11: 黄本 章雄 | F11: smile.jack317@docomo.ne.jp | Q11: 初心者 | R11: 使えるお金が、5万～頑張って10万いかるかなー | S11: ない | T11: 普段から、パソコン、スマホも使えない私ですが、宜しくお願いします??? | U11: キモトアキオ | X11: 45884.803 | Y11: 45884.803 | Z11: https://sub.shirogakucho-web3.com/p/jwf1rmhnKm4S | AA11: 240b:250:58e1:c00:cd0e:beb1:1479:32bd | AB11: 購読中
A12: d2TSp63d0Y1g | F12: s.takeda000@icloud.com | Q12: 初心者 | R12: 50万程度 | S12: ある | T12: これから仮想通貨を学びたいと思いますので宜しくお願い致します | U12: 武田 慎吾 | X12: 45884.805 | Y12: 45884.805 | Z12: https://sub.shirogakucho-web3.com/p/jwf1rmhnKm4S | AA12: 2400:4153:2064:c010:5494:256a:dc1c:fb8c | AB12: 購読中
A13: e8oksGRnuklE | E13: 門田 典美 | F13: ganbamonta@gmail.com | Q13: 初心者 | R13: 30万円以下 | S13: ない | T13: 何度もYouTubeを見返して勉強させていただいています。なかなかサクサク頭に入っていかないことの多いのですがしっかりついていきたいと思います。私も多くの詐欺に遭ったばかりでまとまった額の投資は難しいのですが、よろしくお願いします | U13: 門田 典美 | X13: 45884.805 | Y13: 45884.805 | Z13: https://sub.shirogakucho-web3.com/p/jwf1rmhnKm4S | AA13: 60.102.49.166 | AB13: 購読中
A14: Z6CbT7fbjgwh | E14: 藤原 和憲 | F14: heckel371@yahoo.co.jp | Q14: 初心者 | R14: 20万円 | S14: ある | U14: 藤原和憲 | X14: 45884.807 | Y14: 45884.807 | Z14: https://sub.shirogakucho-web3.com/p/jwf1rmhnKm4S | AA14: 2001:ce8:184:4442:18a0:4f43:82f1:ba19 | AB14: 購読中
A15: X0pIRMuMuiYa | F15: yoh.sekido@gmail.com | Q15: 中級者 | R15: 50万 | S15: ある | T15: 宜しくお願いします。 | U15: 関戸 | X15: 45884.818 | Y15: 45884.818 | Z15: https://sub.shirogakucho-web3.com/p/jwf1rmhnKm4S | AA15: 2405:6581:51e0:7b00:bc11:68cb:b633:8e9e | AB15: 購読中
A16: qVjoToPccxkm | E16: 丸山 満男 | F16: dady152@gmail.com | Q16: 初心者 | R16: 20万以下 | S16: ある | T16: 宜しくお願い致します | U16: 丸山満男 | X16: 45884.822 | Y16: 45884.822 | Z16: https://sub.shirogakucho-web3.com/p/jwf1rmhnKm4S | AA16: 180.92.25.132 | AB16: 購読中
A17: qYXDaYqfsb3E | E17: 櫛田 直 | F17: nao394d@gmail.com | Q17: 初心者 | R17: 50万円程度 | S17: ある | T17: 私も詐欺に遭い、やり直したいと考えています。専門家の力を借りて頑張りたいと考えています。よろしくお願いします。 | U17: 櫛田直 | X17: 45884.824 | Y17: 45884.824 | Z17: https://sub.shirogakucho-web3.com/p/jwf1rmhnKm4S | AA17: 220.211.86.70 | AB17: 購読中
A18: Y4I87GbIs9QD | E18: 滝本 晴子 | F18: supuring0709@gmail.com | Q18: 初心者 | R18: 22万 | S18: ある | U18: 滝本 晴子 | X18: 45884.824 | Y18: 45884.824 | Z18: https://sub.shirogakucho-web3.com/p/jwf1rmhnKm4S | AA18: 211.15.20.244 | AB18: 解除済 | AC18: 45890.327
A19: maBjLxvUHlnP | E19: 登田 英樹 | F19: towahide091q@gmail.com | Q19: 中級 | R19: 50万 | S19: ある | T19: 仮想通貨には5年位関わっていますが、数々の詐欺に遭ってきました。今はトレードはなく現物のコインを毎月少しずつ買っていますが、手持ちの資金が減ってきています。本業も忙しいのですが、少しずつ勉強しながら学んでいきたいです。よろしくお願いします。 | U19: 登田英樹 | X19: 45884.825 | Y19: 45884.825 | Z19: https://sub.shirogakucho-web3.com/p/jwf1rmhnKm4S | AA19: 153.201.87.32 | AB19: 購読中
A20: fcWKgGmD9sB8 | E20: 原野 智哉 | F20: tom1966_11@hotmail.com | Q20: 仮想通貨投資を始めて6ヶ月ですが、知識がまだ浅いです。 | R20: 月収は50万円程度です。 | S20: ある | T20: 現在、娘が2名おり、長女が高1、次女が6年生です。大学への学費などを準備したいと思っています。また自分は60歳手前であり、そのためにこの5年で1000万円、10年で3000万円程度は資金を作りたいと思っています。退職金は安定した退職後の生活に回す必要があるのです。トレードは初めてですが、シロ学長の方法を学ばせてください。他のYouTubeのトレード戦略はよくわかりませんでした。 | U20: 原野 智哉 | X20: 45884.826 | Y20: 45884.826 | Z20: https://sub.shirogakucho-web3.com/p/jwf1rmhnKm4S | AA20: 202.28.7.62 | AB20: 購読中
A21: t395JN2sySTE | E21: 藤堂 憲子 | F21: britelightone1@gmail.com | Q21: やるしかない！初心者です！ | R21: 0円 | S21: ある | T21: 3人同時介護中で預金を切り崩し、体調も崩し、これではいけないとシロさんに辿り着きました。20年前に中央アフリカ大使に1200万円の詐欺にあい、働きながら医療系夜間学校に通っていた為、学費を「いけない事」して稼ぐしかありませんでした。3人同時介護の前も人の面倒ばかりでいい加減に自分の生活を取り戻したい、暗号通貨の世界は面白い！が繋がり、シロ学長のYoutubeを見ていて震えました。中長期のプロジェクトへの投資はしましたが、それまでどうするの？私はもう53歳だよ？10年後って。。。そこまで何とか利益を確保出来る手段がないかな、とずーーーっと考えていました。機械音痴でやっと最近キャッシュレスでのお買い物が出来るようになりました。プレミアロジックの動画は何となくしか理解が出来ませんでしたが今の私の生活でも利益が出せる！深呼吸が出来る！両親と伯母をヘルパーさんに託して(支払って)外へ行けるようになる！その為なら移動中でも勉強をしたい！！成果を出したい！そういう気持ちです。学ぶにはお金がかかるのが普通ですが、それさえもキツい生活です。でもシロ学長のロジックをしっかりと学べるならお返しをしたい！です。PDFだけで見ると頭痛がしてきますがシロ学長なら私のような初心者の為の対応を絶対にして下さる！かなり神頼み的になってしまいましたが、本当に初心者の私でもついて行きますのでどうぞ宜しくお願い致します！ | U21: 藤堂憲子 | X21: 45884.827 | Y21: 45884.827 | Z21: https://sub.shirogakucho-web3.com/p/jwf1rmhnKm4S | AA21: 2400:4050:8801:9c00:3d89:787e:1a57:c3b7 | AB21: 購読中
A22: RuqbIbOkDaq1 | E22: 鵜野 彰洋 | F22: au09054720010@gmail.com | Q22: 初心者 | R22: 90万 | S22: ある | T22: 楽しみにしています。稼ぐ力、着けたいです！ | U22: 鵜野彰洋 | X22: 45884.828 | Y22: 45884.828 | Z22: https://sub.shirogakucho-web3.com/p/jwf1rmhnKm4S | AA22: 240b:252:e60:2800:d4f9:4b18:5f3c:5802 | AB22: 購読中
A23: g557hMPanUIH | F23: jamiko0705@yahoo.co.jp | Q23: 初心者 | R23: 10万円 | S23: ない | T23: 分かりやすいYouTubeをどうもありがとうございます！ | U23: 川津明日香 | X23: 45884.828 | Y23: 45884.828 | Z23: https://sub.shirogakucho-web3.com/p/jwf1rmhnKm4S | AA23: 2001:268:987f:753d:315c:9b56:2619:41af | AB23: 購読中
A24: 3DEdw698qXc9 | E24: 中山 和人 | F24: mikura1969@icloud.com | Q24: 初心者 | R24: 50万 | S24: ある | T24: 57歳のサラリーマンで副業で物販をしていますが、物販の副業で儲け続ける難しさを痛感しています。効率良く安定した収益を仮想通貨であげれるようにぜひともなりたいのでよろしくお願い致します。 | U24: 中山和人 | X24: 45884.83 | Y24: 45884.83 | Z24: https://sub.shirogakucho-web3.com/p/jwf1rmhnKm4S | AA24: 2001:268:73b6:d61c:fd7f:dff6:5560:370a | AB24: 購読中
A25: hOWycn41njc4 | E25: 原口 優子 | F25: y6649851@gmail.com | Q25: 初心者 | R25: 20万円 | S25: ない | T25: よろしくお願いいたします。 | U25: 原口優子 | X25: 45884.831 | Y25: 45884.831 | Z25: https://sub.shirogakucho-web3.com/p/jwf1rmhnKm4S | AA25: 210.136.107.235 | AB25: 購読中
A26: Ioj0uHHtIjDy | E26: 轟 洋子 | F26: paribmw369@gmail.com | Q26: 未経験 | R26: 20万円以下 | S26: ある | T26: 有料で高いと参加できません。何ヶ月も勉強も出来ません。やる気はあります。 | U26: 轟 洋子 | X26: 45884.832 | Y26: 45884.832 | Z26: https://sub.shirogakucho-web3.com/p/jwf1rmhnKm4S | AA26: 2400:4051:c841:100:c855:8884:3f3a:74ac | AB26: 解除済 | AC26: 45958.657
A27: 5v4cfPq1B1Ci | F27: ktkhs@gmail.com | Q27: 未経験 | R27: 30万円程度 | S27: ある | T27: 色々勉強させてください。 | U27: 高橋 敬 | X27: 45884.833 | Y27: 45884.833 | Z27: https://sub.shirogakucho-web3.com/p/jwf1rmhnKm4S | AA27: 160.13.182.22 | AB27: 購読中/配信エラー
A28: Y4I87GbIs9QD | B28: fBA0pxPCPonl | C28: 3d91444815d3d53a5bf376f537ef3a89 | D28: 滝本 晴子 | E28: 滝本 晴子 | F28: supuring0709@gmail.com | Q28: 初心者 | R28: 22万 | S28: ある | T28: 副業しても上手く行かず老後の不安もあります。自由な時間も欲しい節約しないで生活したい今の生活変えたいです。宜しくお願いします。 | U28: 滝本晴子 | X28: 45884.833 | Y28: 45884.833 | Z28: https://sub.shirogakucho-web3.com/p/jwf1rmhnKm4S | AA28: 211.15.20.244 | AB28: 解除済 | AC28: 45890.327
A29: hQ4TwjsverNH | E29: 鈴木 宏一 | F29: h-suzuki@daiwack.co.jp | Q29: 初心者です | R29: 50万円程度 | S29: ある | T29: 会社員のため本業もありますので、ルールがあり淡々とトレードできるのは大変有り難いです。よろしくお願いいたします。 | U29: 鈴木宏一 | X29: 45884.835 | Y29: 45884.835 | Z29: https://sub.shirogakucho-web3.com/p/jwf1rmhnKm4S | AA29: 183.77.56.18 | AB29: 解除済 | AC29: 45907.63
A30: Y8n9eeYqJews | E30: 福島 修 | F30: w.rainey-0840@kuf.biglobe.ne.jp | Q30: 初心者 | R30: 30万円 | S30: ない | T30: プレミアムロジックがどのような手法か、興味があります。個別説明会に申し込みしたいと思います。 | U30: 福島 修 | X30: 45884.836 | Y30: 45884.836 | Z30: https://sub.shirogakucho-web3.com/p/jwf1rmhnKm4S | AA30: 2001:268:c215:58a:c1cd:8e67:19b1:4821 | AB30: 購読中
A31: 2enDrQfa7Fb9 | E31: 坂本 はるみ | F31: kotobukiwithin@gmail.com | Q31: 初心者 | R31: 35万円 | S31: ある | T31: いつも有益な発信感謝しています。にも関わらず、正直に申し上げると、教えに従って行動したにも関わらず、思ったような成果も出せないどころか、大損をしてしまったことも一度や二度ではありません。これまで大きな詐欺に五度遭い、損失総額は5千万円を超えます。株式やゴールドには一度も手を出したことはありませんが、FXをかなりランダムに取引して手数料で資産を溶かしてきました。2016～17年に人生初めて最大の詐欺に遭ってドン底を経験した時、起死回生を狙ってビットコインに手を出しましたが、きちんと勉強もせず周りが騒いでいるからという理由で買ったので、直ぐ不安になり全部売って手数料で損をし、その後そちらの世界には一切目をつぶって生きてきました。仮想通貨を改めて見直したのは、ほんの数ヶ月前からです。昨年から2回続けて投資詐欺に遭い叩きのめされても、AIを使った投資の可能性を捨てることができず、少しずつ我流で取引を始め、そんな中で仮想通貨に辿り着きました。6月末にシロ学長の教えに従って、BYBITでコピートレードから始めましたが中々思うように行かず、MEXCに土俵を移して先物トレードを始めました。レバレッジをたっぷり使って、危険な投資で少し儲けて気を大きくし大損するということを繰り返し、負けを取り戻そうと焦って益々危険な投資行動がエスカレート、変な画面に遭遇し、騙される酷い目に遭いました。それ以来、たった一週間程度の仮想通貨投資経験でしたが、怖くなり、一ヶ月近く、見るのも考えるのも嫌だという最低の精神状態を経験した末、ほんの数週間前からやっと、復活を期してページを開いてみることができるようになったものの、まだ怖くて取引に手を出せずにいます。怖くて見るのも嫌だった時には、もう大嫌いと思いましたが、今はやはり自信を持って取り組むことさえできれば好きなんだなぁとひしひし感じ、自信を持って取り組むことができることへの憧れを強く感じています。是非シロ学長の様に自信を持って取引をし、自信を持ってそれを語れるようになりたい！今心からそう思って、熱意を持って学び続けることを心に誓って、個別説明会に申し込みさせていただきたいと思います。よろしくお願いします。巷には、既に億万長者なのにも関わらず、そうでない人を助けたいと言いながら、結局はお金儲けの道具としか見ていないような人が溢れています。シロ学長のように、有料級を無料で惜しみなく提供し続ける高貴なお方は稀有です。心から尊敬します。 | U31: 坂本はるみ | X31: 45884.845 | Y31: 45884.845 | Z31: https://sub.shirogakucho-web3.com/p/jwf1rmhnKm4S | AA31: 115.69.5.199 | AB31: 解除済 | AC31: 45969.494
A32: ha9DXTnxKJRS | B32: JYrVb5FakncW | C32: 9356dff92a589a573dfd24fec382d1af | D32: 仮想通貨大好き | E32: 大沼 駿介 | F32: greenteas77777@gmail.com | S32: ある | T32: 毎日非常に応援しています | U32: 大沼駿介 | X32: 45884.845 | Y32: 45884.845 | Z32: https://sub.shirogakucho-web3.com/p/jwf1rmhnKm4S | AA32: 103.5.140.180 | AB32: 解除済 | AC32: 45893.886
A33: jHr90M7oVglK | B33: YQfl3RAQuSBF | C33: 239d5cbce2aab8a938084c4668bbe623 | D33: Hiroyuki Chikaraishi | E33: 力石 弘行 | F33: Izaiyak@gmail.com | Q33: From 2020からの初心者です。 | R33: 1000000円 | S33: ある | T33: 色々と勉強をしてみたく、参加希望します。 | U33: HiroC | X33: 45884.846 | Y33: 45884.846 | Z33: https://sub.shirogakucho-web3.com/p/jwf1rmhnKm4S | AA33: 125.26.174.91 | AB33: 購読中
A34: jtcrxqbgxXIZ | E34: 松井 幸弘 | F34: den35738@protonmail.com | Q34: 初心者 投資経験６ヵ月 | R34: 25万くらい | S34: ある | T34: 仮想通貨投資の本質って何でしょう？とても気になってしまいました。 | U34: 松井幸弘 | X34: 45884.85 | Y34: 45884.85 | Z34: https://sub.shirogakucho-web3.com/p/jwf1rmhnKm4S | AA34: 2404:7a84:84c1:100:e1fc:631a:bc04:4d88 | AB34: 購読中
A35: lkiTsoOTe43s | E35: 大江 昌夫 | F35: oe.masao@gmail.com | Q35: シロ学長のYouTubeを見て始めたばかりの初心者です | R35: 45万円程度 | S35: ない | T35: いつもわかりやすい動画ありがとうございます。私は親が残した負の財産がありその返済のため社畜のように働いてきましが、50を目の前にし自分の資産もなければ借金をただ返していくだけの人生は嫌だなと思い、残りの人生を幸せに過ごしたい！と思いこの春からニーサを始めました。いつまで健康でいられるかわからないし、元気なうちに余裕のある生活をしたいと思い、初めて観たYouTubeでシロ学長の動画に出会いました。私もシロ学長のように人生を豊かに生きてみたいと思い、申し込みさせて頂きました。どうぞよろしくお願いいたします。 | U35: 大江昌夫 | X35: 45884.852 | Y35: 45884.852 | Z35: https://sub.shirogakucho-web3.com/p/jwf1rmhnKm4S | AA35: 126.125.21.38 | AB35: 購読中
A36: O8HT8W9oYAer | E36: ホシコ カズヒサ | F36: kazu515257@ymail.ne.jp | Q36: 初心者 | R36: 20万 | S36: ある | T36: 自営業で年金もあてにならず、どうしたものかと、何かを始めなければ不安ですので出来る出来ないはさておき申し込みしました。 | U36: 星子和久 | X36: 45884.853 | Y36: 45884.853 | Z36: https://sub.shirogakucho-web3.com/p/jwf1rmhnKm4S | AA36: 240b:c010:610:20db:6c25:48f9:5fc3:ffe2 | AB36: 購読中
A37: e5bzaimJ0oCm | E37: 小高 和博 | F37: odaka_kazuhiro@yahoo.co.jp | Q37: 初心者 | S37: ある | T37: 他人の判断に頼るのでなく、また感情に振り回されることなく、一定のルールに基づき、淡々と売り買いできるようなりたいです。 | U37: 小高和博 | X37: 45884.869 | Y37: 45884.869 | Z37: https://sub.shirogakucho-web3.com/p/jwf1rmhnKm4S | AA37: 240b:c010:4d2:7ace:d5dc:c626:efdc:349e | AB37: 解除済 | AC37: 45904.611
A38: K6gh2TnaMGjA | E38: 山路 基洋 | F38: kmd249yamaji@gmail.com | Q38: 初心者 | R38: 20万円以下 | S38: ない | T38: 動画はなるほどと思える内容でした。取引所を選ぶ必要があることには、目から鱗です今まで考えたこともありませんでした。 | U38: 山路基洋 | X38: 45884.872 | Y38: 45884.872 | Z38: https://sub.shirogakucho-web3.com/p/jwf1rmhnKm4S | AA38: 133.149.93.80 | AB38: 購読中
A39: kZVFSY6jTtn7 | F39: taishomachi.tamai.y@gmail.com | Q39: 初心者 | R39: 20万以下 | S39: ある | T39: いつも動画ありがとうございます。数ある | U39: 玉井雄也 | X39: 45884.876 | Y39: 45884.876 | Z39: https://sub.shirogakucho-web3.com/p/jwf1rmhnKm4S | AA39: 123.219.23.204 | AB39: 購読中
A40: RaT6PpTaGPLl | F40: skyworudwairudo@gmail.com | Q40: 未経験 | R40: 26万円 | S40: ない | T40: はじめまして、自分は仮想通貨投資については全くの無知ですが、別な投資活動としてはバイナリーをやっていますが。安定とはほぼ遠く、何か未来があり、安定を得られる投資は無いかと考え、ユーチューブでたまたまシロ学長の動画を見つけ拝見させて頂き投資をもう一度しんけ | U40: obata | X40: 45884.885 | Y40: 45884.885 | Z40: https://sub.shirogakucho-web3.com/p/jwf1rmhnKm4S | AA40: 240b:c010:622:3dbe:35f1:424b:3e0c:e7ce | AB40: 購読中
A41: 9JUCLuCqZxKw | E41: 大和谷 あやか | F41: dpqyr077@gmail.com | Q41: 数年複数のコインを長期保有ベースで購入、レンディング | R41: 100万円程度 | S41: ある | T41: 情報提供ありがとうございます | U41: 大和谷 あやか | X41: 45884.893 | Y41: 45884.893 | Z41: https://sub.shirogakucho-web3.com/p/jwf1rmhnKm4S | AA41: 86.105.144.131 | AB41: 購読中
A42: bSaA89EhGCtp | E42: 奥脇 秀一 | F42: o9072768700@gmail.com | Q42: 初心者 | R42: 25万 | S42: ある | T42: 今まで散々ダマされてきたのでいい加減に優良な案件で少しでも稼ぎたい！ | U42: 奥脇秀一 | X42: 45884.897 | Y42: 45884.897 | Z42: https://sub.shirogakucho-web3.com/p/jwf1rmhnKm4S | AA42: 153.186.218.174 | AB42: 購読中
A43: 5diFEtzHQGIM | E43: 山﨑 洋美 | F43: yamasaki.4s@icloud.com | Q43: 初心者 | R43: 30万円以下 | S43: ない | T43: ビットコインに興味があり、よく動画を見せてもらってます。 | U43: 山﨑 洋美 | X43: 45884.897 | Y43: 45884.897 | Z43: https://sub.shirogakucho-web3.com/p/jwf1rmhnKm4S | AA43: 2400:4152:1c2:6d00:b417:f915:224a:3ceb | AB43: 購読中/配信エラー
A44: yukWZK1Z47vx | E44: 小林 祐也 | F44: yu2906yu2906yu@gmail.com | Q44: 半年ほど前から始めた初心者 | R44: 30万程度 | S44: ある | T44: 投資詐欺にあい大損してしまい借金をしてしまいました。それでも将来の不安から投資は大切だと思っています。でもなにを始めたらいいのかわからなく仮想通貨がすごいという話から仮想通貨の動向を追うようになり凄さを実感してきました。ただどのように投資していけばよいとかがわからずシロ学長の動画を拝見してGMOコインの口座開設をしてみたり実際に仮想通貨を買ってみたりしました。説明がわかりやすく何度も繰り返して説明してもらえるのでもっと仮想通貨の理解を深めて損をしない投資と嫁や子供に苦労をかけない将来を築けたらと思い個別説明会に申し込みをしました。 | U44: 小林祐也 | X44: 45884.898 | Y44: 45884.898 | Z44: https://sub.shirogakucho-web3.com/p/jwf1rmhnKm4S | AA44: 2001:268:9031:ea9:d5c6:df3a:417e:3775 | AB44: 購読中
A45: WJ2mMhgMBNax | E45: 野中 由花 | F45: yukaena0502@gmail.com | Q45: 中級者？？ | R45: パート | S45: ない | T45: 仮想通貨について、詳しくお聞きしたいです！ | U45: 野中 由花 | X45: 45884.9 | Y45: 45884.9 | Z45: https://sub.shirogakucho-web3.com/p/jwf1rmhnKm4S | AA45: 27.122.11.38 | AB45: 購読中
A46: nDojvuOZ0LNn | E46: 足立 欣永 | F46: adachi.yoshinaga.4241@gmail.com | Q46: ほぼ初心者です。今年1月にWEB3という世界を知りました。BTCの積立とスポット買いで0.09BTCまで到達したところです。 | R46: 50万円 | S46: ある | T46: 有料のトレードスクールに興味は有りますが、初心者にはハードルが高く感じます。でもこの動画を見て、どんな手法なのか自分で確かめてみたいです。どうかご教授下さい。正直申しますと、人生後がなく、老後破綻ほぼ間違いない状態なのです。家族もおり、子供はまだ小さいうえ、住宅ローンも3500万。何としてでも、経済的に安心して生活が送れるようにしたいと望んでます。是非審査を通していただけないでしょうか。 | U46: 足立欣永 | X46: 45884.903 | Y46: 45884.903 | Z46: https://sub.shirogakucho-web3.com/p/jwf1rmhnKm4S | AA46: 202.75.124.191 | AB46: 購読中
A47: MhQcZHaxBNFC | E47: 福井 孝正 | F47: 99jastnet@gmail.com | Q47: 初心者 | R47: ゼロ | S47: ある | T47: 感情に左右されずに取引きしてビジネスとして取り組みたいと考えていたので、期待してます！宜しくお願いします！ | U47: たいちょ | X47: 45884.907 | Y47: 45884.907 | Z47: https://sub.shirogakucho-web3.com/p/jwf1rmhnKm4S | AA47: 27.111.11.174 | AB47: 購読中
A48: n6b8UWtCyfnm | E48: 菊口 貴久 | F48: tkiku62@gmail.com | Q48: 初心者 | R48: 50万程度 | S48: ない | T48: 動画説明のようにまずは無料で参加して人生を変えたいです。 | U48: 菊口 貴久 | X48: 45884.908 | Y48: 45884.908 | Z48: https://sub.shirogakucho-web3.com/p/jwf1rmhnKm4S | AA48: 2001:318:2014:cc6:9ccb:bc85:4f25:e6a8 | AB48: 購読中
A49: dg6nV369iwT7 | E49: 藤井 龍咲 | F49: lizrose258@gmail.com | Q49: 初心者 | R49: なし | S49: ない | T49: 株の資金を利用して、お金を増やせたらと考えているます。 株は長期保有しかしておらず、売買をあまりしてこなっかった。 このタイミングがわかれば仮想通貨で役に立つのにと思っています。 最近は本人のやる気で無料で勉強もできます。ただいざ自分の資産を投じるとなると結局売買できず、タイミングがイマイチわからないです。 | U49: 藤井龍咲 | X49: 45884.912 | Y49: 45884.912 | Z49: https://sub.shirogakucho-web3.com/p/jwf1rmhnKm4S | AA49: 2.56.252.131 | AB49: 購読中
A50: 0HJI7zUns4kq | E50: 佐伯 孝樹 | F50: ta.sa.one6@gmail.com | Q50: 初級者 | R50: 70万円程度 | S50: ない | T50: Youtube分かりやすくて応援してます！ | U50: 佐伯 孝樹 | X50: 45884.917 | Y50: 45884.917 | Z50: https://sub.shirogakucho-web3.com/p/jwf1rmhnKm4S | AA50: 2001:f71:5180:2200:ea62:ae01:d8ed:233 | AB50: 購読中
A51: HbrSNckGhhI7 | E51: 松本 貴子 | F51: kirrakirat@yahoo.co.jp | Q51: 初心者 | R51: 20 | U51: 松本貴子 | X51: 45884.92 | Y51: 45884.92 | Z51: https://sub.shirogakucho-web3.com/p/jwf1rmhnKm4S | AA51: 2001:268:9b88:439c:4410:4f3a:78d5:f0cb | AB51: 解除済 | AC51: 45892.371
A52: aF1vIVscTGoT | E52: 鈴木 大亮 | F52: daisuke0776@gmail.com | Q52: 初心者 | R52: 50万 | S52: ある | T52: よろしくお願いします！ | U52: 鈴木大亮 | X52: 45884.92 | Y52: 45884.92 | Z52: https://sub.shirogakucho-web3.com/p/jwf1rmhnKm4S | AA52: 2405:6584:4260:9b00:7052:ef2a:96cb:50f5 | AB52: 購読中
A53: yGUovgPYEv28 | E53: 若園 繁博 | F53: shigetaka0427@gmail.com | Q53: 初心者 | R53: 100万 | S53: ある | T53: 今年の4月頃から仮想通貨投資を始めました。長期投資をメインにしたいのですが、少ない元手ではなかなか増えませんので、短期で資産を増やす方法を知りたい。 | U53: 若園繁博 | X53: 45884.922 | Y53: 45884.922 | Z53: https://sub.shirogakucho-web3.com/p/jwf1rmhnKm4S | AA53: 2405:6585:c200:1f00:4d0c:1ab2:7110:ff12 | AB53: 購読中
A54: 1hkZhZCwD4s1 | E54: 太田 明 | F54: armando.tomigusuku@gmail,com | Q54: 初心者 | R54: 30万円 | S54: ある | T54: とてもわかりやすい動画ありがとうございます。インジケータを使ったテクニカル分析に興味あります。 | U54: 豊見城アルマンド | X54: 45884.922 | Y54: 45884.922 | Z54: https://sub.shirogakucho-web3.com/p/jwf1rmhnKm4S | AA54: 2806:102e:b:9db0:a1d6:c73:1f29:a3ba | AB54: 解除済/配信エラー | AC54: 45904.316
A55: 5fz74JCWdZIT | E55: 新田 佳祐 | F55: itumodachinikansya@gmail.com | Q55: 初心者 | R55: 25万 | S55: ない | T55: 初心者で右も左もわかりません。初心者がすべき事また、資金が少なくても利益を出せる方法はありますか？ | U55: 新田佳祐 | X55: 45884.927 | Y55: 45884.927 | Z55: https://sub.shirogakucho-web3.com/p/jwf1rmhnKm4S | AA55: 153.184.134.137 | AB55: 購読中
A56: 4B3RBY2muqcW | E56: 根本 勝利 | F56: toto.oku19@outlook.jp | Q56: 初心者? | R56: 40万程度 | S56: ある | T56: 定年退職を間近に控え、収入源を探してこちらにきました。再就職の低賃金で苦しむより、自由な時間て豊かさを手にするために頑張ります。 | U56: 根本勝利 | X56: 45884.934 | Y56: 45884.934 | Z56: https://sub.shirogakucho-web3.com/p/jwf1rmhnKm4S | AA56: 122.214.0.241 | AB56: 購読中
A57: vwWRy0GUovy1 | E57: 久保田 貢 | F57: mitsu_1962@yahoo.com | Q57: 初心者、現在少額を現物保有 | R57: 35万 | S57: ある | T57: トレードも少しは経験ありますが全然勝てませんでしたシロ学長から学んで資産を増やしていきたいと思います宜しくお願い致します | U57: 久保田貢 | X57: 45884.935 | Y57: 45884.935 | Z57: https://sub.shirogakucho-web3.com/p/jwf1rmhnKm4S | AA57: 2400:2200:7e2:c46b:acad:1b29:d105:dfca | AB57: 購読中
A58: sh3YziFr4mhC | B58: 6sx81ummJ2xI | C58: 765bb6bec03384d5d3281713968d74b7 | D58: ノリさん | E58: 古谷 徳史 | F58: nori853853@gmail.com | Q58: 初心者 半年ぐらい前から情報を集め出したぐらいです | R58: 50万円 | S58: ある | T58: 一所懸命勉強して頑張りますので、どうぞよろしくお願いします。 | U58: 古谷徳史 | X58: 45884.935 | Y58: 45884.935 | Z58: https://sub.shirogakucho-web3.com/p/jwf1rmhnKm4S | AA58: 2400:2200:9ec:7b61:c854:4a36:311c:a364 | AB58: 購読中
A59: cYVRqOTbrTS6 | E59: 野口 博史 | F59: hiroshi.n197891@gmail.com | Q59: 初心者 | R59: 40万円ていと | S59: ある | T59: 勉強して活用したいです。 | U59: 野口博史 | X59: 45884.941 | Y59: 45884.941 | Z59: https://sub.shirogakucho-web3.com/p/jwf1rmhnKm4S | AA59: 240b:c010:4d1:1fb3:f9bd:3f6b:fe82:251d | AB59: 解除済 | AC59: 45890.338
A60: SQ0kQRgMeOHt | E60: 松田 豊貴 | F60: toyoking1040@hotmail.com | Q60: 初心者 | R60: 50万程度 | S60: ない | U60: 松田 豊貴 | X60: 45884.943 | Y60: 45884.943 | Z60: https://sub.shirogakucho-web3.com/p/jwf1rmhnKm4S | AA60: 2400:2200:613:8c6a:a93d:437a:b0ab:740a | AB60: 購読中
A61: qy5biW6VI3cP | F61: turu.427@me.com | Q61: 初心者 | R61: 30万以下 | S61: ない | T61: 仮想通貨をどのようにすれば稼いでいけるのかもっと良く知りたいです。老後を安心して過ごす手立てが欲しいです。 | U61: 鶴田隆司 | X61: 45884.952 | Y61: 45884.952 | Z61: https://sub.shirogakucho-web3.com/p/jwf1rmhnKm4S | AA61: 221.254.46.193 | AB61: 購読中
A62: unkJhEsGnMrf | E62: とだ ひさえ | F62: 39@aramaa.net | Q62: 年数から言えば中級程度 | R62: 年金のみで月にすれば9万円 | S62: ない | T62: 資産10億有るので貴重な授業も無料でいい、皆に幸せになって欲しいからというところに感動しました。 | U62: とだひさえ | X62: 45884.955 | Y62: 45884.955 | Z62: https://sub.shirogakucho-web3.com/p/jwf1rmhnKm4S | AA62: 240f:92:c384:1:38de:ef40:776:1dbd | AB62: 購読中/配信エラー
A63: FetZ6v1tZPAj | E63: 深谷 尚史 | F63: orange7.x@gmail.com | Q63: 初心者 | R63: 40万程度 | S63: ある | T63: 仮想通貨を収入源にしたいと考えています。ご教授お願い致します。 | U63: 尚史 | X63: 45884.962 | Y63: 45884.962 | Z63: https://sub.shirogakucho-web3.com/p/jwf1rmhnKm4S | AA63: 240d:1a:3d9:2a00:5922:6443:ef3a:a3c8 | AB63: 購読中
A64: VXgkRvo2V1yZ | F64: s515m1213t84@yahoo.co.jp | Q64: 初心者 | R64: 50万ていど | S64: ない | T64: 初めまして！老後の資金や仕事への不安、解消したいです。宜しくお願いします | U64: 河村正志 | X64: 45884.962 | Y64: 45884.962 | Z64: https://sub.shirogakucho-web3.com/p/jwf1rmhnKm4S | AA64: 2001:268:d2ce:65d3:48c8:3b65:c3d2:4e0 | AB64: 購読中
A65: I6s1Kzlhwc4Z | E65: 北平 一喜 | F65: kitakazu3333@icloud.com | Q65: 初心者 | R65: 50万円程度 | S65: ない | T65: 私もシロ学長と同様、投資詐欺に合い500万を失いました。子供の為に貯めた大学資金の300万円と借金を200万円を失いました。なんとかして復活したいと考えております。お力をお貸し頂けませんでしょうか？何卒、宜しくお願い致します。?? | U65: 北平一喜 | X65: 45884.963 | Y65: 45884.963 | Z65: https://sub.shirogakucho-web3.com/p/jwf1rmhnKm4S | AA65: 210.203.212.17 | AB65: 購読中/配信エラー
A66: X1PmVidLGUm1 | E66: 小原 正行 | F66: obamasa911@gmail.com | R66: 20 | S66: ない | U66: 小原正行 | X66: 45884.966 | Y66: 45884.966 | Z66: https://sub.shirogakucho-web3.com/p/jwf1rmhnKm4S | AA66: 2001:3b0:22:4256:3679:1123:ea8b:9e93 | AB66: 解除済 | AC66: 45927.116
A67: fGCAlxkCQYTY | E67: 平田 和子 | F67: kazuko0413@icloud.com | Q67: 未経験 | R67: 20万円以下 | S67: ない | U67: 平田 和子 | X67: 45884.967 | Y67: 45884.967 | Z67: https://sub.shirogakucho-web3.com/p/jwf1rmhnKm4S | AA67: 2001:ce8:102:eb7f:8cb7:1a3d:c827:17f8 | AB67: 購読中/配信エラー
A68: Sxap6PfCJrQB | E68: 田中 友晴 | F68: tmhr1958@ybb.ne.jp | Q68: 初心者 | R68: 50万円程度 | S68: ない | T68: これから世界の金融で革命が起こる前夜と考えてます。トランプ大統領がアメリカで進めている仮想通貨大国の波に日本人として乗っていこう考えていて、その方法をシロ学長から学ぼうと思ってます。 | U68: 田中友晴 | X68: 45884.968 | Y68: 45884.968 | Z68: https://sub.shirogakucho-web3.com/p/jwf1rmhnKm4S | AA68: 2400:2412:540:df00:cd99:117b:1346:e44c | AB68: 購読中
A69: 97vOR89rVGRl | E69: 中原 久美子 | F69: velmukumiko@gmail.com | Q69: 初心者 | R69: 30万以下 | S69: ある | T69: 仮想通貨は2年程前からしております。下がった時に買うという知識しかないので、もっと勉強して資産を増やしていきたいです。 | U69: 中原久美子 | X69: 45884.972 | Y69: 45884.972 | Z69: https://sub.shirogakucho-web3.com/p/jwf1rmhnKm4S | AA69: 2400:2200:4fe:6ee4:868f:aa59:2f9a:ad9e | AB69: 購読中
A70: fQhIoay8kuGK | E70: 田中 加奈子 | F70: kanako.masita@ezweb.ne.jp | Q70: 初心者 | R70: 25万程度 | S70: ある | T70: 最近、シロ学長の動画を見つけました。還暦を迎えた私でもトレードできるでしょうか。なんとかして生活を変えたいです。 | U70: 田中加奈子 | X70: 45884.979 | Y70: 45884.979 | Z70: https://sub.shirogakucho-web3.com/p/jwf1rmhnKm4S | AA70: 2001:268:9231:ae5f:484b:21ac:bde1:91d7 | AB70: 解除済 | AC70: 45889.93
A71: rebwWSYWrMfe | E71: 外山広行 トヤマヒロユキ | F71: toyaman23-2525@docomo.ne.jp | Q71: 初心者 | R71: 40万円 | S71: ない | T71: 私らの星でいて下さい。 | U71: 外山広行 | X71: 45884.98 | Y71: 45884.98 | Z71: https://sub.shirogakucho-web3.com/p/jwf1rmhnKm4S | AA71: 193.114.24.49 | AB71: 解除済 | AC71: 45909.892
A72: ryNQzAbS6QG1 | B72: ZkmxOYfS4LTx | C72: 54216c0dfe301b8c86c493be17143c64 | D72: 河本浩和 | E72: 河本 浩和 | F72: deepmeruado@yahoo.co.jp | Q72: 口座開設済みだが、投資自体は未経験 | R72: 20万程度 | S72: ある | T72: 半信半疑な所もありますが、とても興味深い内容で、仮想通貨で月利30％以上で稼ぎたいと真剣に考えています。 | U72: 河本浩和 | X72: 45884.983 | Y72: 45884.983 | Z72: https://sub.shirogakucho-web3.com/p/jwf1rmhnKm4S | AA72: 61.27.149.15 | AB72: 解除済 | AC72: 45888.553
A73: X3vO1KUl5BX8 | E73: 藤縄 大 | F73: hiroshi.fujinawa@gmail.com | Q73: 中級者 | R73: 50万程度 | S73: ある | T73: いつも貴重な学びの機会ありがとうございます。 YouTubeをとても興味深く拝見しております。 ROI30%は夢のような数字だと思います！！ 動画の中で、チラリと出てくる様々なキーワードが興味深く、レンディングや借り入れ、BYBITのボットなど様々な方法を複合されて、1% 1%、利回りを上げられていることと思います。 私は、2021年から現物の仮想通貨を小額保有していましたが、今年の3月頃から主にBIBITボットを使用した戦略で戦っております。 AIと試行錯誤しながら戦略を組んでいますが相談できる人や仲間がいないため、これで良いのか、リスクリワードの取り方や資産配分は適切か、個人でBTC保有し会社に貸し付けて会社で運用すべきなのか..などいつもモヤモヤしておりました。 bybit歴も浅い初心者ですが ぜひ、お話しさせていただける機会を頂けますと幸いです。 よろしくお願いいたします。 | U73: 藤縄大 | X73: 45885.004 | Y73: 45885.004 | Z73: https://sub.shirogakucho-web3.com/p/jwf1rmhnKm4S | AA73: 240b:12:21a2:1300:382a:65cf:f314:77b8 | AB73: 解除済 | AC73: 45889.084
A74: A88JHulSRgpV | E74: 富田 絵理 | F74: noizayfrance222@yahoo.co.jp | Q74: 未経験、勉強中 | R74: 20万以下 | S74: ある,ない | T74: いつも拝見しています。今年からYouTubeを見るようになり、仮想通貨に興味が出て購入したいと思うようになりました。子供には不自由な思いをさせたくないと、シングルで頑張って働いても希望が見えにくいので、経済的、時間的に余裕のある暮らしを実現するためにもシロ学長さんのように仮想通貨で成功したいです。ゆとりがないのでスクールは興味はあっても現実的に厳しいですが、宜しくお願いします。 | U74: 富田絵理 | X74: 45885.009 | Y74: 45885.009 | Z74: https://sub.shirogakucho-web3.com/p/jwf1rmhnKm4S | AA74: 121.82.120.230 | AB74: 購読中
A75: WhMKcjvjonYr | F75: cap3853@icloud.com | Q75: 新人 | R75: 20まんぃか | S75: ある | T75: Now or never | U75: Miyako. Keisyu | X75: 45885.016 | Y75: 45885.016 | Z75: https://sub.shirogakucho-web3.com/p/jwf1rmhnKm4S | AA75: 221.118.20.76 | AB75: 購読中
A76: 6QKLGudtjH2a | E76: 石井 珠莉 | F76: tamariworld@hotmail.com | Q76: 初心者 | R76: 学びの時間にしているため、現在無職です。 | S76: ない,ある | T76: 貴重な情報をありがとうございます！シングルマザーで寝る間もなくずっと働いてきたので、これからは不労収入と思い投資を勉強し始めました。現行の株などよりボラティリティが激しい暗号資産の方が、若くない私には(時間がないので)希望が持てます。日本経済の失われた30年間も巻き返したいです！よろしくお願い致します。 | U76: 池田珠美 | X76: 45885.025 | Y76: 45885.025 | Z76: https://sub.shirogakucho-web3.com/p/jwf1rmhnKm4S | AA76: 27.55.77.18 | AB76: 購読中
A77: etByImjGryLw | F77: toshiya3.soso@gmail.com | Q77: まぁまぁ | R77: 100万円 | S77: ない | T77: 頑張ります | U77: 清水俊也 | X77: 45885.034 | Y77: 45885.034 | Z77: https://sub.shirogakucho-web3.com/p/jwf1rmhnKm4S | AA77: 240b:10:aba2:9500:d47:46e4:b48b:84ca | AB77: 購読中
A78: ajg30EvGfyCs | E78: 井上 ムツ子 | F78: inouemutti@gmail.com | Q78: 初心者 | R78: ２０万円以下 | S78: ある | T78: 2016年にある塾に入ったからの投資でした。その翌年のICOではかなりの投資をつぎ込んで来ましたが大方は詐欺に匹敵というか微塵にも資金は失ってきました。今となっては当時のBTC,ADAコインについては悔しい気持ちもありますが、これからはトレードを優先して稼げるようにすることが目標となってます。ただ年金受給者となり、資金的に寂しいところも大ですがシロさんの手法で稼いでいけたら最高と思ってます。よろしくお願いします。 | U78: 井上ムツ子 | X78: 45885.037 | Y78: 45885.037 | Z78: https://sub.shirogakucho-web3.com/p/jwf1rmhnKm4S | AA78: 2400:2410:ffe0:c800:38c6:84f6:3491:c891 | AB78: 購読中
A79: jnHgHmZj8PD9 | E79: 有川 航平 | F79: puko25082508@gmail.com | Q79: 初心者(BTCの積立、レンディング実施中、DeFI勉強中) | R79: 15～20万以下 | S79: ある | T79: 興味があり、ぜひお話を聞いてみたいです！よろしくお願いいたします！ | U79: 有川航平 | X79: 45885.053 | Y79: 45885.053 | Z79: https://sub.shirogakucho-web3.com/p/jwf1rmhnKm4S | AA79: 2400:4152:83a0:fe00:f933:7266:8688:c2ac | AB79: 解除済 | AC79: 45888.173
A80: Ioj0uHHtIjDy | B80: nkL1y5lDBiFj | C80: 5391ff918f92392e796db71f06e93ba6 | D80: Doreml773 | E80: 轟 洋子 | F80: paribmw369@gmail.com | Q80: 未経験ですが1年前からやろうと思っていました。 | R80: 20万円前後 | S80: ある | T80: シロ学長が全身全霊で教えますと言っていたのを2度目の動画で聴き、私も全身全霊で、受けようとおもいました。いろいろ有料無料の動画を見ましたが、高くて本気でやる気にはなりませんでした。は仮想通貨は、これから絶対必要となる通貨だと、思っていますので頑張ります！ | U80: 轟 洋子 | X80: 45885.077 | Y80: 45885.077 | Z80: https://sub.shirogakucho-web3.com/p/jwf1rmhnKm4S | AA80: 2400:4051:c841:100:c855:8884:3f3a:74ac | AB80: 解除済 | AC80: 45958.657
A81: dM58zI150Kxs | E81: 有井 淳一 | F81: planet7198@gmail.com | Q81: 初心者 | R81: 30万円以下 | S81: ある | T81: 妻を幸せにしたい。この思いで本業+副業をがんばってきましたが、資産が全然増えないです。「現状を変えないと...」と強く考えています。ぜひ、力を貸していただきたいです。 | U81: 有井淳一 | X81: 45885.097 | Y81: 45885.097 | Z81: https://sub.shirogakucho-web3.com/p/jwf1rmhnKm4S | AA81: 240f:69:6c51:1:7d6c:b5db:c351:1170 | AB81: 購読中
A82: bcQ5vYDZi8OP | F82: info@irb.jp | Q82: 初心者 | R82: 60万円 | S82: ある | T82: 引き続きよろしくお願いします。 | U82: 佐藤一成 | X82: 45885.151 | Y82: 45885.151 | Z82: https://sub.shirogakucho-web3.com/p/jwf1rmhnKm4S | AA82: 2400:4151:75e0:cc00:51c2:5634:adb3:4403 | AB82: 購読中
A83: XKcNjRmyfHXu | E83: 藤巻 健司 | F83: ken964fu@ezweb.ne.jp | Q83: 未経験者 | R83: 28万円位 | S83: ある | T83: 有益な情報をありがとうございます | U83: 藤巻 健司 | X83: 45885.178 | Y83: 45885.178 | Z83: https://sub.shirogakucho-web3.com/p/jwf1rmhnKm4S | AA83: 2001:268:98ef:3343:4565:97bd:bd11:6a53 | AB83: 解除済 | AC83: 45903.875
A84: BX7HIQPFHzex | E84: 別井 秀一 | F84: shubetui@icloud.com | Q84: 初心者 | R84: 50 | S84: ない | T84: XRP XLM XDCを2030年までガチホしようと思っていますどう思われますか | U84: shu31 | X84: 45885.237 | Y84: 45885.237 | Z84: https://sub.shirogakucho-web3.com/p/jwf1rmhnKm4S | AA84: 240a:61:50f6:5ba3:1144:ef64:a077:c411 | AB84: 購読中
A85: XhxKm9Wsf9PT | F85: jjto2no@gmail.com | Q85: 初心者 | R85: 20万前後 | S85: ある | T85: 師匠！よろしくお願いします！ | U85: 知子 | X85: 45885.257 | Y85: 45885.257 | Z85: https://sub.shirogakucho-web3.com/p/jwf1rmhnKm4S | AA85: 240b:c020:643:b308:f167:3eae:e535:4cb7 | AB85: 購読中
A86: SrsYDbKxA5bx | E86: 宮内 富美夫 | F86: fm6.28fumi@gmail.com | Q86: 中級 | R86: 20万以下 | S86: ある,ない | T86: 仮想通貨投資自体は6年前位から初めてますが、いかに資産を増やすかという部分がいまいち理解出来てない、以前有料のスクールも課金した事もありますが、メリットがありませんでした。最近シロ学長の動画を、見て根本的な作業を理解して来ましたので、是非資産運用の正しいやり方を学びたいです。 | U86: 宮内 富美夫 | X86: 45885.32 | Y86: 45885.32 | Z86: https://sub.shirogakucho-web3.com/p/jwf1rmhnKm4S | AA86: 60.87.162.94 | AB86: 解除済 | AC86: 45888.411
A87: l68NjHymyGI1 | F87: white-rider-111@ezweb.ne.jp | Q87: 初心者 | R87: ２０万 | S87: ない | T87: 絶対やり抜き頑張って努力します。 | U87: 河野裕史 | X87: 45885.321 | Y87: 45885.321 | Z87: https://sub.shirogakucho-web3.com/p/jwf1rmhnKm4S | AA87: 240f:6d:cf74:1:9dde:a91b:8e1f:3ce5 | AB87: 購読中
A88: QciKLdpdqBz0 | E88: 松浦 章展 | F88: akikoko0110@yahoo.co.jp | Q88: 初心者 | R88: 20万 | S88: ある | T88: 私の目的は日本人の金融リテラシーがない人にこの暗号資産や資産運用方法を教えることで、1人でも多く人々が豊かな表情になる仕事がしたいです。私はまだ会社員でそちら側に踏み出す為にはまず私も資金が必要だと自負しております。お金を追うのではなく、お金を使い本当にしたい価値を提供できる人物になる為に機会を与えて頂ければ幸いです。 | U88: 松浦章展 | X88: 45885.323 | Y88: 45885.323 | Z88: https://sub.shirogakucho-web3.com/p/jwf1rmhnKm4S | AA88: 2001:ce8:144:b55b:51e9:6304:bec4:6105 | AB88: 解除済 | AC88: 45901.81
A89: rKXCWrWZw3u7 | E89: 間瀬 順司 | F89: mase.mase.masse@gmail.com | Q89: 初心者 | R89: 30万以下 | S89: ない | T89: お世話になります。いつも勉強させていただきありがとうございます。今後ともよろしくお願いいたします。 | U89: 間瀬 順司 | X89: 45885.332 | Y89: 45885.332 | Z89: https://sub.shirogakucho-web3.com/p/jwf1rmhnKm4S | AA89: 240b:c020:653:618e:98eb:95e6:76af:a16a | AB89: 解除済 | AC89: 45888.331
A90: FQfoj3UIqwhe | E90: 杉川 直子 | F90: sugikawa705@gmail.com | Q90: 初心者～ | R90: 20～25万円 | S90: ある | T90: 5年以内に1BTC購入できるよう知識をつけ実践したいです。よろしくお願いいたします。 | U90: 杉川直子 | X90: 45885.335 | Y90: 45885.335 | Z90: https://sub.shirogakucho-web3.com/p/jwf1rmhnKm4S | AA90: 240d:1a:1c3:6400:10ef:9150:2019:993f | AB90: 購読中
A91: c3mV2WrTOWzN | E91: 松村 博敏 | F91: yuntakuy@gmail.com | Q91: 初心者 | R91: 約10万円 | T91: 改めまして松村博敏と申します。宜しく御願い致します。暗号資産に関して経緯を簡単に説明させて戴きます。私が最初に暗号資産の事を知ったのはBTCが出始めの頃、話を聞いたり友人から紹介されたりして暗号資産と言う物が在ると聴いて居ました。ですが興味事態は在りましたが手は出せずに居ました。そして2017年に暗号資産系のプロダクトローンチに引っ掛かり、でもその頃は人生のどん底でも在ったので申し込みたくても申し込む事が出来ずプロダクトローンチ事態には被害には遭いませんでしたが其の他の件で十数万騙し取られたりしました。また其の時に此れからバブルが来てxrp等が暴騰すると言う情報は得てましたが其れを完全に信じる事は出来ず迷っている内に時が過ぎコインチェックの事件が起きました。その頃に知人からアドバイスを受け暗号資産に付いて教える代わりに知人が良いと言うまでは投資には一切関わるなと言われました。今ならその理由は身に沁みて理解出来ますが其時の私には理解出来ず御金欲しさに生活資金にまで手を付けて数万円暗号資産を購入したりしてました。当然生活資金に手を付けて居るので生活が苦しくなり購入してせっかく利益が出てもその都度換金する、でも御金が欲しいのでまた生活資金に手を付け購入すると言う事を繰り返して来ました。結果自分が投資すべき時に纏まった御金を用意出来ず肝心な時に投資出来ないと言うのが今の現状です。現在は脱炭素系のXELSプロジェクや幹細胞系のsctプロジェクトに投資し順調に進めば今年の11月以降に在る程度纏まった収益を得られる予定です。そして其れを元手にbtc等に分散投資をしたいと考えて居ります。そして次のバブルが来る頃には私の目標を達成する為に今から準備をして行きその頃には本格的な活動をして行きたいと考えて居ます。乱雑乱文で読み辛いと思いますが申し訳御在ません。 | U91: 松村博敏 | X91: 45885.336 | Y91: 45885.336 | Z91: https://sub.shirogakucho-web3.com/p/jwf1rmhnKm4S | AA91: 27.230.34.34 | AB91: 解除済 | AC91: 45912.395
A92: M7aYDtZMUE57 | E92: 中田 雄之 | F92: nakata@kindly-link.com | Q92: 中級 | R92: 70万程度 | S92: ある | T92: よろしくお願いします。 | U92: 中田 雄之 | X92: 45885.343 | Y92: 45885.343 | Z92: https://sub.shirogakucho-web3.com/p/jwf1rmhnKm4S | AA92: 61.46.0.172 | AB92: 購読中
A93: Qnt4R4VPmu4R | B93: NCh9l86UT2pX | C93: fed83fcf6177274178d9aae0ce1af3fb | D93: 宮本 義孝 | E93: 宮本 義孝 | F93: mymtystk@gmail.com | Q93: 初心者 | R93: 50万円程度 | S93: ある | T93: ２度目のメールになります。暗号資産について投資対象として認識したのは3カ月ほど前になります。ブロックチェーンの技術等についてはAIと同じく社会を変革する内容だと認識しています。仮想通貨の購入については、大きな変動リスクのあるものでもあり、わからないことも多いので、少額を少しずつ買っています。シロ学長の投資戦略については、リスクを最小限にする合理的な方法だと感じますので、是非取り組ませて頂ければと思います。私は既に高齢ですが、資産は多くありません。すぐに動かせる資金も少額にとどまります。是非、堅実な方法で着実に資産を増やして行きたいと考えています。よろしくお願いします。思います | U93: 宮本義孝 | X93: 45885.349 | Y93: 45885.349 | Z93: https://sub.shirogakucho-web3.com/p/jwf1rmhnKm4S | AA93: 58.70.182.228 | AB93: 購読中
A94: SrsYDbKxA5bx | B94: 04IPCLiBa02U | C94: 06132689cc49605d221c27a124004b51 | D94: F.Miya | E94: 宮内 富美夫 | F94: fm6.28fumi@gmail.com | Q94: 約8年 | R94: 30万程度 | S94: ない | T94: 再度送らせてもらいます、動画を全部見る前に申し込みしてしまったので改めて送らせていただきます。仮想通貨自体は、約8年位前に誘われて、始めましたが、ビットコインで、多少利益は出ましたがシロ学長の言う通り、どう資産を増やしていいのか、どれが正しいのか？YouTubeの動画を見て、いわれるままに行動した結果損をした事もあり、自分自身事業をしておりますが、事業における借入もあり、中々返済もままならない状況が続いております。現実事業以外の部分で資産を増やして、本業の部分に投資して行きたいと思っております、有料のスクールにも入った事もありますが、一歩的な配信だけで、身になる部分がなかったです。本業もあるので時間的にも限られているので、この機会に一から学びプレミアムロジックをマスターして、安定した利益を確保する努力をして行きたいと思います。仮想通貨に関しては夢を持っていますのでご指導宜しくお願い致します。 | U94: 宮内富美夫 | X94: 45885.364 | Y94: 45885.364 | Z94: https://sub.shirogakucho-web3.com/p/jwf1rmhnKm4S | AA94: 60.87.162.94 | AB94: 解除済 | AC94: 45888.411
A95: WD18t5q4Zi24 | E95: 倉田 正美 | F95: masamiaug2@softbank.ne.jp | Q95: 初心者 | R95: 70万 | S95: ある | T95: シロ学長のYouTubeをきっかけに仮想通貨を購入しました。大変感謝しています。どのYouTubeよりもわかりやすく、頭にすんなり入ってきました。ぜひシロ学長から色々学びたいと思い、申し込みをしております。どうぞよろしくお願い致します。 | U95: 倉田正美 | X95: 45885.364 | Y95: 45885.364 | Z95: https://sub.shirogakucho-web3.com/p/jwf1rmhnKm4S | AA95: 2404:7a80:9e20:2200:3555:b0d3:2a7e:8e22 | AB95: 購読中
A96: 5mfCt38ryN66 | E96: まつもと しげお | F96: sig@mzmt.jp | Q96: 未経験 | R96: 50万円以上 | S96: ある | T96: リップルに500万円入れて、3億円になるのを待とうかと考えてます。 | U96: 松本茂生 | X96: 45885.372 | Y96: 45885.372 | Z96: https://sub.shirogakucho-web3.com/p/jwf1rmhnKm4S | AA96: 2001:ce8:117:4245:820:eb99:3239:1346 | AB96: 解除済 | AC96: 45888.866
A97: 8gKJgGQayrgE | E97: 水上 めぐみ | F97: megu_mi0901@yahoo.co.jp | Q97: 初心者です | R97: 30万少々 | S97: ある | T97: 人生を変えたいです。よろしくお願いします！ | U97: 水上めぐみ | X97: 45885.39 | Y97: 45885.39 | Z97: https://sub.shirogakucho-web3.com/p/jwf1rmhnKm4S | AA97: 2a09:bac2:43bc:dc::16:21d | AB97: 解除済 | AC97: 45898.087
A98: rUuuLhUKaUrg | E98: 田井 輝彦 | F98: teruhiko0226@gmail.com | Q98: 初級 | R98: 45万 | S98: ある | T98: よろしくお願いします | U98: 田井輝彦 | X98: 45885.391 | Y98: 45885.391 | Z98: https://sub.shirogakucho-web3.com/p/jwf1rmhnKm4S | AA98: 124.110.165.151 | AB98: 購読中
A99: lLxlCkCxbjjP | E99: 中田 由香利 | F99: delight.yukari@gmail.com | Q99: 初心者 | R99: ２０万以下 | S99: ある | T99: 初心者なので不安も一杯ですが、ぜひ頑張りたいと思います！よろしくお願いします。 | U99: 中田 由香利 | X99: 45885.453 | Y99: 45885.453 | Z99: https://sub.shirogakucho-web3.com/p/jwf1rmhnKm4S | AA99: 61.46.0.172 | AB99: 解除済 | AC99: 45888.303
A100: ze996CzF6RkW | E100: 久保 誠三 | F100: syamunekokubo@gmail.com | Q100: 初心者 | R100: 20万くらい | S100: ない | T100: よろしくお願いいたします。 | U100: 久保誠三 | X100: 45885.466 | Y100: 45885.466 | Z100: https://sub.shirogakucho-web3.com/p/jwf1rmhnKm4S | AA100: 153.189.19.252 | AB100: 購読中
...

Sheet 審査フォーム回答者②
A1: 全シナリオ共通読者ID | B1: LINE友だちID | C1: アカウント共通LINE友だちID | D1: LINE登録名 | E1: お名前 | F1: メールアドレス | G1: 姓 | H1: 名 | I1: フリガナ | J1: 電話番号 | K1: 郵便番号 | L1: 都道府県 | M1: 市区町村 | N1: 番地 | O1: マンション名 部屋番号 | P1: イベント参加日 | Q1: 登録経路 | R1: 配信基準日時 | S1: 登録日時 | T1: 登録元ページ | U1: 登録元IP | V1: ステータス | W1: 解除日時
A2: OYgI3YxHf4x4 | B2: iE7YkVVxHURT | C2: 711cb87b164b6b4ff959b801da956d3b | D2: Ta.m | E2: 増山 武彦 | F2: take.mas1969@gmail.com | R2: 45884.796 | S2: 45884.796 | V2: 購読中
A3: Qnt4R4VPmu4R | B3: NCh9l86UT2pX | C3: fed83fcf6177274178d9aae0ce1af3fb | D3: 宮本 義孝 | E3: 宮本 義孝 | F3: mymtystk@gmail.com | R3: 45884.796 | S3: 45884.796 | V3: 購読中
A4: qYXDaYqfsb3E | B4: AWFj3RtXK8Af | C4: 7ff0db4da65101568b655003744f1efa | D4: Kushida | E4: 櫛田 直 | F4: nao394d@gmail.com | R4: 45884.796 | S4: 45884.796 | V4: 購読中
A5: TllJMv4INfZr | B5: znieTIWhoyIe | C5: 4745124a6fab280d500d5b5bc0436c18 | D5: soulword | E5: 吉田 隆 | F5: ty11055yoshi@gmail.com | R5: 45884.797 | S5: 45884.797 | V5: 解除済 | W5: 45911.229
A6: XwUE3ZIRp5VH | B6: 0CiiwIqvDegW | C6: 0e7959b74f2c1e8bdeb99423750b6e80 | D6: かつや | E6: 藤原 克哉 | F6: fujiwara.katsuya@gmail.com | R6: 45884.797 | S6: 45884.797 | V6: 購読中
A7: gTFnGp2CVJtw | B7: EBymfg1BrZES | C7: ec755f96bd6c26454464151c60c79b2d | D7: mizupapa | E7: 水間 将誉 | F7: mmizuma@gmail.com | R7: 45884.8 | S7: 45884.8 | V7: 購読中
A8: gwDgFYKmElzE | B8: yDIk3BoZeqR3 | C8: f32681baef82e68704334dce9cfdc16a | D8: Kazumi | E8: 木村 和美 | F8: millenniumstar8@gmail.com | R8: 45884.802 | S8: 45884.802 | V8: 購読中
A9: 5ZYHptx28VYZ | B9: HIt9BGTn8QAx | C9: 032bf3422ee6913e9518fc1892774c9c | D9: さかい ゆみ | E9: 酒井 由美 | F9: yamayu0462@gmail.com | R9: 45884.803 | S9: 45884.803 | V9: 解除済 | W9: 45888.282
A10: Dh9hYNpEZJoJ | B10: 5dxHy3wf8JuC | C10: 173b50897c439f8eca6169371586a546 | D10: おさるさん | E10: 黄本 章雄 | F10: smile.jack317@docomo.ne.jp | R10: 45884.803 | S10: 45884.803 | V10: 購読中
A11: d2TSp63d0Y1g | B11: hEnTAzMQHnWV | C11: 87145cde3da7c71653c1ae5fdf6f6c0a | D11: 武田慎吾 | F11: s.takeda000@icloud.com | R11: 45884.805 | S11: 45884.805 | V11: 購読中
A12: Z6CbT7fbjgwh | B12: wPseBRsfNRze | C12: 34cf842afa10a7fb5d9a87df6e865e17 | D12: 藤原和憲 | E12: 藤原 和憲 | F12: heckel371@yahoo.co.jp | R12: 45884.807 | S12: 45884.807 | V12: 購読中
A13: X0pIRMuMuiYa | B13: mibpTNVHyME2 | C13: 299e5c1accf9f1c7213697d13baa408f | D13: 関戸 陽 | F13: yoh.sekido@gmail.com | R13: 45884.818 | S13: 45884.818 | V13: 購読中
A14: qVjoToPccxkm | B14: tiGbCCIe38YS | C14: 39de4a5d2abe7a60676496959d9a8600 | D14: maru | E14: 丸山 満男 | F14: dady152@gmail.com | R14: 45884.822 | S14: 45884.822 | V14: 購読中
A15: Y4I87GbIs9QD | B15: fBA0pxPCPonl | C15: 3d91444815d3d53a5bf376f537ef3a89 | D15: 滝本 晴子 | E15: 滝本 晴子 | F15: supuring0709@gmail.com | R15: 45884.825 | S15: 45884.825 | V15: 解除済 | W15: 45890.327
A16: maBjLxvUHlnP | B16: dcbF8Y6rnmxV | C16: 8ecea127199fdda7860f8950bcdf8796 | D16: 登田英樹 | E16: 登田 英樹 | F16: towahide091q@gmail.com | R16: 45884.826 | S16: 45884.826 | V16: 購読中
A17: fcWKgGmD9sB8 | B17: WzWF52TxUV65 | C17: 99a656201e9cc95a28d0d8672543a226 | D17: Tomoki Harano(原野智哉) | E17: 原野 智哉 | F17: tom1966_11@hotmail.com | R17: 45884.826 | S17: 45884.826 | V17: 購読中
A18: t395JN2sySTE | B18: y0Yn1zr0AwuA | C18: 2d6a72a101c76352dd457f12cd479b63 | D18: noriko okuzumi | E18: 藤堂 憲子 | F18: britelightone1@gmail.com | R18: 45884.827 | S18: 45884.827 | V18: 購読中
A19: RuqbIbOkDaq1 | B19: CqWKnrgnrO99 | C19: eaf287255ce8f1f6d5e91e9ef74cbc11 | D19: Akihiro Uno | E19: 鵜野 彰洋 | F19: au09054720010@gmail.com | R19: 45884.828 | S19: 45884.828 | V19: 購読中
A20: g557hMPanUIH | B20: 2vrE9VfGGjKH | C20: 0088a7b12641ce538886bd3bb7f350ab | D20: 川津明日香 | F20: jamiko0705@yahoo.co.jp | R20: 45884.828 | S20: 45884.828 | V20: 購読中
A21: 3DEdw698qXc9 | B21: nQxlzA5y83CX | C21: 1089d5db2375c78edea1c971c9bde99c | D21: NAKAYAMA 2175 | E21: 中山 和人 | F21: mikura1969@icloud.com | R21: 45884.83 | S21: 45884.83 | V21: 購読中
A22: hOWycn41njc4 | B22: q2qrBVEKGSRW | C22: 93abf46bf00b2235d5fa590e1a7789e8 | D22: ゆうこ | E22: 原口 優子 | F22: y6649851@gmail.com | R22: 45884.831 | S22: 45884.831 | V22: 購読中
A23: Ioj0uHHtIjDy | B23: nkL1y5lDBiFj | C23: 5391ff918f92392e796db71f06e93ba6 | D23: Doreml773 | E23: 轟 洋子 | F23: paribmw369@gmail.com | R23: 45884.832 | S23: 45884.832 | V23: 解除済 | W23: 45958.657
A24: 5v4cfPq1B1Ci | B24: ZSimEw0sC5VP | C24: 27a13c19884520b33b8c6932505a0a23 | D24: 高橋 敬 | F24: ktkhs@gmail.com | R24: 45884.833 | S24: 45884.833 | V24: 購読中/配信エラー
A25: hQ4TwjsverNH | B25: 94ZJ16u0hl5l | C25: 8b073b858e01f381032a7352e0d588f6 | D25: ＨＩＲＯ | E25: 鈴木 宏一 | F25: h-suzuki@daiwack.co.jp | R25: 45884.835 | S25: 45884.835 | V25: 解除済 | W25: 45907.63
A26: Y8n9eeYqJews | B26: ZjnBM60dhCCZ | C26: f76bb4fdaf454d8f08cc323eca0df0e7 | D26: fukufukuhappy | E26: 福島 修 | F26: w.rainey-0840@kuf.biglobe.ne.jp | R26: 45884.837 | S26: 45884.837 | V26: 購読中
A27: ha9DXTnxKJRS | B27: JYrVb5FakncW | C27: 9356dff92a589a573dfd24fec382d1af | D27: 仮想通貨大好き | E27: 大沼 駿介 | F27: greenteas77777@gmail.com | R27: 45884.845 | S27: 45884.845 | V27: 解除済 | W27: 45893.886
A28: 2enDrQfa7Fb9 | B28: j60DJ58kKIK8 | C28: 04964b86a05ce9f10bd1970d70ced9d7 | D28: Harumi Sakamoto | E28: 坂本 はるみ | F28: kotobukiwithin@gmail.com | R28: 45884.845 | S28: 45884.845 | V28: 解除済 | W28: 45969.494
A29: jHr90M7oVglK | B29: YQfl3RAQuSBF | C29: 239d5cbce2aab8a938084c4668bbe623 | D29: Hiroyuki Chikaraishi | E29: 力石 弘行 | F29: Izaiyak@gmail.com | R29: 45884.847 | S29: 45884.847 | V29: 購読中
A30: jtcrxqbgxXIZ | B30: FKZMMK2G7RcF | C30: e767ff95d3ff93c06938a06c0f04b7e5 | D30: 松井幸弘 | E30: 松井 幸弘 | F30: den35738@protonmail.com | R30: 45884.851 | S30: 45884.851 | V30: 購読中
A31: lkiTsoOTe43s | B31: Gs4Fnp25gxkU | C31: 100b9ef4b5e78c70e87374780f3726ae | D31: トキＯＥ | E31: 大江 昌夫 | F31: oe.masao@gmail.com | R31: 45884.852 | S31: 45884.852 | V31: 購読中
A32: O8HT8W9oYAer | B32: UAcGxQGZfGHs | C32: c860dcf3f2303e13cccd14c38219f0fc | D32: K-HOSHI | E32: ホシコ カズヒサ | F32: kazu515257@ymail.ne.jp | R32: 45884.853 | S32: 45884.853 | V32: 購読中
A33: e5bzaimJ0oCm | B33: QobJHz86zqGy | C33: 603ac8f03210242416dda698e3dba6f7 | D33: かず | E33: 小高 和博 | F33: odaka_kazuhiro@yahoo.co.jp | R33: 45884.872 | S33: 45884.872 | V33: 解除済 | W33: 45904.611
A34: K6gh2TnaMGjA | B34: FHldvJlqvpku | C34: e0fe3dd802ba0f6a219e70f6f4a26c52 | D34: 山路基洋 | E34: 山路 基洋 | F34: kmd249yamaji@gmail.com | R34: 45884.873 | S34: 45884.873 | V34: 購読中
A35: 9JUCLuCqZxKw | B35: D6MaBLUwEyH8 | C35: 23b6f60a0f4c643c3f6d19bc5ecd8079 | D35: Ayaka.K | E35: 大和谷 あやか | F35: dpqyr077@gmail.com | R35: 45884.894 | S35: 45884.894 | V35: 購読中
A36: bSaA89EhGCtp | B36: WXIUFLLU8h9i | C36: 162eb2de76cb93c90ef7655ce9ba8c61 | D36: しゅう様 | E36: 奥脇 秀一 | F36: o9072768700@gmail.com | R36: 45884.897 | S36: 45884.897 | V36: 購読中
A37: 5diFEtzHQGIM | B37: v44xlbwwWzlg | C37: 6fd53f627333ecd43f8c1d7d250ff3de | D37: Hiromi Yamasaki | E37: 山﨑 洋美 | F37: yamasaki.4s@icloud.com | R37: 45884.898 | S37: 45884.898 | V37: 購読中/配信エラー
A38: yukWZK1Z47vx | B38: LGAKaWys8uld | C38: 035fb698a537b5503cf6243b9f5595c7 | D38: 小林祐也 | E38: 小林 祐也 | F38: yu2906yu2906yu@gmail.com | R38: 45884.9 | S38: 45884.9 | V38: 購読中
A39: WJ2mMhgMBNax | B39: 6o4p1yigKo5z | C39: f852f2a33656c5a66b02df335ab2a37f | D39: 由花 | E39: 野中 由花 | F39: yukaena0502@gmail.com | R39: 45884.9 | S39: 45884.9 | V39: 購読中
A40: nDojvuOZ0LNn | B40: vovH37WjXMWr | C40: 1cc6f6dc8bed90f015294afe628aafe7 | D40: @ADAKIN_WEB3 | E40: 足立 欣永 | F40: adachi.yoshinaga.4241@gmail.com | R40: 45884.904 | S40: 45884.904 | V40: 購読中
A41: MhQcZHaxBNFC | B41: Q6b9EZNIRxHo | C41: 239aaa491310a098dd3e4ab9fc2c47a9 | D41: Taicho???? | E41: 福井 孝正 | F41: 99jastnet@gmail.com | R41: 45884.907 | S41: 45884.907 | V41: 購読中
A42: n6b8UWtCyfnm | B42: N8gEXvVvdtyN | C42: 49e95842adda639e667bb62de071e930 | D42: たか | E42: 菊口 貴久 | F42: tkiku62@gmail.com | R42: 45884.908 | S42: 45884.908 | V42: 購読中
A43: dg6nV369iwT7 | B43: cmtAQyHInJd9 | C43: 01e37fc84b620187ab28a9a2bb445cf9 | D43: Liz | E43: 藤井 龍咲 | F43: lizrose258@gmail.com | R43: 45884.913 | S43: 45884.913 | V43: 購読中
A44: 0HJI7zUns4kq | B44: fvUapXtyAlj1 | C44: 9c6326c600744d6aa104bcfd9d9b6341 | D44: takaki SAIKI | E44: 佐伯 孝樹 | F44: ta.sa.one6@gmail.com | R44: 45884.918 | S44: 45884.918 | V44: 購読中
A45: HbrSNckGhhI7 | B45: veaEZMsJd6Wu | C45: b330e7c0e7507f88afdaa960171529ba | D45: たあさん358 | E45: 松本 貴子 | F45: kirrakirat@yahoo.co.jp | R45: 45884.92 | S45: 45884.92 | V45: 解除済 | W45: 45892.371
A46: aF1vIVscTGoT | B46: oI3We2hS1VLD | C46: de72fdc08f509261f9db9cc680d75a36 | D46: Daisuke | E46: 鈴木 大亮 | F46: daisuke0776@gmail.com | R46: 45884.921 | S46: 45884.921 | V46: 購読中
A47: yGUovgPYEv28 | B47: sbtZWQPmDkOp | C47: 59ca315bb83054a00ea251e5ae6c97a4 | D47: しげ | E47: 若園 繁博 | F47: shigetaka0427@gmail.com | R47: 45884.922 | S47: 45884.922 | V47: 購読中
A48: 1hkZhZCwD4s1 | B48: vxQufk7l17Gy | C48: 34b8bae1a973ba9e6ca834dc561259ae | D48: Akira Ota (Miguel) | E48: 太田 明 | F48: armando.tomigusuku@gmail,com | R48: 45884.922 | S48: 45884.922 | V48: 解除済/配信エラー | W48: 45904.316
A49: 5fz74JCWdZIT | B49: 3hU5tN2IA8D3 | C49: 2bd6de67291978d5a12c9f82465e10bc | D49: Nitta Keisuke | E49: 新田 佳祐 | F49: itumodachinikansya@gmail.com | R49: 45884.928 | S49: 45884.928 | V49: 購読中
A50: 4B3RBY2muqcW | B50: oiRSMtEcSmA9 | C50: 4e957959599c46d13ac0a2246ba98b24 | D50: toto | E50: 根本 勝利 | F50: toto.oku19@outlook.jp | R50: 45884.934 | S50: 45884.934 | V50: 購読中
A51: vwWRy0GUovy1 | B51: xEvbmWC3Si1X | C51: 3e91635d6508004daaf60a02ee521c72 | D51: Mitsugu | E51: 久保田 貢 | F51: mitsu_1962@yahoo.com | R51: 45884.935 | S51: 45884.935 | V51: 購読中
A52: sh3YziFr4mhC | B52: 6sx81ummJ2xI | C52: 765bb6bec03384d5d3281713968d74b7 | D52: ノリさん | E52: 古谷 徳史 | F52: nori853853@gmail.com | R52: 45884.936 | S52: 45884.936 | V52: 購読中
A53: cYVRqOTbrTS6 | B53: DBHkJHMTfaqV | C53: a07f320c7016d4d0866bb420d7e930b4 | D53: 野口 博史 | E53: 野口 博史 | F53: hiroshi.n197891@gmail.com | R53: 45884.941 | S53: 45884.941 | V53: 解除済 | W53: 45890.338
A54: SQ0kQRgMeOHt | B54: lLnfFKKHDoAu | C54: cba1430e514a16d2774fec9b80f3ffd0 | D54: 松田 豊貴 | E54: 松田 豊貴 | F54: toyoking1040@hotmail.com | R54: 45884.944 | S54: 45884.944 | V54: 購読中
A55: qy5biW6VI3cP | B55: sEeYUIO4FRZZ | C55: cf701e131f2fea1f0caed33a3acd747f | D55: タカ | F55: turu.427@me.com | R55: 45884.952 | S55: 45884.952 | V55: 購読中
A56: unkJhEsGnMrf | B56: 8ZVeHatJn17h | C56: d4197e3998f7c72b5946fa9ac980e6cb | D56: ひさえちゃん | E56: とだ ひさえ | F56: 39@aramaa.net | R56: 45884.955 | S56: 45884.955 | V56: 購読中/配信エラー
A57: FetZ6v1tZPAj | B57: AlDYLz41HNjI | C57: 87197acc116e805357142d6c637e2d83 | D57: 尚史 | E57: 深谷 尚史 | F57: orange7.x@gmail.com | R57: 45884.963 | S57: 45884.963 | V57: 購読中
A58: I6s1Kzlhwc4Z | B58: b2n9GJZIUAnk | C58: c6229437736c4b0be921f15773e61842 | D58: カブ～キ | E58: 北平 一喜 | F58: kitakazu3333@icloud.com | R58: 45884.964 | S58: 45884.964 | V58: 購読中/配信エラー
A59: X1PmVidLGUm1 | B59: ZZQQ6YyagEX0 | C59: a61124e454a58dc49affc293adc790a0 | D59: 小原 正行 | E59: 小原 正行 | F59: obamasa911@gmail.com | R59: 45884.966 | S59: 45884.966 | V59: 解除済 | W59: 45927.116
A60: fGCAlxkCQYTY | B60: TSJz3VuJoutb | C60: fa7dcaf982a86bb9038aae6d5f8bcdc9 | D60: catkazuko | E60: 平田 和子 | F60: kazuko0413@icloud.com | R60: 45884.967 | S60: 45884.967 | V60: 購読中/配信エラー
A61: Sxap6PfCJrQB | B61: 7RACNUXkGEtn | C61: a1087dae2388838b203dd814ab0e6a18 | D61: トモ | E61: 田中 友晴 | F61: tmhr1958@ybb.ne.jp | R61: 45884.97 | S61: 45884.97 | V61: 購読中
A62: 97vOR89rVGRl | B62: ZNOHrZEj20Ue | C62: d7d4a14406501c5ee990e8bfa8651050 | D62: くみこ | E62: 中原 久美子 | F62: velmukumiko@gmail.com | R62: 45884.973 | S62: 45884.973 | V62: 購読中
A63: fQhIoay8kuGK | B63: 4kBEbaM8ofz7 | C63: 401639219fec5c42a84b36bf642f2185 | D63: Kanako? | E63: 田中 加奈子 | F63: kanako.masita@ezweb.ne.jp | R63: 45884.979 | S63: 45884.979 | V63: 解除済 | W63: 45889.93
A64: rebwWSYWrMfe | B64: rXoPbiUp0YuB | C64: c452e0259109160958b68b8db2b0f742 | D64: 外山広行 | E64: 外山広行 トヤマヒロユキ | F64: toyaman23-2525@docomo.ne.jp | R64: 45884.98 | S64: 45884.98 | V64: 解除済 | W64: 45909.892
A65: ryNQzAbS6QG1 | B65: ZkmxOYfS4LTx | C65: 54216c0dfe301b8c86c493be17143c64 | D65: 河本浩和 | E65: 河本 浩和 | F65: deepmeruado@yahoo.co.jp | R65: 45884.983 | S65: 45884.983 | V65: 購読中
A66: X3vO1KUl5BX8 | B66: 9bpFlom0XxIW | C66: 8719ce1a299e9c3975e67a4244e1f8fd | D66: 藤縄 大 | E66: 藤縄 大 | F66: hiroshi.fujinawa@gmail.com | R66: 45885.004 | S66: 45885.004 | V66: 解除済 | W66: 45889.084
A67: A88JHulSRgpV | B67: CGaKl8JJKvug | C67: 68de48dc958ad1f5fc008131d85467ba | D67: 富田 絵理 | E67: 富田 絵理 | F67: noizayfrance222@yahoo.co.jp | R67: 45885.011 | S67: 45885.011 | V67: 購読中
A68: 6QKLGudtjH2a | B68: 0JOzeRIOEVKi | C68: 3d449f5fb08e2341a7aec31d05440818 | D68: たまちゃん | E68: 石井 珠莉 | F68: tamariworld@hotmail.com | R68: 45885.026 | S68: 45885.026 | V68: 購読中
A69: jnHgHmZj8PD9 | B69: 2hqM4WIwWhYb | C69: a1e7cc4e7ecc124c7b60b2465e6a07a6 | D69: コウ | E69: 有川 航平 | F69: puko25082508@gmail.com | R69: 45885.055 | S69: 45885.055 | V69: 解除済 | W69: 45888.173
A70: dM58zI150Kxs | B70: xLbVgNMRmqOV | C70: 7ce1b7af81547595315799d373b6b05e | D70: JA | E70: 有井 淳一 | F70: planet7198@gmail.com | R70: 45885.097 | S70: 45885.097 | V70: 購読中
A71: bcQ5vYDZi8OP | B71: Ba3EjrLuoI0a | C71: ab5df874a85e4158444a9b3e19c786b1 | D71: s.kazu | F71: info@irb.jp | R71: 45885.152 | S71: 45885.152 | V71: 購読中
A72: XKcNjRmyfHXu | B72: 1JSN7BqATzQ5 | C72: a0004b387698e55941e63f31e1323968 | D72: 藤巻健司 | E72: 藤巻 健司 | F72: ken964fu@ezweb.ne.jp | R72: 45885.178 | S72: 45885.178 | V72: 解除済 | W72: 45903.875
A73: BX7HIQPFHzex | B73: gm4879oPjWwC | C73: 9a30010c0c807d0f382ab4293e9de5c2 | D73: 別井秀一 | E73: 別井 秀一 | F73: shubetui@icloud.com | R73: 45885.238 | S73: 45885.238 | V73: 購読中
A74: XhxKm9Wsf9PT | B74: HKJ7GvakSkpe | C74: 82c0fb054c4fae7d2b7a66c6078b17bd | D74: 知子 | F74: jjto2no@gmail.com | R74: 45885.258 | S74: 45885.258 | V74: 購読中
A75: l68NjHymyGI1 | B75: lHtCOWgrKMbJ | C75: 633ec21eb3f07dbd9ac5891002816999 | D75: Kouno | F75: white-rider-111@ezweb.ne.jp | R75: 45885.321 | S75: 45885.321 | V75: 購読中
A76: SrsYDbKxA5bx | B76: 04IPCLiBa02U | C76: 06132689cc49605d221c27a124004b51 | D76: F.Miya | E76: 宮内 富美夫 | F76: fm6.28fumi@gmail.com | R76: 45885.321 | S76: 45885.321 | V76: 解除済 | W76: 45888.411
A77: QciKLdpdqBz0 | B77: eh8HsD0I4OUG | C77: 3938fe00f01dd045dc271d441afaffc0 | D77: あき | E77: 松浦 章展 | F77: akikoko0110@yahoo.co.jp | R77: 45885.323 | S77: 45885.323 | V77: 解除済 | W77: 45901.81
A78: rKXCWrWZw3u7 | B78: m7vU4MM5QOlG | C78: f52fb844dca74d67d3c2860348b2603d | D78: 間瀬順司 | E78: 間瀬 順司 | F78: mase.mase.masse@gmail.com | R78: 45885.333 | S78: 45885.333 | V78: 解除済 | W78: 45888.331
A79: FQfoj3UIqwhe | B79: cYHm2AYNQkW7 | C79: d1131a8db63c25f74a18694ce607a432 | D79: 杉川 Naoko | E79: 杉川 直子 | F79: sugikawa705@gmail.com | R79: 45885.336 | S79: 45885.336 | V79: 購読中
A80: M7aYDtZMUE57 | B80: i5wt65h9C2sw | C80: e465c3f1b75b0bc7ac666ce249c0e2f9 | D80: Nakata | E80: 中田 雄之 | F80: nakata@kindly-link.com | R80: 45885.343 | S80: 45885.343 | V80: 購読中
A81: WD18t5q4Zi24 | B81: 8rii0Xi6AZft | C81: 2774ca850c1ec5f69b0dabf322b742db | D81: 倉田 正美 | E81: 倉田 正美 | F81: masamiaug2@softbank.ne.jp | R81: 45885.364 | S81: 45885.364 | V81: 購読中
A82: 5mfCt38ryN66 | B82: KmPDlcLETu1O | C82: e4a1717683bc3df45e47ea279b49e7fc | D82: まつもと | E82: まつもと しげお | F82: sig@mzmt.jp | R82: 45885.372 | S82: 45885.372 | V82: 解除済 | W82: 45888.866
A83: 8gKJgGQayrgE | B83: sXXt1BP0ENpl | C83: b6fce42938742947297647f2808e495d | D83: メグ | E83: 水上 めぐみ | F83: megu_mi0901@yahoo.co.jp | R83: 45885.39 | S83: 45885.39 | V83: 解除済 | W83: 45898.087
A84: rUuuLhUKaUrg | B84: KhP7KkCxFJfc | C84: 94cf1adffa85ea8d8cf6f06f68e3954f | D84: 田井 | E84: 田井 輝彦 | F84: teruhiko0226@gmail.com | R84: 45885.392 | S84: 45885.392 | V84: 購読中
A85: lLxlCkCxbjjP | B85: GTqbJnXG45hV | C85: 5f566d91ba5ff9447d45b87b97f120db | D85: Yukari Nakata | E85: 中田 由香利 | F85: delight.yukari@gmail.com | R85: 45885.453 | S85: 45885.453 | V85: 解除済 | W85: 45888.303
A86: ze996CzF6RkW | B86: mJhFdLJ3uqmW | C86: 5492b51638eea0dda4d7f2124f636b81 | D86: 白黒の猫 | E86: 久保 誠三 | F86: syamunekokubo@gmail.com | R86: 45885.467 | S86: 45885.467 | V86: 購読中
A87: YDwpY6hYapr1 | B87: tRYSaalU3Frc | C87: bc244cfda20c808b244fc25a9386d60c | D87: えいじ | E87: 根本 栄治 | F87: nemo10812@gmail.com | R87: 45885.525 | S87: 45885.525 | V87: 解除済 | W87: 45889.008
A88: xgYHoeuYw3tY | B88: fDTRIz6UKHuM | C88: 5b7a72437574e2e2ead2341f2fe248af | D88: 年夫 | E88: 吉田 年夫 | F88: lionheart8139@gmail.com | R88: 45885.582 | S88: 45885.582 | V88: 解除済 | W88: 45888.896
A89: Bn1rd6QiLDVQ | B89: 5eVCJTdspr2A | C89: ddf4d3375ab76ddfeb28f31b36c6dd31 | D89: 萩広 | E89: 萩原 広昭 | F89: hagi160aki@yahoo.co.jp | R89: 45885.677 | S89: 45885.677 | V89: 解除済 | W89: 46035.183
A90: t1ZYvGBZpbrM | B90: EFAOvRFQV8OL | C90: dd7e82fbec084700e2d03538e84be233 | D90: 隆司 | E90: 遠藤 隆司 | F90: blunmoon@icloud.com | R90: 45885.711 | S90: 45885.711 | V90: 購読中/配信エラー
A91: Xn7Gip8tYe30 | B91: MdZKJQIstWM1 | C91: 7c71b188e75cc7c83c604efa0fedb489 | D91: Akiko Kawasaki | E91: 川崎 亜紀子 | F91: akiko1k@hotmail.com | R91: 45885.747 | S91: 45885.747 | V91: 購読中
A92: hBLsujfcq9Ru | B92: bU3a376Vckuz | C92: 2dd8cf125fb6bc0c3c07fcec0ef7a659 | D92: Ahn Bokyoung | F92: byahn0815@gmail.com | R92: 45885.826 | S92: 45885.826 | V92: 購読中
A93: CHKaBmAZIxJc | B93: oa8yJoqCFXNf | C93: 25b0897a76dd0ad40adcc9e9d531fa45 | D93: なつみ | E93: 野村 奈津美 | F93: wtipxr2236@yahoo.co.jp | R93: 45885.859 | S93: 45885.859 | V93: 解除済 | W93: 45894.316
A94: 0mCtEM1pTbXT | B94: vzVyAKG5Zgxd | C94: 9e9bc8e8c92ac215c14c8fc73f032970 | D94: takao.w | F94: gfm100taka@gmail.com | R94: 45885.863 | S94: 45885.863 | V94: 購読中
A95: 1Y9EPRJzL79Y | B95: RHMsKMq1Hico | C95: b94a3c984a089fd49953b89c20741928 | D95: sakata | E95: 坂田 剛士 | F95: tuyosaka13@gmail.com | R95: 45885.865 | S95: 45885.865 | V95: 解除済 | W95: 45903.494
A96: H3o3rx1IuCv0 | B96: jswCKrd0hNOu | C96: 1dbb1eeb7aaa464f7cb53288e28e5720 | D96: TERU | E96: 佐藤 輝雄 | F96: satetesa_3883@yahoo.co.jp | R96: 45885.923 | S96: 45885.923 | V96: 購読中
A97: uKVxsz0a8Bxi | B97: UHXF5f44PmFu | C97: 8e1a25992d742a9cdc06ca8632945273 | D97: ピリカ | E97: 玉井 秀人 | F97: dracolulu2018@yahoo.ne.jp | R97: 45885.926 | S97: 45885.926 | V97: 購読中
A98: w46xP0fbGJme | B98: Qqey3PALduA4 | C98: 72017f5f08e91a77ec290505bb1b2808 | D98: 津田 | E98: 津田 将司 | F98: t.boys1206@gmail.com | R98: 45885.975 | S98: 45885.975 | V98: 解除済 | W98: 45887.901
A99: osGsfVdadMXo | B99: lj1aumRbl2ys | C99: e8e1e8170290e1043a9a083f1c8fa79d | D99: タピオカミルクティー甘さMAX | F99: nonsan0622@gmail.com | R99: 45886.11 | S99: 45886.11 | V99: 購読中
A100: 4qTmIUy3Ppxz | B100: QSIKIEB9SBKq | C100: f88d288ae6fecec0ca2ff116173fcfcb | D100: 鈴木京子 | E100: 鈴木 京子 | F100: kyoko1206804@gmail.com | R100: 45886.162 | S100: 45886.162 | V100: 解除済 | W100: 45889.895
...

Sheet 予約者①
A1: 全シナリオ共通読者ID | B1: LINE友だちID | C1: アカウント共通LINE友だちID | D1: LINE登録名 | E1: お名前 | F1: メールアドレス | G1: 姓 | H1: 名 | I1: フリガナ | J1: 電話番号 | K1: 郵便番号 | L1: 都道府県 | M1: 市区町村 | N1: 番地 | O1: マンション名 部屋番号 | P1: イベント参加日時 | Q1: 登録経路 | R1: 配信基準日時 | S1: 登録日時 | T1: 登録元ページ | U1: 登録元IP | V1: ステータス | W1: 解除日時
A2: yXDNT4WwPTV1 | E2: test test | F2: private@jun-otsu.com | G2: test | H2: test | J2: 9069622079 | P2: 45877.646 | R2: 45874.959 | S2: 45874.959 | T2: https://sub.shirogakucho-web3.com/event/5qGgQUWRlr3f/confirm | U2: 124.122.128.223 | V2: 購読中
A3: Y8n9eeYqJews | B3: ZjnBM60dhCCZ | C3: f76bb4fdaf454d8f08cc323eca0df0e7 | D3: fukufukuhappy | E3: 福島 修 | F3: w.rainey-0840@kuf.biglobe.ne.jp | G3: 福島 | H3: 修 | J3: 9061242998 | P3: 45887.812 | R3: 45885.816 | S3: 45885.816 | T3: https://sub.shirogakucho-web3.com/event/5qGgQUWRlr3f/confirm | U3: 2001:268:c205:3680:61b9:45fb:2948:a802 | V3: 購読中
A4: OYgI3YxHf4x4 | B4: iE7YkVVxHURT | C4: 711cb87b164b6b4ff959b801da956d3b | D4: Ta.m | E4: 増山 武彦 | F4: take.mas1969@gmail.com | G4: 増山 | H4: 武彦 | J4: 080-2653-5946 | P4: 45887.458 | R4: 45885.816 | S4: 45885.816 | T4: https://sub.shirogakucho-web3.com/event/5qGgQUWRlr3f/confirm | U4: 2404:7a85:4860:2f00:333e:d34d:429a:3ee8 | V4: 購読中
A5: MhQcZHaxBNFC | B5: Q6b9EZNIRxHo | C5: 239aaa491310a098dd3e4ab9fc2c47a9 | D5: Taicho???? | E5: 福井 孝正 | F5: 99jastnet@gmail.com | G5: 福井 | H5: 孝正 | J5: 855965961328 | P5: 45886.667 | R5: 45885.816 | S5: 45885.816 | T5: https://sub.shirogakucho-web3.com/event/5qGgQUWRlr3f/confirm | U5: 27.111.11.174 | V5: 購読中
A6: aF1vIVscTGoT | B6: oI3We2hS1VLD | C6: de72fdc08f509261f9db9cc680d75a36 | D6: Daisuke | E6: 鈴木 大亮 | F6: daisuke0776@gmail.com | G6: 鈴木 | H6: 大亮 | J6: 8061509684 | P6: 45886.417 | R6: 45885.816 | S6: 45885.816 | T6: https://sub.shirogakucho-web3.com/event/5qGgQUWRlr3f/confirm | U6: 2405:6584:4260:9b00:9118:6aea:87b1:4cd9 | V6: 購読中
A7: Qnt4R4VPmu4R | B7: El01LEuU6iu7 | C7: 509b428660205aa0176828f82e8707f7 | D7: SiriusB | E7: 宮本 義孝 | F7: mymtystk@gmail.com | G7: 宮本 | H7: 義孝 | J7: 8033814761 | P7: 45892.667 | R7: 45885.817 | S7: 45885.817 | T7: https://sub.shirogakucho-web3.com/event/5qGgQUWRlr3f/confirm | U7: 58.70.180.47 | V7: 購読中
A8: Dh9hYNpEZJoJ | B8: 5dxHy3wf8JuC | C8: 173b50897c439f8eca6169371586a546 | D8: おさるさん | E8: 黄本 章雄 | F8: smile.jack317@docomo.ne.jp | G8: 黄本 | H8: 章雄 | J8: 8083101224 | P8: 45888.833 | R8: 45885.819 | S8: 45885.819 | T8: https://sub.shirogakucho-web3.com/event/5qGgQUWRlr3f/confirm | U8: 240b:250:58e1:c00:84d0:b2b1:9079:278b | V8: 購読中
A9: 5diFEtzHQGIM | B9: v44xlbwwWzlg | C9: 6fd53f627333ecd43f8c1d7d250ff3de | D9: Hiromi Yamasaki | E9: 山﨑 洋美 | F9: yamasaki.4s@icloud.com | G9: 山﨑 | H9: 洋美 | J9: 9024827223 | P9: 45900.417 | R9: 45885.821 | S9: 45885.821 | T9: https://sub.shirogakucho-web3.com/event/5qGgQUWRlr3f/confirm | U9: 2400:4152:1c2:6d00:40a7:c469:92a7:94c7 | V9: 購読中/配信エラー
A10: nDojvuOZ0LNn | B10: vovH37WjXMWr | C10: 1cc6f6dc8bed90f015294afe628aafe7 | D10: @ADAKIN_WEB3 | E10: 足立 欣永 | F10: adachi.yoshinaga.4241@gmail.com | G10: 足立 | H10: 欣永 | J10: 9095655845 | P10: 45886.521 | R10: 45885.824 | S10: 45885.824 | T10: https://sub.shirogakucho-web3.com/event/5qGgQUWRlr3f/confirm | U10: 202.75.124.191 | V10: 購読中
A11: gwDgFYKmElzE | B11: yDIk3BoZeqR3 | C11: f32681baef82e68704334dce9cfdc16a | D11: Kazumi | E11: 木村 和美 | F11: millenniumstar8@gmail.com | G11: 木村 | H11: 和美 | J11: 18082923806 | P11: 45887.604 | R11: 45885.825 | S11: 45885.825 | T11: https://sub.shirogakucho-web3.com/event/5qGgQUWRlr3f/confirm | U11: 2603:800c:12f0:2030:8d0e:a99c:a91b:37c7 | V11: 購読中
A12: K6gh2TnaMGjA | B12: FHldvJlqvpku | C12: e0fe3dd802ba0f6a219e70f6f4a26c52 | D12: 山路基洋 | E12: 山路 基洋 | F12: kmd249yamaji@gmail.com | G12: 山路 | H12: 基洋 | J12: 9081594322 | P12: 45886.833 | R12: 45885.826 | S12: 45885.826 | T12: https://sub.shirogakucho-web3.com/event/5qGgQUWRlr3f/confirm | U12: 133.149.93.80 | V12: 購読中
A13: unkJhEsGnMrf | B13: 8ZVeHatJn17h | C13: d4197e3998f7c72b5946fa9ac980e6cb | D13: ひさえちゃん | E13: とだ ひさえ | F13: 39@aramaa.net | G13: とだ | H13: ひさえ | J13: 9096281015 | P13: 45890.458 | R13: 45885.826 | S13: 45885.826 | T13: https://sub.shirogakucho-web3.com/event/5qGgQUWRlr3f/confirm | U13: 240f:92:c384:1:d869:46d4:4f63:e87c | V13: 購読中/配信エラー
A14: n6b8UWtCyfnm | B14: N8gEXvVvdtyN | C14: 49e95842adda639e667bb62de071e930 | D14: たか | E14: 菊口 貴久 | F14: tkiku62@gmail.com | G14: 菊口 | H14: 貴久 | J14: 9028268818 | P14: 45886.75 | R14: 45885.827 | S14: 45885.827 | T14: https://sub.shirogakucho-web3.com/event/5qGgQUWRlr3f/confirm | U14: 2001:318:2014:cc6:cc7d:a039:a478:1480 | V14: 購読中
A15: gTFnGp2CVJtw | B15: EBymfg1BrZES | C15: ec755f96bd6c26454464151c60c79b2d | D15: mizupapa | E15: 水間 将誉 | F15: mmizuma@gmail.com | G15: 水間 | H15: 将誉 | J15: 9047411665 | P15: 45892.833 | R15: 45885.827 | S15: 45885.827 | T15: https://sub.shirogakucho-web3.com/event/5qGgQUWRlr3f/confirm | U15: 2400:4050:c164:1e00:ba17:f705:de16:4223 | V15: 購読中
A16: rebwWSYWrMfe | B16: rXoPbiUp0YuB | C16: c452e0259109160958b68b8db2b0f742 | D16: 外山広行 | E16: 外山広行 トヤマヒロユキ | F16: toyaman23-2525@docomo.ne.jp | G16: 外山 | H16: 広行 | J16: 9021745990 | P16: 45891.833 | R16: 45885.828 | S16: 45885.828 | T16: https://sub.shirogakucho-web3.com/event/5qGgQUWRlr3f/confirm | U16: 2400:4052:5164:b400:4c57:4b45:9265:84d0 | V16: 解除済 | W16: 45891.421
A17: 2enDrQfa7Fb9 | B17: j60DJ58kKIK8 | C17: 04964b86a05ce9f10bd1970d70ced9d7 | D17: Harumi Sakamoto | E17: 坂本 はるみ | F17: kotobukiwithin@gmail.com | G17: 坂本 | H17: はるみ | J17: 61447319931 | P17: 45888.417 | R17: 45885.833 | S17: 45885.833 | T17: https://sub.shirogakucho-web3.com/event/5qGgQUWRlr3f/confirm | U17: 115.69.5.205 | V17: 購読中
A18: fcWKgGmD9sB8 | B18: WzWF52TxUV65 | C18: 99a656201e9cc95a28d0d8672543a226 | D18: Tomoki Harano(原野智哉) | E18: 原野 智哉 | F18: tom1966_11@hotmail.com | G18: 原野 | H18: 智哉 | J18: 9089736419 | P18: 45891.708 | R18: 45885.837 | S18: 45885.837 | T18: https://sub.shirogakucho-web3.com/event/5qGgQUWRlr3f/confirm | U18: 2001:44c8:41a4:36c5:7962:2bb6:27c0:cc96 | V18: 解除済 | W18: 45885.846
A19: WJ2mMhgMBNax | B19: 6o4p1yigKo5z | C19: f852f2a33656c5a66b02df335ab2a37f | D19: 由花 | E19: 野中 由花 | F19: yukaena0502@gmail.com | G19: 野中 | H19: 由花 | J19: 9069010860 | P19: 45889.833 | R19: 45885.85 | S19: 45885.85 | T19: https://sub.shirogakucho-web3.com/event/5qGgQUWRlr3f/confirm | U19: 126.254.147.77 | V19: 購読中
A20: hOWycn41njc4 | B20: q2qrBVEKGSRW | C20: 93abf46bf00b2235d5fa590e1a7789e8 | D20: ゆうこ | E20: 原口 優子 | F20: y6649851@gmail.com | G20: 原口 | H20: 優子 | J20: 8026705677 | P20: 45891.479 | R20: 45885.851 | S20: 45885.851 | T20: https://sub.shirogakucho-web3.com/event/5qGgQUWRlr3f/confirm | U20: 210.136.107.235 | V20: 購読中
A21: qYXDaYqfsb3E | B21: AWFj3RtXK8Af | C21: 7ff0db4da65101568b655003744f1efa | D21: Kushida | E21: 櫛田 直 | F21: nao394d@gmail.com | G21: 櫛田 | H21: 直 | J21: 8069602009 | P21: 45894.812 | R21: 45885.852 | S21: 45885.852 | T21: https://sub.shirogakucho-web3.com/event/5qGgQUWRlr3f/confirm | U21: 220.211.86.70 | V21: 購読中
A22: dg6nV369iwT7 | B22: cmtAQyHInJd9 | C22: 01e37fc84b620187ab28a9a2bb445cf9 | D22: Liz | E22: 藤井 龍咲 | F22: lizrose258@gmail.com | G22: 藤井 | H22: 龍咲 | J22: 60172143740 | P22: 45903.833 | R22: 45885.855 | S22: 45885.855 | T22: https://sub.shirogakucho-web3.com/event/5qGgQUWRlr3f/confirm | U22: 193.36.237.11 | V22: 解除済 | W22: 45903.875
A23: vwWRy0GUovy1 | B23: xEvbmWC3Si1X | C23: 3e91635d6508004daaf60a02ee521c72 | D23: Mitsugu | E23: 久保田 貢 | F23: mitsu_1962@yahoo.com | G23: 久保田 | H23: 貢 | J23: 8039735229 | P23: 45892.75 | R23: 45885.859 | S23: 45885.859 | T23: https://sub.shirogakucho-web3.com/event/5qGgQUWRlr3f/confirm | U23: 2400:2200:76b:7d1a:5ced:cc11:3f02:f997 | V23: 購読中
A24: RuqbIbOkDaq1 | B24: CqWKnrgnrO99 | C24: eaf287255ce8f1f6d5e91e9ef74cbc11 | D24: Akihiro Uno | E24: 鵜野 彰洋 | F24: au09054720010@gmail.com | G24: 鵜野 | H24: 彰洋 | J24: 9054720010 | P24: 45894.708 | R24: 45885.871 | S24: 45885.871 | T24: https://sub.shirogakucho-web3.com/event/5qGgQUWRlr3f/confirm | U24: 240b:252:e60:2800:599d:a1c6:7b64:342e | V24: 購読中
A25: XwUE3ZIRp5VH | B25: 0CiiwIqvDegW | C25: 0e7959b74f2c1e8bdeb99423750b6e80 | D25: かつや | E25: 藤原 克哉 | F25: fujiwara.katsuya@gmail.com | G25: 藤原 | H25: 克哉 | J25: 9021018879 | P25: 45893.5 | R25: 45885.883 | S25: 45885.883 | T25: https://sub.shirogakucho-web3.com/event/5qGgQUWRlr3f/confirm | U25: 2404:7a84:3c60:e00:4941:7411:f93c:135f | V25: 購読中
A26: lkiTsoOTe43s | B26: Gs4Fnp25gxkU | C26: 100b9ef4b5e78c70e87374780f3726ae | D26: トキＯＥ | E26: 大江 昌夫 | F26: oe.masao@gmail.com | G26: 大江 | H26: 昌夫 | J26: 8043316517 | P26: 45887.729 | R26: 45885.889 | S26: 45885.889 | T26: https://sub.shirogakucho-web3.com/event/5qGgQUWRlr3f/confirm | U26: 114.150.58.22 | V26: 購読中
A27: yGUovgPYEv28 | B27: sbtZWQPmDkOp | C27: 59ca315bb83054a00ea251e5ae6c97a4 | D27: しげ | E27: 若園 繁博 | F27: shigetaka0427@gmail.com | G27: 若園 | H27: 繁博 | J27: 9098922445 | P27: 45890.833 | R27: 45885.902 | S27: 45885.902 | T27: https://sub.shirogakucho-web3.com/event/5qGgQUWRlr3f/confirm | U27: 240a:61:52c5:b2fb:55bd:3f0:711b:f028 | V27: 購読中
A28: FetZ6v1tZPAj | B28: AlDYLz41HNjI | C28: 87197acc116e805357142d6c637e2d83 | D28: 尚史 | E28: 深谷 尚史 | F28: orange7.x@gmail.com | G28: 深谷 | H28: 尚史 | J28: 9093476135 | P28: 45900.562 | R28: 45885.906 | S28: 45885.906 | T28: https://sub.shirogakucho-web3.com/event/5qGgQUWRlr3f/confirm | U28: 240d:1a:3d9:2a00:7dd2:b753:193d:f1d | V28: 購読中
A29: e5bzaimJ0oCm | B29: QobJHz86zqGy | C29: 603ac8f03210242416dda698e3dba6f7 | D29: かず | E29: 小高 和博 | F29: odaka_kazuhiro@yahoo.co.jp | G29: 小高 | H29: 和博 | J29: 7084316398 | P29: 45904.833 | R29: 45885.927 | S29: 45885.927 | T29: https://sub.shirogakucho-web3.com/event/5qGgQUWRlr3f/confirm | U29: 240b:c010:4d2:7ace:6856:4111:a16c:4239 | V29: 解除済 | W29: 45904.555
A30: Z6CbT7fbjgwh | B30: wPseBRsfNRze | C30: 34cf842afa10a7fb5d9a87df6e865e17 | D30: 藤原和憲 | E30: 藤原 和憲 | F30: heckel371@yahoo.co.jp | G30: 藤原 | H30: 和憲 | J30: 8061872147 | P30: 45893.417 | R30: 45885.951 | S30: 45885.951 | T30: https://sub.shirogakucho-web3.com/event/5qGgQUWRlr3f/confirm | U30: 2001:ce8:184:4442:41ce:216e:ee27:8a20 | V30: 購読中
A31: SQ0kQRgMeOHt | B31: lLnfFKKHDoAu | C31: cba1430e514a16d2774fec9b80f3ffd0 | D31: 松田 豊貴 | E31: 松田 豊貴 | F31: toyoking1040@hotmail.com | G31: 松田 | H31: 豊貴 | J31: 9033405915 | P31: 45888.75 | R31: 45885.98 | S31: 45885.98 | T31: https://sub.shirogakucho-web3.com/event/5qGgQUWRlr3f/confirm | U31: 2400:2410:cc21:eb00:19a2:25ce:504a:f1b7 | V31: 購読中
A32: sh3YziFr4mhC | E32: 古谷 徳史 | F32: nori853853@gmail.com | G32: 古谷 | H32: 徳史 | J32: 8042683580 | P32: 45891.562 | R32: 45885.98 | S32: 45885.98 | T32: https://sub.shirogakucho-web3.com/event/5qGgQUWRlr3f/confirm | U32: 2400:2200:849:8d14:490:7452:ad:46ef | V32: 購読中
A33: 9JUCLuCqZxKw | E33: 大和谷 あやか | F33: dpqyr077@gmail.com | G33: 大和谷 | H33: あやか | J33: 7089637415 | P33: 45890.708 | R33: 45885.995 | S33: 45885.995 | T33: https://sub.shirogakucho-web3.com/event/5qGgQUWRlr3f/confirm | U33: 86.105.144.131 | V33: 購読中
A34: 3DEdw698qXc9 | B34: nQxlzA5y83CX | C34: 1089d5db2375c78edea1c971c9bde99c | D34: NAKAYAMA 2175 | E34: 中山 和人 | F34: kura221231@gmail.com | G34: 中山 | H34: 和人 | J34: 9021752291 | P34: 45888.833 | R34: 45885.999 | S34: 45885.999 | T34: https://sub.shirogakucho-web3.com/event/5qGgQUWRlr3f/confirm | U34: 2001:268:73b2:198f:d114:7f88:603:1fee | V34: 購読中
A35: 5fz74JCWdZIT | B35: 3hU5tN2IA8D3 | C35: 2bd6de67291978d5a12c9f82465e10bc | D35: Nitta Keisuke | E35: 新田 佳祐 | F35: itumodachinikansya@gmail.com | G35: 新田 | H35: 佳祐 | J35: 8039789073 | P35: 45894.458 | R35: 45886.023 | S35: 45886.023 | T35: https://sub.shirogakucho-web3.com/event/5qGgQUWRlr3f/confirm | U35: 153.184.134.137 | V35: 購読中
A36: bSaA89EhGCtp | B36: WXIUFLLU8h9i | C36: 162eb2de76cb93c90ef7655ce9ba8c61 | D36: しゅう様 | E36: 奥脇 秀一 | F36: o9072768700@gmail.com | G36: 奥脇 | H36: 秀一 | J36: 9072768700 | P36: 45888.521 | R36: 45886.238 | S36: 45886.238 | T36: https://sub.shirogakucho-web3.com/event/5qGgQUWRlr3f/confirm | U36: 153.186.218.174 | V36: 購読中
A37: t395JN2sySTE | B37: y0Yn1zr0AwuA | C37: 2d6a72a101c76352dd457f12cd479b63 | D37: noriko okuzumi | E37: 藤堂 憲子 | F37: britelightone1@gmail.com | G37: 藤堂 | H37: 憲子 | J37: 9053364882 | P37: 45888.604 | R37: 45886.248 | S37: 45886.248 | T37: https://sub.shirogakucho-web3.com/event/5qGgQUWRlr3f/confirm | U37: 2400:4050:8801:9c00:3d89:787e:1a57:c3b7 | V37: 購読中
A38: Ioj0uHHtIjDy | B38: nkL1y5lDBiFj | C38: 5391ff918f92392e796db71f06e93ba6 | D38: Doreml773 | E38: 轟 洋子 | F38: paribmw369@gmail.com | G38: 轟 | H38: 洋子 | J38: 8050506693 | P38: 45894.625 | R38: 45886.344 | S38: 45886.344 | T38: https://sub.shirogakucho-web3.com/event/5qGgQUWRlr3f/confirm | U38: 2400:4051:c841:100:11f3:6320:6c14:19ac | V38: 購読中
A39: 4B3RBY2muqcW | B39: oiRSMtEcSmA9 | C39: 4e957959599c46d13ac0a2246ba98b24 | D39: toto | E39: 根本 勝利 | F39: minato0555@outlook.jp | G39: 根本 | H39: 勝利 | J39: 8044190555 | P39: 45899.812 | R39: 45886.417 | S39: 45886.417 | T39: https://sub.shirogakucho-web3.com/event/5qGgQUWRlr3f/confirm | U39: 122.214.0.241 | V39: 購読中
A40: jHr90M7oVglK | B40: YQfl3RAQuSBF | C40: 239d5cbce2aab8a938084c4668bbe623 | D40: Hiroyuki Chikaraishi | E40: 力石 弘行 | F40: izaiyak@gmail.com | G40: 力石 | H40: 弘行 | J40: 66879778862 | P40: 45889.458 | R40: 45886.43 | S40: 45886.43 | T40: https://sub.shirogakucho-web3.com/event/5qGgQUWRlr3f/confirm | U40: 2405:9800:b660:ea58:7493:a51a:7950:5830 | V40: 解除済 | W40: 45888.832
A41: TjZxxtAOIiTl | B41: i7xb01GUagyn | C41: 153817682eb4d561b2a5a25938aab031 | D41: 足立 | E41: 足立 啓悟 | F41: adachi0712@gmail.com | G41: 足立 | H41: 啓悟 | J41: 9074026160 | P41: 45893.833 | R41: 45886.479 | S41: 45886.479 | T41: https://sub.shirogakucho-web3.com/event/5qGgQUWRlr3f/confirm | U41: 2400:4051:84a0:d900:2977:1e64:9df5:6b67 | V41: 購読中
A42: FFRpe4MDsCId | B42: u9TnwzNsmFVQ | C42: 16c44be4cd92be279a7df499a689e7f6 | D42: 松山諭文 | E42: 松山 諭文 | F42: sato_matsu@leto.eonet.ne.jp | G42: 松山 | H42: 諭文 | J42: 8042965932 | P42: 45892.417 | R42: 45886.503 | S42: 45886.503 | T42: https://sub.shirogakucho-web3.com/event/5qGgQUWRlr3f/confirm | U42: 58.188.234.178 | V42: 購読中
A43: e8oksGRnuklE | E43: 門田 典美 | F43: ganbamonta@gmail.com | G43: 門田 | H43: 典美 | J43: 9062832000 | P43: 45889.542 | R43: 45886.561 | S43: 45886.561 | T43: https://sub.shirogakucho-web3.com/event/5qGgQUWRlr3f/confirm | U43: 60.102.49.166 | V43: 購読中
A44: maBjLxvUHlnP | B44: dcbF8Y6rnmxV | C44: 8ecea127199fdda7860f8950bcdf8796 | D44: 登田英樹 | E44: 登田 英樹 | F44: towahide091q@gmail.com | G44: 登田 | H44: 英樹 | J44: 9015616535 | P44: 45895.667 | R44: 45886.599 | S44: 45886.599 | T44: https://sub.shirogakucho-web3.com/event/5qGgQUWRlr3f/confirm | U44: 153.201.87.32 | V44: 購読中
A45: I6s1Kzlhwc4Z | B45: b2n9GJZIUAnk | C45: c6229437736c4b0be921f15773e61842 | D45: カブ～キ | E45: 北平 一喜 | F45: kitakazu3333@icloud.com | G45: 北平 | H45: 一喜 | J45: 9034195907 | P45: 45893.583 | R45: 45886.668 | S45: 45886.668 | T45: https://sub.shirogakucho-web3.com/event/5qGgQUWRlr3f/confirm | U45: 210.203.212.17 | V45: 購読中/配信エラー
A46: jtcrxqbgxXIZ | B46: FKZMMK2G7RcF | C46: e767ff95d3ff93c06938a06c0f04b7e5 | D46: 松井幸弘 | E46: 松井 幸弘 | F46: den35738@protonmail.com | G46: 松井 | H46: 幸弘 | J46: 9031668572 | P46: 45893.667 | R46: 45886.789 | S46: 45886.789 | T46: https://sub.shirogakucho-web3.com/event/5qGgQUWRlr3f/confirm | U46: 240a:61:6050:24a2:b01a:ae6a:8adb:14e8 | V46: 購読中
A47: M7aYDtZMUE57 | B47: i5wt65h9C2sw | C47: e465c3f1b75b0bc7ac666ce249c0e2f9 | D47: Nakata | E47: 中田 雄之 | F47: nakata@kindly-link.com | G47: 中田 | H47: 雄之 | J47: 9059735501 | P47: 45889.625 | R47: 45886.814 | S47: 45886.814 | T47: https://sub.shirogakucho-web3.com/event/5qGgQUWRlr3f/confirm | U47: 61.46.0.172 | V47: 購読中
A48: rUuuLhUKaUrg | B48: KhP7KkCxFJfc | C48: 94cf1adffa85ea8d8cf6f06f68e3954f | D48: 田井 | E48: 田井 輝彦 | F48: teruhiko0226@gmail.com | G48: 田井 | H48: 輝彦 | J48: 9035272121 | P48: 45893.75 | R48: 45886.815 | S48: 45886.815 | T48: https://sub.shirogakucho-web3.com/event/5qGgQUWRlr3f/confirm | U48: 2001:268:73b6:602c:fc9d:197a:9e1b:19f5 | V48: 購読中
A49: Bn1rd6QiLDVQ | B49: 5eVCJTdspr2A | C49: ddf4d3375ab76ddfeb28f31b36c6dd31 | D49: 萩広 | E49: 萩原 広昭 | F49: hagi160aki@yahoo.co.jp | G49: 萩原 | H49: 広昭 | J49: 9074221700 | P49: 45889.708 | R49: 45886.816 | S49: 45886.816 | T49: https://sub.shirogakucho-web3.com/event/5qGgQUWRlr3f/confirm | U49: 2400:4052:84e7:3b00:7daa:9659:780c:d076 | V49: 解除済 | W49: 46036.561
A50: QciKLdpdqBz0 | B50: eh8HsD0I4OUG | C50: 3938fe00f01dd045dc271d441afaffc0 | D50: あき | E50: 松浦 章展 | F50: akikoko0110@yahoo.co.jp | G50: 松浦 | H50: 章展 | J50: 080-3767-4531 | P50: 45899.708 | R50: 45886.817 | S50: 45886.817 | T50: https://sub.shirogakucho-web3.com/event/5qGgQUWRlr3f/confirm | U50: 2001:ce8:144:b55b:3caa:d096:6427:809a | V50: 解除済 | W50: 45900.4
A51: Sxap6PfCJrQB | B51: 7RACNUXkGEtn | C51: a1087dae2388838b203dd814ab0e6a18 | D51: トモ | E51: 田中 友晴 | F51: tmhr1958@ybb.ne.jp | G51: 田中 | H51: 友晴 | J51: 9024203460 | P51: 45897.479 | R51: 45886.825 | S51: 45886.825 | T51: https://sub.shirogakucho-web3.com/event/5qGgQUWRlr3f/confirm | U51: 2400:2412:540:df00:5d0d:95db:220f:4900 | V51: 購読中
A52: t1ZYvGBZpbrM | B52: EFAOvRFQV8OL | C52: dd7e82fbec084700e2d03538e84be233 | D52: 隆司 | E52: 遠藤 隆司 | F52: blunmoon@icloud.com | G52: 遠藤 | H52: 隆司 | J52: 8064788804 | P52: 45897.75 | R52: 45886.842 | S52: 45886.842 | T52: https://sub.shirogakucho-web3.com/event/5qGgQUWRlr3f/confirm | U52: 122.209.145.198 | V52: 購読中/配信エラー
A53: ze996CzF6RkW | B53: mJhFdLJ3uqmW | C53: 5492b51638eea0dda4d7f2124f636b81 | D53: 白黒の猫 | E53: 久保 誠三 | F53: syamunekokubo@gmail.com | G53: 久保 | H53: 誠三 | J53: 9028234945 | P53: 45887.833 | R53: 45886.845 | S53: 45886.845 | T53: https://sub.shirogakucho-web3.com/event/5qGgQUWRlr3f/confirm | U53: 153.189.19.252 | V53: 購読中
A54: A88JHulSRgpV | B54: CGaKl8JJKvug | C54: 68de48dc958ad1f5fc008131d85467ba | D54: 富田 絵理 | E54: 富田 絵理 | F54: noizayfrance222@yahoo.co.jp | G54: 富田 | H54: 絵理 | J54: 090-2680-2176 | P54: 45902.667 | R54: 45886.85 | S54: 45886.85 | T54: https://sub.shirogakucho-web3.com/event/5qGgQUWRlr3f/confirm | U54: 121.82.120.230 | V54: 購読中
A55: FQfoj3UIqwhe | B55: cYHm2AYNQkW7 | C55: d1131a8db63c25f74a18694ce607a432 | D55: 杉川 Naoko | E55: 杉川 直子 | F55: sugikawa705@gmail.com | G55: 杉川 | H55: 直子 | J55: 9010271819 | P55: 45895.417 | R55: 45886.857 | S55: 45886.857 | T55: https://sub.shirogakucho-web3.com/event/5qGgQUWRlr3f/confirm | U55: 156.59.26.134 | V55: 購読中
A56: 97vOR89rVGRl | B56: ZNOHrZEj20Ue | C56: d7d4a14406501c5ee990e8bfa8651050 | D56: くみこ | E56: 中原 久美子 | F56: velmukumiko@gmail.com | G56: 中原 | H56: 久美子 | J56: 9015621206 | P56: 45911.438 | R56: 45886.857 | S56: 45886.857 | T56: https://sub.shirogakucho-web3.com/event/5qGgQUWRlr3f/confirm | U56: 2400:2200:7d5:649d::c54c:eadf | V56: 購読中
A57: Xn7Gip8tYe30 | B57: MdZKJQIstWM1 | C57: 7c71b188e75cc7c83c604efa0fedb489 | D57: Akiko Kawasaki | E57: 川崎 亜紀子 | F57: akiko1k@hotmail.com | G57: 川崎 | H57: 亜紀子 | J57: 9067110333 | P57: 45895.771 | R57: 45886.861 | S57: 45886.861 | T57: https://sub.shirogakucho-web3.com/event/5qGgQUWRlr3f/confirm | U57: 122.199.38.35 | V57: 購読中
A58: I6s1Kzlhwc4Z | B58: b2n9GJZIUAnk | C58: c6229437736c4b0be921f15773e61842 | D58: カブ～キ | E58: 北平 一喜 | F58: kitakazu3333@icloud.com | R58: 45886.898 | S58: 45886.898 | V58: 購読中/配信エラー
A59: H3o3rx1IuCv0 | E59: 佐藤 輝雄 | F59: satetesa_3883@yahoo.co.jp | G59: 佐藤 | H59: 輝雄 | J59: 9023637394 | P59: 45905.542 | R59: 45886.907 | S59: 45886.907 | T59: https://sub.shirogakucho-web3.com/event/5qGgQUWRlr3f/confirm | U59: 2400:4053:25e1:a400:3105:82c1:7a7d:f439 | V59: 購読中
A60: 5mfCt38ryN66 | B60: KmPDlcLETu1O | C60: e4a1717683bc3df45e47ea279b49e7fc | D60: まつもと | E60: まつもと しげお | F60: sig@mzmt.jp | G60: 松本 | H60: 茂生 | J60: 090-6669-2944 | P60: 45898.417 | R60: 45886.913 | S60: 45886.913 | T60: https://sub.shirogakucho-web3.com/event/5qGgQUWRlr3f/confirm | U60: 2001:ce8:117:4245:edf1:aeb9:1b95:a558 | V60: 購読中
A61: WD18t5q4Zi24 | B61: 8rii0Xi6AZft | C61: 2774ca850c1ec5f69b0dabf322b742db | D61: 倉田 正美 | E61: 倉田 正美 | F61: masamiaug2@softbank.ne.jp | G61: 倉田 | H61: 正美 | J61: 8038548541 | P61: 45907.667 | R61: 45886.955 | S61: 45886.955 | T61: https://sub.shirogakucho-web3.com/event/5qGgQUWRlr3f/confirm | U61: 2404:7a80:9e20:2200:d0a4:bfcf:ea82:df43 | V61: 解除済 | W61: 45904.883
A62: dM58zI150Kxs | E62: 有井 淳一 | F62: planet7198@gmail.com | G62: 有井 | H62: 淳一 | J62: 9091517086 | P62: 45896.833 | R62: 45886.956 | S62: 45886.956 | T62: https://sub.shirogakucho-web3.com/event/5qGgQUWRlr3f/confirm | U62: 240f:69:6c51:1:3582:ee7f:844d:a07b | V62: 購読中
A63: 6QKLGudtjH2a | B63: 0JOzeRIOEVKi | C63: 3d449f5fb08e2341a7aec31d05440818 | D63: たまちゃん | E63: 石井 珠莉 | F63: tamariworld@hotmail.com | G63: 石井 | H63: 珠莉 | J63: 9033134758 | P63: 45896.75 | R63: 45886.971 | S63: 45886.971 | T63: https://sub.shirogakucho-web3.com/event/5qGgQUWRlr3f/confirm | U63: 27.55.81.124 | V63: 購読中
A64: BX7HIQPFHzex | B64: gm4879oPjWwC | C64: 9a30010c0c807d0f382ab4293e9de5c2 | D64: 別井秀一 | E64: 別井 秀一 | F64: shubetui@icloud.com | G64: 別井 | H64: 秀一 | J64: 9032298768 | P64: 45895.583 | R64: 45887.321 | S64: 45887.321 | T64: https://sub.shirogakucho-web3.com/event/5qGgQUWRlr3f/confirm | U64: 219.117.218.135 | V64: 解除済 | W64: 45893.417
A65: uKVxsz0a8Bxi | B65: UHXF5f44PmFu | C65: 8e1a25992d742a9cdc06ca8632945273 | D65: ピリカ | E65: 玉井 秀人 | F65: dracolulu2018@yahoo.ne.jp | G65: 玉井 | H65: 秀人 | J65: 7085403109 | P65: 45896.521 | R65: 45887.394 | S65: 45887.394 | T65: https://sub.shirogakucho-web3.com/event/5qGgQUWRlr3f/confirm | U65: 2400:2411:aa00:7500:dce5:9a5:5626:901e | V65: 購読中
A66: yukWZK1Z47vx | B66: LGAKaWys8uld | C66: 035fb698a537b5503cf6243b9f5595c7 | D66: 小林祐也 | E66: 小林 祐也 | F66: yu2906yu2906yu@gmail.com | G66: 小林 | H66: 祐也 | J66: 8012444839 | P66: 45898.792 | R66: 45887.411 | S66: 45887.411 | T66: https://sub.shirogakucho-web3.com/event/5qGgQUWRlr3f/confirm | U66: 2001:268:902f:e8bf:170:38e7:aa6c:5f38 | V66: 購読中
A67: fGCAlxkCQYTY | B67: TSJz3VuJoutb | C67: fa7dcaf982a86bb9038aae6d5f8bcdc9 | D67: catkazuko | E67: 平田 和子 | F67: kazuko0413@icloud.com | G67: 平田 | H67: 和子 | J67: 9097126109 | P67: 45905.458 | R67: 45887.445 | S67: 45887.445 | T67: https://sub.shirogakucho-web3.com/event/5qGgQUWRlr3f/confirm | U67: 2001:ce8:102:eb7f:8580:7be4:cd32:849c | V67: 解除済/配信エラー | W67: 45905.406
A68: ajg30EvGfyCs | B68: yH9pjOmoZRfu | C68: db37c4f872c6dcd24bfce8561b7db867 | D68: 井上むつこ | E68: 井上 ムツ子 | F68: inouemutti@gmail.com | G68: 井上 | H68: ムツ子 | J68: 8030024356 | P68: 45901.458 | R68: 45887.527 | S68: 45887.527 | T68: https://sub.shirogakucho-web3.com/event/5qGgQUWRlr3f/confirm | U68: 2400:2410:ffe0:c800:a0a6:f430:4f9d:88ad | V68: 購読中
A69: O8HT8W9oYAer | B69: UAcGxQGZfGHs | C69: c860dcf3f2303e13cccd14c38219f0fc | D69: K-HOSHI | E69: ホシコ カズヒサ | F69: kazu515257@gmail.com | G69: ホシコ | H69: カズヒサ | J69: 9046764635 | P69: 45900.833 | R69: 45887.552 | S69: 45887.552 | T69: https://sub.shirogakucho-web3.com/event/5qGgQUWRlr3f/confirm | U69: 240b:c010:4a0:3d0e:49a3:9275:f91a:9b10 | V69: 購読中
A70: wKjavR9z5cHb | B70: A5V2VHkEwXH4 | C70: 9cccc21de37a7d50927f404f0292124b | D70: YOSHIKI | E70: 岡本 芳樹 | F70: yookamoto@soc.co.jp | G70: 岡本 | H70: 芳樹 | J70: 8054560120 | P70: 45898.667 | R70: 45887.826 | S70: 45887.826 | T70: https://sub.shirogakucho-web3.com/event/5qGgQUWRlr3f/confirm | U70: 2400:2200:431:b67:810c:8d76:5685:70b8 | V70: 解除済 | W70: 45900.716
A71: hQ4TwjsverNH | B71: 94ZJ16u0hl5l | C71: 8b073b858e01f381032a7352e0d588f6 | D71: ＨＩＲＯ | E71: 鈴木 宏一 | F71: h-suzuki@daiwack.co.jp | G71: 鈴木 | H71: 宏一 | J71: 9033816577 | P71: 45906.708 | R71: 45887.848 | S71: 45887.848 | T71: https://sub.shirogakucho-web3.com/event/5qGgQUWRlr3f/confirm | U71: 183.77.56.18 | V71: 購読中
A72: qVjoToPccxkm | E72: 丸山 満男 | F72: dady152@gmail.com | G72: 丸山 | H72: 満男 | J72: 9049286114 | P72: 45901.583 | R72: 45887.848 | S72: 45887.848 | T72: https://sub.shirogakucho-web3.com/event/5qGgQUWRlr3f/confirm | U72: 2a09:bac2:43df:efa::17e:143 | V72: 購読中
A73: 0HJI7zUns4kq | B73: fvUapXtyAlj1 | C73: 9c6326c600744d6aa104bcfd9d9b6341 | D73: takaki SAIKI | E73: 佐伯 孝樹 | F73: ta.sa.one6@gmail.com | G73: 佐伯 | H73: 孝樹 | J73: 8064218496 | P73: 45901.667 | R73: 45887.85 | S73: 45887.85 | T73: https://sub.shirogakucho-web3.com/event/5qGgQUWRlr3f/confirm | U73: 2001:f71:5180:2200:9925:82a0:880:3246 | V73: 購読中
A74: opPMoQRZssfU | E74: 鈴東 耕太 | F74: suzuhigashikota@gmail.com | G74: 鈴東 | H74: 耕太 | J74: 9049323220 | P74: 45898.5 | R74: 45887.882 | S74: 45887.882 | T74: https://sub.shirogakucho-web3.com/event/5qGgQUWRlr3f/confirm | U74: 240a:61:11c6:f906:844e:78ff:febe:130e | V74: 購読中
A75: w46xP0fbGJme | E75: 津田 将司 | F75: t.boys1206@gmail.com | G75: 津田 | H75: 将司 | J75: 8051695821 | P75: 45901.75 | R75: 45887.901 | S75: 45887.901 | T75: https://sub.shirogakucho-web3.com/event/5qGgQUWRlr3f/confirm | U75: 240a:61:4261:dcd3:cf5:82c5:67c8:3a86 | V75: 購読中
A76: 1Y9EPRJzL79Y | B76: RHMsKMq1Hico | C76: b94a3c984a089fd49953b89c20741928 | D76: sakata | E76: 坂田 剛士 | F76: tuyosaka13@gmail.com | G76: 坂田 | H76: 剛士 | J76: 8042305093 | P76: 45896.604 | R76: 45887.936 | S76: 45887.936 | T76: https://sub.shirogakucho-web3.com/event/5qGgQUWRlr3f/confirm | U76: 101.142.75.171 | V76: 購読中
A77: cgBBJPEB9BEv | B77: Onif882AJo43 | C77: 36beac826b3d280dbab53abad32647ae | D77: サクマ | E77: 佐久間 栄一 | F77: ssakuma8@gmail.com | G77: 佐久間 | H77: 栄一 | J77: 8010274032 | P77: 45900.75 | R77: 45887.968 | S77: 45887.968 | T77: https://sub.shirogakucho-web3.com/event/5qGgQUWRlr3f/confirm | U77: 14.8.53.192 | V77: 購読中
A78: O5kTZryq5D2W | B78: RVssDA56ekrg | C78: 387ca1115e4b98c997699fcca347f161 | D78: T.鉄也 | E78: 鳥居 鉄也 | F78: f360indy@gmail.com | G78: 鳥居 | H78: 鉄也 | J78: 9020839252 | P78: 45905.708 | R78: 45887.985 | S78: 45887.985 | T78: https://sub.shirogakucho-web3.com/event/5qGgQUWRlr3f/confirm | U78: 240b:c020:650:67e7:8eba:e598:c0db:9bb1 | V78: 購読中
A79: jnHgHmZj8PD9 | B79: 2hqM4WIwWhYb | C79: a1e7cc4e7ecc124c7b60b2465e6a07a6 | D79: コウ | E79: 有川 航平 | F79: puko25082508@gmail.com | G79: 有川 | H79: 航平 | J79: 8064062508 | P79: 45900.646 | R79: 45888.173 | S79: 45888.173 | T79: https://sub.shirogakucho-web3.com/event/5qGgQUWRlr3f/confirm | U79: 118.241.251.193 | V79: 購読中
A80: 5ZYHptx28VYZ | B80: HIt9BGTn8QAx | C80: 032bf3422ee6913e9518fc1892774c9c | D80: さかい ゆみ | E80: 酒井 由美 | F80: yamayu0462@gmail.com | G80: 酒井 | H80: 由美 | J80: 9076582624 | P80: 45902.583 | R80: 45888.282 | S80: 45888.282 | T80: https://sub.shirogakucho-web3.com/event/5qGgQUWRlr3f/confirm | U80: 114.48.188.145 | V80: 購読中
A81: lLxlCkCxbjjP | B81: GTqbJnXG45hV | C81: 5f566d91ba5ff9447d45b87b97f120db | D81: Yukari Nakata | E81: 中田 由香利 | F81: delight.yukari@gmail.com | G81: 中田 | H81: 由香利 | J81: 9050159925 | P81: 45902.417 | R81: 45888.303 | S81: 45888.303 | T81: https://sub.shirogakucho-web3.com/event/5qGgQUWRlr3f/confirm | U81: 61.46.0.172 | V81: 解除済 | W81: 45890.649
A82: rKXCWrWZw3u7 | B82: m7vU4MM5QOlG | C82: f52fb844dca74d67d3c2860348b2603d | D82: 間瀬順司 | E82: 間瀬 順司 | F82: mass.mase.masse@gmail.com | G82: 間瀬 | H82: 順司 | J82: 9068399383 | P82: 45907.417 | R82: 45888.331 | S82: 45888.331 | T82: https://sub.shirogakucho-web3.com/event/5qGgQUWRlr3f/confirm | U82: 153.224.232.122 | V82: 購読中/配信エラー
A83: SrsYDbKxA5bx | B83: 04IPCLiBa02U | C83: 06132689cc49605d221c27a124004b51 | D83: F.Miya | E83: 宮内 富美夫 | F83: fm6.28fumi@gmail.com | G83: 宮内 | H83: 富美夫 | J83: 7050861387 | P83: 45898.583 | R83: 45888.411 | S83: 45888.411 | T83: https://sub.shirogakucho-web3.com/event/5qGgQUWRlr3f/confirm | U83: 2a09:bac2:43a6:efa::17e:141 | V83: 購読中
A84: ryNQzAbS6QG1 | B84: ZkmxOYfS4LTx | C84: 54216c0dfe301b8c86c493be17143c64 | D84: 河本浩和 | E84: 河本 浩和 | F84: deepmeruado@yahoo.co.jp | G84: 河本 | H84: 浩和 | J84: 9094629667 | P84: 45901.833 | R84: 45888.552 | S84: 45888.552 | T84: https://sub.shirogakucho-web3.com/event/5qGgQUWRlr3f/confirm | U84: 61.27.149.15 | V84: 購読中
A85: 4SHGT0AY015V | B85: XpM2qzk7K1xr | C85: edbd0290435911eeb564ff941811bc68 | D85: コウユウ | E85: 八巻 孝勇 | F85: paochan115@gmail.com | G85: 八巻 | H85: 孝勇 | J85: 8033513489 | P85: 45903.542 | R85: 45888.818 | S85: 45888.818 | T85: https://sub.shirogakucho-web3.com/event/5qGgQUWRlr3f/confirm | U85: 2400:2410:c3e2:c400:1817:9a23:4a7a:f0bf | V85: 購読中

Sheet 予約者②
A1: 全シナリオ共通読者ID | B1: LINE友だちID | C1: アカウント共通LINE友だちID | D1: LINE登録名 | E1: お名前 | F1: メールアドレス | G1: 姓 | H1: 名 | I1: フリガナ | J1: 電話番号 | K1: 郵便番号 | L1: 都道府県 | M1: 市区町村 | N1: 番地 | O1: マンション名 部屋番号 | P1: イベント参加日時 | Q1: 登録経路 | R1: 配信基準日時 | S1: 登録日時 | T1: 登録元ページ | U1: 登録元IP | V1: ステータス | W1: 解除日時
A2: y7WNIwTjJsfa | B2: lNx7pYC10qMd | C2: 812e1f039c7f8b2270fa82e2c03ec4ed | D2: まさちゃん | E2: 高垣 正孝 | F2: takataka791@yahoo.co.jp | G2: 高垣 | H2: 正孝 | J2: 8019094801 | P2: 45894.5 | R2: 45890.92 | S2: 45890.92 | T2: https://sub.shirogakucho-web3.com/event/YHwwoAOxsUKX/confirm | U2: 128.53.198.75 | V2: 購読中
A3: kfYZMr9iXRuc | B3: NMXOEjGqpwhv | C3: c5d709f6baacacb1b940200621eb30cf | D3: Z1030 | E3: 榊 孝之 | F3: usamat2018@gmail.com | G3: 榊 | H3: 孝之 | J3: 9036569509 | P3: 45895.833 | R3: 45891.908 | S3: 45891.908 | T3: https://sub.shirogakucho-web3.com/event/YHwwoAOxsUKX/confirm | U3: 2001:268:942d:290a:da8:d36e:a35a:a1ac | V3: 購読中
A4: glHfAfeOqgxM | B4: dzdKUhWjWENd | C4: 436c7dfdf9e5064cc271ddfb614ae3e6 | D4: Saeko | E4: 西村 さえこ | F4: saeko-nishi168@nifty.com | G4: 西村 | H4: さえこ | J4: 9027308130 | P4: 45930.792 | R4: 45902.82 | S4: 45902.82 | T4: https://sub.shirogakucho-web3.com/event/YHwwoAOxsUKX/confirm | U4: 2400:2410:36c1:5000:7a40:a6c7:9cb8:dd4c | V4: 購読中

Sheet 予約者③
A1: 全シナリオ共通読者ID | B1: LINE友だちID | C1: アカウント共通LINE友だちID | D1: LINE登録名 | E1: お名前 | F1: メールアドレス | G1: 姓 | H1: 名 | I1: フリガナ | J1: 電話番号 | K1: 郵便番号 | L1: 都道府県 | M1: 市区町村 | N1: 番地 | O1: マンション名 部屋番号 | P1: イベント参加日時 | Q1: 登録経路 | R1: 配信基準日時 | S1: 登録日時 | T1: 登録元ページ | U1: 登録元IP | V1: ステータス | W1: 解除日時
A2: AW6diVzKbxRx | B2: aQLnH1jZn58o | C2: 7d4fe8025525a8c2d31454c2cb335e74 | D2: がっきー | E2: 板垣 良雄 | F2: y.itagaki0528@gmail.com | G2: 板垣 | H2: 良雄 | J2: 9028351024 | P2: 45906.792 | R2: 45888.816 | S2: 45888.816 | T2: https://sub.shirogakucho-web3.com/event/jZ7wxfoOunBs/confirm | U2: 2400:2200:95c:f9f5:d088:61e:c0a1:1fd2 | V2: 購読中
A3: 4SHGT0AY015V | B3: XpM2qzk7K1xr | C3: edbd0290435911eeb564ff941811bc68 | D3: コウユウ | E3: 八巻 孝勇 | F3: paochan115@gmail.com | R3: 45888.818 | S3: 45888.818 | V3: 購読中
A4: NoxCPPemxc4U | B4: kiQ3AMlisFod | C4: 3836868802e5add5344033ea235abe22 | D4: 理恵 | E4: 岡本 理恵 | F4: vinus8.rie@gmail.com | G4: 岡本 | H4: 理恵 | J4: 9022326301 | P4: 45904.438 | R4: 45888.824 | S4: 45888.824 | T4: https://sub.shirogakucho-web3.com/event/jZ7wxfoOunBs/confirm | U4: 2400:2412:39a1:8700:4489:407a:550d:3146 | V4: 購読中
A5: TOkbroH3QDAk | B5: af1wr56xue8H | C5: 3042ae2df5ded0cb77d8cf5d9ed4fc5c | D5: 白井 博 | E5: 白井 博 | F5: wakumazaki@yahoo.co.jp | G5: 白井 | H5: 博 | J5: 8055737597 | P5: 45907.542 | R5: 45888.826 | S5: 45888.826 | T5: https://sub.shirogakucho-web3.com/event/jZ7wxfoOunBs/confirm | U5: 2400:4053:540:c900:6c64:c46f:6652:1562 | V5: 解除済 | W5: 45889.645
A6: obd0qA5imEJp | B6: kXRyO0psoI7G | C6: 2d414d427b01072f692e128326344b74 | D6: やぐちたかゆき | E6: 矢口 隆幸 | F6: yagutaka0927@gmail.com | G6: 矢口 | H6: 隆幸 | J6: 7011443031 | P6: 45902.771 | R6: 45888.83 | S6: 45888.83 | T6: https://sub.shirogakucho-web3.com/event/jZ7wxfoOunBs/confirm | U6: 2400:2200:712:9bda::247:1620 | V6: 購読中
A7: A6GvhNVtGkkW | B7: BTmhR1w0IqnZ | C7: 8439c677bd3b66f6d6c3bafdb80452ef | D7: 谷口敦史（福乃彦） | E7: 谷口 敦史 | F7: bc.usanou.358@gmail.com | G7: 谷口 | H7: 敦史 | J7: 9019619713 | P7: 45909.833 | R7: 45888.835 | S7: 45888.835 | T7: https://sub.shirogakucho-web3.com/event/jZ7wxfoOunBs/confirm | U7: 2001:ce8:164:35b4:c2f0:77ba:3d5e:8112 | V7: 解除済 | W7: 45931.414
A8: 5mfCt38ryN66 | B8: KmPDlcLETu1O | C8: e4a1717683bc3df45e47ea279b49e7fc | D8: まつもと | E8: まつもと しげお | F8: sig@mzmt.jp | G8: まつもと | H8: しげお | J8: 9066692944 | P8: 45903.688 | R8: 45888.866 | S8: 45888.866 | T8: https://sub.shirogakucho-web3.com/event/jZ7wxfoOunBs/confirm | U8: 126.182.26.141 | V8: 解除済 | W8: 45900.555
A9: eRFPnOET9mNS | B9: qgpI1CYZr8dg | C9: 49723c4e70892e55f5fbfcf4528c5582 | D9: TAKA | E9: 川島 隆幸 | F9: drinkingorgeous@gmail.com | G9: 川島 | H9: 隆幸 | J9: 9034320254 | P9: 45889.458 | R9: 45888.881 | S9: 45888.881 | T9: https://sub.shirogakucho-web3.com/event/jZ7wxfoOunBs/confirm | U9: 240a:61:5225:17c1:e025:bed4:3a13:24bd | V9: 購読中
A10: xgYHoeuYw3tY | B10: fDTRIz6UKHuM | C10: 5b7a72437574e2e2ead2341f2fe248af | D10: 年夫 | E10: 吉田 年夫 | F10: lionheart8139@gmail.com | G10: 吉田 | H10: 年夫 | J10: 9086995045 | P10: 45905.625 | R10: 45888.895 | S10: 45888.895 | T10: https://sub.shirogakucho-web3.com/event/jZ7wxfoOunBs/confirm | U10: 240b:253:4c20:8800:8d21:9c5f:91f1:4f64 | V10: 購読中
A11: YDwpY6hYapr1 | B11: tRYSaalU3Frc | C11: bc244cfda20c808b244fc25a9386d60c | D11: えいじ | E11: 根本 栄治 | F11: nemo10812@gmail.com | G11: 根本 | H11: 栄治 | J11: 9028184816 | P11: 45908.75 | R11: 45889.008 | S11: 45889.008 | T11: https://sub.shirogakucho-web3.com/event/jZ7wxfoOunBs/confirm | U11: 2400:2410:3a63:2700:5dc6:62e0:857f:9c8e | V11: 購読中
A12: X3vO1KUl5BX8 | B12: 9bpFlom0XxIW | C12: 8719ce1a299e9c3975e67a4244e1f8fd | D12: 藤縄 大 | E12: 藤縄 大 | F12: hiroshi.fujinawa@gmail.com | G12: 藤縄 | H12: 大 | J12: 090-9443-9277 | P12: 45903.458 | R12: 45889.083 | S12: 45889.083 | T12: https://sub.shirogakucho-web3.com/event/jZ7wxfoOunBs/confirm | U12: 240b:12:21a2:1300:b4a2:3db4:495d:9544 | V12: 購読中
A13: DGCEKNmufKGt | B13: LaEGl0LH2yLt | C13: b845bb061896138a123b92a61b01aabf | D13: たえこ | E13: 青柳 妙子 | F13: tatotuv6@gmail.com | G13: 青柳 | H13: 妙子 | J13: 9045303338 | P13: 45908.458 | R13: 45889.213 | S13: 45889.213 | T13: https://sub.shirogakucho-web3.com/event/jZ7wxfoOunBs/confirm | U13: 240f:3b:8478:1:4178:4e27:475a:fd0f | V13: 購読中
A14: TqVhTqMpHDPV | B14: ylFQQ0RxOsed | C14: 4447458a06fb415c359034ff9b559a57 | D14: 山本 | E14: 山本 政之 | F14: masayu0633@gmail.com | G14: 山本 | H14: 政之 | J14: 7050887785 | P14: 45904.75 | R14: 45889.26 | S14: 45889.26 | T14: https://sub.shirogakucho-web3.com/event/jZ7wxfoOunBs/confirm | U14: 118.241.248.97 | V14: 購読中
A15: 0GyxqxkI6VuW | B15: 7h8hNKRkQFBF | C15: a4e0ae15f65f1abde2b9be776bec72b3 | D15: 河村 守一 | E15: 河村 守一 | F15: shu511119@gmail.com | G15: 河村 | H15: 守一 | J15: 9073694043 | P15: 45907.75 | R15: 45889.34 | S15: 45889.34 | T15: https://sub.shirogakucho-web3.com/event/jZ7wxfoOunBs/confirm | U15: 49.106.209.144 | V15: 購読中
A16: SYqVYCQpjDgK | B16: 60fuRVptbQ25 | C16: ccf3ee37bcdc817ae181d8d027990e3a | D16: すなべひろや | E16: S H | F16: lsjfiekd@gmail.com | G16: S | H16: H | J16: 9019492800 | P16: 45907.833 | R16: 45889.508 | S16: 45889.508 | T16: https://sub.shirogakucho-web3.com/event/jZ7wxfoOunBs/confirm | U16: 240d:1a:9bd:2100:29a9:2684:5860:f31d | V16: 解除済 | W16: 45907.868
A17: HtYdsZVsKM2v | B17: 5yuCnRTTGdOB | C17: 569f062681c442bcb9c819bb0d29a5f3 | D17: しずめ?まきこ | E17: 鎭目 真喜子 | F17: shizumemakiko@gmail.com | G17: 鎭目 | H17: 真喜子 | J17: 9024464625 | P17: 45908.667 | R17: 45889.756 | S17: 45889.756 | T17: https://sub.shirogakucho-web3.com/event/jZ7wxfoOunBs/confirm | U17: 2001:268:98ea:1de0:4431:339a:fcb4:82d9 | V17: 解除済 | W17: 45904.567
A18: 4qTmIUy3Ppxz | B18: QSIKIEB9SBKq | C18: f88d288ae6fecec0ca2ff116173fcfcb | D18: 鈴木京子 | E18: 鈴木 京子 | F18: kyoko1206804@gmail.com | G18: 鈴木 | H18: 京子 | J18: 9010661356 | P18: 45908.583 | R18: 45889.895 | S18: 45889.895 | T18: https://sub.shirogakucho-web3.com/event/jZ7wxfoOunBs/confirm | U18: 133.238.22.119 | V18: 購読中
A19: fQhIoay8kuGK | B19: 4kBEbaM8ofz7 | C19: 401639219fec5c42a84b36bf642f2185 | D19: Kanako? | E19: 田中 加奈子 | F19: kanako.masita@ezweb.ne.jp | G19: 田中 | H19: 加奈子 | J19: 9011314662 | P19: 45907.5 | R19: 45889.93 | S19: 45889.93 | T19: https://sub.shirogakucho-web3.com/event/jZ7wxfoOunBs/confirm | U19: 2001:ce8:125:9954:7d21:c08:f4e0:c873 | V19: 購読中
A20: 85hiEKGekswk | B20: HnGPS2fhmxBi | C20: 83d85a29ab59bc0884dd5c10fa76f976 | D20: のりこ | E20: 舩津 典子 | F20: 2norinkoo221@gmail.com | G20: 舩津 | H20: 典子 | J20: 9077613897 | P20: 45908.833 | R20: 45889.96 | S20: 45889.96 | T20: https://sub.shirogakucho-web3.com/event/jZ7wxfoOunBs/confirm | U20: 240a:61:60f3:97a6:c124:2369:3d25:5e74 | V20: 購読中
A21: bUsVFgRPDlXl | B21: omuuXhVia2VE | C21: a90b5cfd8cbe93aa282628f526d9517b | D21: 井口 直道 | E21: 井口 直道 | F21: nao.igu-.1536@docomo.ne.jp | G21: 井口 | H21: 直道 | J21: 9027754038 | P21: 45907.583 | R21: 45890.081 | S21: 45890.081 | T21: https://sub.shirogakucho-web3.com/event/jZ7wxfoOunBs/confirm | U21: 240a:61:7011:310c:593a:bf69:808c:1d2b | V21: 購読中
A22: AjXL8oHEbfXa | E22: 宮川 泰 | F22: dryde194@gmail.com | G22: 宮川 | H22: 泰 | J22: 8055879764 | P22: 45909.75 | R22: 45890.148 | S22: 45890.148 | T22: https://sub.shirogakucho-web3.com/event/jZ7wxfoOunBs/confirm | U22: 202.16.105.136 | V22: 購読中
A23: X0XmSeXCc9t3 | B23: FOdcuCfjrwrZ | C23: 12ada6c4cfe89bb609ffd4680be27aac | D23: SachikoShinobu | E23: シノブ サチコ | F23: sa.shinobu@gmail.com | G23: シノブ | H23: サチコ | J23: 8053732364 | P23: 45909.625 | R23: 45890.275 | S23: 45890.275 | T23: https://sub.shirogakucho-web3.com/event/jZ7wxfoOunBs/confirm | U23: 2400:4051:b541:2d00:d502:4229:87a0:1475 | V23: 解除済 | W23: 45908.744
A24: Y4I87GbIs9QD | B24: fBA0pxPCPonl | C24: 3d91444815d3d53a5bf376f537ef3a89 | D24: 滝本 晴子 | E24: 滝本 晴子 | F24: supuring0709@gmail.com | G24: 滝本 | H24: 晴子 | J24: 9076746925 | P24: 45910.833 | R24: 45890.327 | S24: 45890.327 | T24: https://sub.shirogakucho-web3.com/event/jZ7wxfoOunBs/confirm | U24: 211.15.20.244 | V24: 購読中
A25: cYVRqOTbrTS6 | B25: DBHkJHMTfaqV | C25: a07f320c7016d4d0866bb420d7e930b4 | D25: 野口 博史 | E25: 野口 博史 | F25: hiroshi.n197891@gmail.com | G25: 野口 | H25: 博史 | J25: 0900-5581-4743 | P25: 45910.542 | R25: 45890.338 | S25: 45890.338 | T25: https://sub.shirogakucho-web3.com/event/jZ7wxfoOunBs/confirm | U25: 240b:c010:610:5e57:9327:7c3a:f2a:1094 | V25: 購読中
A26: URoncUipvEyr | B26: kq1Nyi2Ya0By | C26: b737a78e418c3f475e215720dc918682 | D26: サキコ | E26: 小笠原 咲子 | F26: ssfrst77@gmail.com | G26: 小笠原 | H26: 咲子 | J26: 7090502726 | P26: 45910.75 | R26: 45890.338 | S26: 45890.338 | T26: https://sub.shirogakucho-web3.com/event/jZ7wxfoOunBs/confirm | U26: 240b:c020:662:c7e5:20c6:28bc:7204:a49b | V26: 解除済 | W26: 45908.456
A27: Scv9MJESIDRP | B27: ss0YrufyhqQE | C27: 257f3588adc493d583c17a68f8dead7b | D27: はる | E27: 川村 晴彦 | F27: cherryharuk@gmail.com | G27: 川村 | H27: 晴彦 | J27: 542531528 | P27: 45910.625 | R27: 45890.626 | S27: 45890.626 | T27: https://sub.shirogakucho-web3.com/event/jZ7wxfoOunBs/confirm | U27: 94.177.17.137 | V27: 購読中
A28: aQJL7P1GJDOx | B28: wCRrKTqbm6Hz | C28: 702a7126553e9ecc443a0917a4757e95 | D28: pinkstar | E28: オオエ ムツコ | F28: pometree358@gmail.com | G28: オオエ | H28: ムツコ | J28: 8030370397 | P28: 45910.458 | R28: 45890.783 | S28: 45890.783 | T28: https://sub.shirogakucho-web3.com/event/jZ7wxfoOunBs/confirm | U28: 2405:1204:c415:7d00:2485:bc63:4bc1:9e14 | V28: 購読中
A29: z1rGTlfhvT7V | B29: yczeZbNHXTHT | C29: 25614cf7e93bddd6e03ea95daa7df301 | D29: 山元広之 | E29: 山元 広之 | F29: yamagen6750@gmail.com | G29: 山元 | H29: 広之 | J29: 9030347458 | P29: 45911.75 | R29: 45890.933 | S29: 45890.933 | T29: https://sub.shirogakucho-web3.com/event/jZ7wxfoOunBs/confirm | U29: 2001:ce8:127:eaa7:1d69:f52d:c3ba:43c7 | V29: 解除済 | W29: 45910.685
A30: HH1VZkMA2eWs | B30: r9W2EP5r9b8m | C30: a587a194da3ebd59460d0057db596ba8 | D30: Asao | E30: 増田 滋夫 | F30: asao3313@gmail.com | G30: 増田 | H30: 滋夫 | J30: 080-5417-7683 | P30: 45902.417 | R30: 45890.975 | S30: 45890.975 | T30: https://sub.shirogakucho-web3.com/event/jZ7wxfoOunBs/confirm | U30: 240d:1a:8ab:d100:ee2b:5ebc:6209:237b | V30: 購読中
A31: VwPh1zFlvuvB | B31: pMwpyh7TmWQt | C31: 3aef5f27bfa37e8430d0325e63ba2df6 | D31: tak | E31: 塚田 卓弥 | F31: tsukada@japaho.com | G31: 塚田 | H31: 卓弥 | J31: 9035203176 | P31: 45913.708 | R31: 45891.993 | S31: 45891.993 | T31: https://sub.shirogakucho-web3.com/event/jZ7wxfoOunBs/confirm | U31: 240b:12:8880:7d10:a037:8cdc:123d:efa0 | V31: 解除済 | W31: 45909.902
A32: HbrSNckGhhI7 | B32: veaEZMsJd6Wu | C32: b330e7c0e7507f88afdaa960171529ba | D32: たあさん358 | E32: 松本 貴子 | F32: kirrakirat@yahoo.co.jp | G32: 松本 | H32: 貴子 | J32: 9068567233 | P32: 45913.812 | R32: 45892.371 | S32: 45892.371 | T32: https://sub.shirogakucho-web3.com/event/jZ7wxfoOunBs/confirm | U32: 2001:268:9b27:81b2:51e4:6252:7998:3c20 | V32: 購読中
A33: vKqrgUlsedoL | B33: Jtj2bz7cjsjq | C33: 44b98a321f9282d25be47ff75ce269a9 | D33: 龍蔵 | E33: 宮本 龍蔵 | F33: miyamototatsuzo@icloud.com | G33: 宮本 | H33: 龍蔵 | J33: 9058883149 | P33: 45915.833 | R33: 45892.839 | S33: 45892.839 | T33: https://sub.shirogakucho-web3.com/event/jZ7wxfoOunBs/confirm | U33: 117.108.83.220 | V33: 購読中/配信エラー
A34: TUNo8X1zbI78 | B34: bvqOsSKp0XyS | C34: 6fbfafc59cb5912d2f20f33055c9f429 | D34: ひろみ | E34: 鈴木 裕美 | F34: onepiece-lover@docomo.ne.jp | G34: 鈴木 | H34: 裕美 | J34: 8019756262 | P34: 45914.417 | R34: 45892.839 | S34: 45892.839 | T34: https://sub.shirogakucho-web3.com/event/jZ7wxfoOunBs/confirm | U34: 240a:61:11d0:bcdb:c525:f7c6:9025:ab58 | V34: 購読中
A35: Yw4peQcMmBn1 | E35: 斉藤 至 | F35: cosmic4c@gmail.com | G35: 斉藤 | H35: 至 | J35: 8054116135 | P35: 45915.646 | R35: 45892.875 | S35: 45892.875 | T35: https://sub.shirogakucho-web3.com/event/jZ7wxfoOunBs/confirm | U35: 240f:109:8da3:1:45fb:c25a:f233:d77a | V35: 購読中
A36: e2iV2OfuoqGz | B36: 6VgrKcbqAaGu | C36: b6a46ea67eecb3a047f08c221327c1ad | D36: 河村正志 | E36: 河村 正志 | F36: k.masashi.5520@gmail.com | G36: 河村 | H36: 正志 | J36: 9098955520 | P36: 45915.75 | R36: 45892.926 | S36: 45892.926 | T36: https://sub.shirogakucho-web3.com/event/jZ7wxfoOunBs/confirm | U36: 2402:6b00:f551:f700:d0bc:8e46:e0d1:d0a7 | V36: 購読中
A37: Eess6BA6Uv4T | B37: PPUjqARW5iJ3 | C37: 5bff15815d93c3b225faa3be1df8c52c | D37: JJ伸介 | E37: 治部 伸介 | F37: bagzy.1133@docomo.ne.jp | G37: 治部 | H37: 伸介 | J37: 8019173726 | P37: 45914.542 | R37: 45893.36 | S37: 45893.36 | T37: https://sub.shirogakucho-web3.com/event/jZ7wxfoOunBs/confirm | U37: 240a:61:21f0:799b:b08e:2af4:39aa:b41e | V37: 購読中
A38: nVdgZN5kRx2x | B38: jmfz6Dgy6VEW | C38: fc0818c15ff6440fc9a3bb065bbc7c5c | D38: M.Kondoh | E38: 近藤 光浩 | F38: newkon1224@gmail.com | G38: 近藤 | H38: 光浩 | J38: 9035496200 | P38: 45895.583 | R38: 45893.476 | S38: 45893.476 | T38: https://sub.shirogakucho-web3.com/event/jZ7wxfoOunBs/confirm | U38: 2404:7a80:2aa0:6000:653f:5463:8fd3:5648 | V38: 購読中
A39: ha9DXTnxKJRS | B39: JYrVb5FakncW | C39: 9356dff92a589a573dfd24fec382d1af | D39: 仮想通貨大好き | E39: 大沼 駿介 | F39: greenteas77777@gmail.com | G39: 大沼 | H39: 駿介 | J39: 8080731571 | P39: 45914.792 | R39: 45893.886 | S39: 45893.886 | T39: https://sub.shirogakucho-web3.com/event/jZ7wxfoOunBs/confirm | U39: 103.5.140.162 | V39: 解除済 | W39: 45914.872
A40: CHKaBmAZIxJc | B40: oa8yJoqCFXNf | C40: 25b0897a76dd0ad40adcc9e9d531fa45 | D40: なつみ | E40: 野村 奈津美 | F40: wtipxr2236@yahoo.co.jp | G40: 野村 | H40: 奈津美 | J40: 8063315240 | P40: 45916.417 | R40: 45894.316 | S40: 45894.316 | T40: https://sub.shirogakucho-web3.com/event/jZ7wxfoOunBs/confirm | U40: 2001:268:73d2:ad56:8417:c096:3574:97ca | V40: 購読中
A41: QzadoqtVs2Mg | B41: WVjyZSW0yHgy | C41: 8473c16625015f0da585bc4621f04d79 | D41: おたぬ | E41: 東 寿子 | F41: otanu0713@gmail.com | G41: 東 | H41: 寿子 | J41: 8033415932 | P41: 45916.562 | R41: 45894.387 | S41: 45894.387 | T41: https://sub.shirogakucho-web3.com/event/jZ7wxfoOunBs/confirm | U41: 2001:268:73cb:79c3:f4b3:ee37:5375:b391 | V41: 解除済 | W41: 45916.718
A42: CrgcsGBnRblz | B42: VTLrkv8hjHII | C42: ad1326c01eae58314f7e7a406a0292a9 | D42: ちはる | E42: 東 千春 | F42: hugaryubya@xmailer.be | G42: 東 | H42: 千春 | J42: 9071620530 | P42: 45916.667 | R42: 45894.556 | S42: 45894.556 | T42: https://sub.shirogakucho-web3.com/event/jZ7wxfoOunBs/confirm | U42: 2400:4152:4182:d500:95c6:b1f2:5160:4590 | V42: 購読中
A43: crqnwAQgxA8Y | B43: 6nfwYPRTGxJp | C43: 773ac55b00cea14bc1415889fc5ae19e | D43: Tomoya Kaminade | E43: 上撫 智也 | F43: kaminade@gmail.com | G43: 上撫 | H43: 智也 | J43: 7090281925 | P43: 45917.812 | R43: 45894.847 | S43: 45894.847 | T43: https://sub.shirogakucho-web3.com/event/jZ7wxfoOunBs/confirm | U43: 240d:1e:20b:e000:7d7f:ce50:ab32:ebe0 | V43: 購読中
A44: JoXjiKFf0eZz | B44: MOb0AmpVhdsz | C44: 4b3fd8f633bd3c7fe1cd8df908b22e4d | D44: HIDE ISHIYAMA | E44: 石山 秀也 | F44: yokohama1480@gmail.com | G44: 石山 | H44: 秀也 | J44: 8033240595 | P44: 45914.625 | R44: 45894.946 | S44: 45894.946 | T44: https://sub.shirogakucho-web3.com/event/jZ7wxfoOunBs/confirm | U44: 160.13.181.204 | V44: 購読中
A45: kfYZMr9iXRuc | B45: NMXOEjGqpwhv | C45: c5d709f6baacacb1b940200621eb30cf | D45: Z1030 | E45: 榊 孝之 | F45: usamat2018@gmail.com | G45: 榊 | H45: 孝之 | J45: 9036569509 | P45: 45915.458 | R45: 45895.794 | S45: 45895.794 | T45: https://sub.shirogakucho-web3.com/event/jZ7wxfoOunBs/confirm | U45: 2001:268:942c:272e:212b:4ef7:15ee:5af3 | V45: 購読中
A46: pwfexuXRvTgg | B46: 33Ha9O3zsBg1 | C46: 09c11c0f2541a3bc766e726e6e262825 | D46: Katsuyuki | E46: 齋藤 勝之 | F46: acr50g212@gmail.com | G46: 齋藤 | H46: 勝之 | J46: 8057383777 | P46: 45914.708 | R46: 45895.86 | S46: 45895.86 | T46: https://sub.shirogakucho-web3.com/event/jZ7wxfoOunBs/confirm | U46: 2404:7a83:2560:1300:789e:bef9:bfd1:bedf | V46: 購読中
A47: Z7l2gunykP2d | B47: HVRUXHsXH7Z4 | C47: e30f7137960fc97738a0533a054a4da1 | D47: masa | E47: 伊里 昌晃 | F47: tarachan1111@docomo.ne.jp | G47: 伊里 | H47: 昌晃 | J47: 9050391443 | P47: 45919.688 | R47: 45896.883 | S47: 45896.883 | T47: https://sub.shirogakucho-web3.com/event/jZ7wxfoOunBs/confirm | U47: 103.235.112.13 | V47: 購読中
A48: 2mTdzGbDHUw7 | B48: sVbMsL1Bk7xM | C48: 0de67619a5c4e1d3d590ac68d026ed7a | D48: F，Masui | E48: 増井 文夫 | F48: fnkda.m@gmail.com | G48: 増井 | H48: 文夫 | J48: 9036451094 | P48: 45916.833 | R48: 45897.364 | S48: 45897.364 | T48: https://sub.shirogakucho-web3.com/event/jZ7wxfoOunBs/confirm | U48: 118.6.134.232 | V48: 購読中
A49: XAsNdIpSYi06 | B49: lFnPKghpSJxA | C49: b32f7349ef2c4dceafc0e7674bbd99f7 | D49: せつこ | E49: 吉見 節子 | F49: rockkun2020@gmail.com | G49: 吉見 | H49: 節子 | J49: 9095321955 | P49: 45918.458 | R49: 45897.575 | S49: 45897.575 | T49: https://sub.shirogakucho-web3.com/event/jZ7wxfoOunBs/confirm | U49: 2400:2413:1a69:bd00:ed8b:8004:4c3c:cf42 | V49: 解除済 | W49: 45915.683
A50: i8Em0jhwhF8U | B50: qTHwNRUiIfgN | C50: 403a3f5116e18ac1ed1a5e0cf4dd6bef | D50: やっちゃん | E50: 川野 泰宏 | F50: kawanokaiji0412@yahoo.co.jp | G50: 川野 | H50: 泰宏 | J50: 9082409173 | P50: 45916.75 | R50: 45897.831 | S50: 45897.831 | T50: https://sub.shirogakucho-web3.com/event/jZ7wxfoOunBs/confirm | U50: 2400:2200:730:8591::834:50cc | V50: 解除済 | W50: 45916.905
A51: rV7y42VvyNnO | B51: 2Co6veJdFn3x | C51: 6a19fe48646e503c31b85ce373472d48 | D51: 國田 | E51: くにた しんご | F51: pikota20162016@gmail.com | G51: くにた | H51: しんご | J51: 9028011749 | P51: 45919.833 | R51: 45897.832 | S51: 45897.832 | T51: https://sub.shirogakucho-web3.com/event/jZ7wxfoOunBs/confirm | U51: 219.100.53.205 | V51: 購読中
A52: d1FNkaVqCiVE | B52: 8Vhz4QNINqjj | C52: cef66dc88cb239cacd0757d2988ba329 | D52: 柴 昌史 | E52: 柴 昌史 | F52: shibasyouten@icloud.com | G52: 柴 | H52: 昌史 | J52: 9089724429 | P52: 45920.833 | R52: 45897.848 | S52: 45897.848 | T52: https://sub.shirogakucho-web3.com/event/jZ7wxfoOunBs/confirm | U52: 2001:318:201d:df:6993:3b4b:9dde:bfd0 | V52: 購読中/配信エラー
A53: 8gKJgGQayrgE | B53: sXXt1BP0ENpl | C53: b6fce42938742947297647f2808e495d | D53: メグ | E53: 水上 めぐみ | F53: megu_mi0901@yahoo.co.jp | G53: 水上 | H53: めぐみ | J53: 9087203939 | P53: 45919.5 | R53: 45898.087 | S53: 45898.087 | T53: https://sub.shirogakucho-web3.com/event/jZ7wxfoOunBs/confirm | U53: 223.217.2.168 | V53: 購読中
A54: CL95AzYrs8hC | B54: JYsq5fo2zga0 | C54: 1e6ebd7d6ee115e3af484e93705521d2 | D54: Jun | E54: 二枝 順子 | F54: jun4518.tai@gmail.com | G54: 二枝 | H54: 順子 | J54: 9098893138 | P54: 45919.417 | R54: 45898.822 | S54: 45898.822 | T54: https://sub.shirogakucho-web3.com/event/jZ7wxfoOunBs/confirm | U54: 2405:1205:909c:5a00:c970:9e64:39e3:445a | V54: 購読中
A55: blIeEk7uzfOT | B55: TFFU7872LiTT | C55: b652689716fed13cfc97e8c99863645a | D55: Taichiro | E55: 久保 太一郎 | F55: taichirokubo1@gmail.com | G55: 久保 | H55: 太一郎 | J55: 8058983074 | P55: 45917.458 | R55: 45898.861 | S55: 45898.861 | T55: https://sub.shirogakucho-web3.com/event/jZ7wxfoOunBs/confirm | U55: 101.50.55.106 | V55: 購読中
A56: zRVBX8D2UI84 | B56: V5xKgz0zXKN3 | C56: 8ca1528de53cad2a24a46157fe306bea | D56: 蛇渕 | E56: 蛇渕 勉 | F56: avs0522@gmail.com | G56: 蛇渕 | H56: 勉 | J56: 9013142477 | P56: 45921.583 | R56: 45899.73 | S56: 45899.73 | T56: https://sub.shirogakucho-web3.com/event/jZ7wxfoOunBs/confirm | U56: 133.32.177.121 | V56: 解除済 | W56: 45918.547
A57: zJyNbhLHq7Ax | B57: aAUgJci2lJxG | C57: 74f9119f5bee9b34bf26896882d1f0d4 | D57: HIKARU | E57: 井戸 雅栄 | F57: seoritsuhime7@gmail.com | G57: 井戸 | H57: 雅栄 | J57: 7092282135 | P57: 45917.542 | R57: 45899.82 | S57: 45899.82 | T57: https://sub.shirogakucho-web3.com/event/jZ7wxfoOunBs/confirm | U57: 240d:f:401:3400:a4ac:cee6:49f7:e67f | V57: 購読中
A58: E5VHlmrBoUtm | B58: cFwEWtLU7Lnv | C58: 6e9f9894fddfd79249fb3cb16be28d3a | D58: タケダアツシ | E58: 竹田 篤史 | F58: amdbsgt1@gmail.com | G58: 竹田 | H58: 篤史 | J58: 9013935281 | P58: 45921.417 | R58: 45899.897 | S58: 45899.897 | T58: https://sub.shirogakucho-web3.com/event/jZ7wxfoOunBs/confirm | U58: 240b:10:f02:ae00:dcda:b5d8:2419:7954 | V58: 購読中
A59: lUaSVQWzM0ni | B59: aXXej21DkEPE | C59: 9796aaf26c82d30074c88103412ba72c | D59: ラファエル | E59: 斉藤 正幸 | F59: yuuzouka@yahoo.co.jp | G59: 斉藤 | H59: 正幸 | J59: 8048660596 | P59: 45917.625 | R59: 45899.976 | S59: 45899.976 | T59: https://sub.shirogakucho-web3.com/event/jZ7wxfoOunBs/confirm | U59: 2001:f71:1a00:6900:4c61:dc33:341b:f6b2 | V59: 購読中
A60: 28gI46Kr6jCF | B60: rx8DgfddwPbc | C60: c97e0fa7b48c516d1cd7d6fe7cbd7a90 | D60: SEIJI OKADA | E60: 岡田 聖司 | F60: okada@nkeg.net | G60: 岡田 | H60: 聖司 | J60: 9060020262 | P60: 45918.708 | R60: 45901.603 | S60: 45901.603 | T60: https://sub.shirogakucho-web3.com/event/jZ7wxfoOunBs/confirm | U60: 223.219.187.189 | V60: 購読中
A61: nRA8TLfC9Dlq | B61: nemEf7dY5hq6 | C61: 9979c1f1ffaea4f756abfece42a9fc70 | D61: Haliua | E61: 佐野 治美 | F61: harumir7@gmail.com | G61: 佐野 | H61: 治美 | J61: 273092323 | P61: 45922.667 | R61: 45901.797 | S61: 45901.797 | T61: https://sub.shirogakucho-web3.com/event/jZ7wxfoOunBs/confirm | U61: 139.180.110.34 | V61: 購読中
A62: QciKLdpdqBz0 | B62: eh8HsD0I4OUG | C62: 3938fe00f01dd045dc271d441afaffc0 | D62: あき | E62: 松浦 章展 | F62: akikoko0110@yahoo.co.jp | G62: 松浦 | H62: 章展 | J62: 8034937458 | P62: 45923.417 | R62: 45901.81 | S62: 45901.81 | T62: https://sub.shirogakucho-web3.com/event/jZ7wxfoOunBs/confirm | U62: 2001:ce8:144:b55b:4c97:7a37:6bd2:7cde | V62: 購読中
A63: 0LbWhdne5mov | B63: Qk03xF79oEGi | C63: e4abd8bac8ce846821cc93e70a7d4848 | D63: 齋藤 拓己 | E63: 齋藤 拓己 | F63: hypocrite5843@gmail.com | G63: 齋藤 | H63: 拓己 | J63: 9073266764 | P63: 45919.583 | R63: 45901.816 | S63: 45901.816 | T63: https://sub.shirogakucho-web3.com/event/jZ7wxfoOunBs/confirm | U63: 60.88.80.86 | V63: 購読中
A64: AG1fJUaoEq2N | B64: QTdbAAsme1C0 | C64: e09ab61697cfbc00324df88dcccfe8c5 | D64: Kentaro Hatakeyama | E64: 畠山 健太郎 | F64: kefu051204@outlook.jp | G64: 畠山 | H64: 健太郎 | J64: 8056451509 | P64: 45922.583 | R64: 45902.596 | S64: 45902.596 | T64: https://sub.shirogakucho-web3.com/event/jZ7wxfoOunBs/confirm | U64: 180.50.183.186 | V64: 購読中
A65: 6h5hfHc1kBfM | B65: hBvvDKFH6U7G | C65: 1f387100fc84124595837be9200a172f | D65: えみ | E65: 正木 晃 | F65: emi.emi.honey@gmail.com | G65: 正木 | H65: 晃 | J65: 9089183189 | P65: 45925.417 | R65: 45902.883 | S65: 45902.883 | T65: https://sub.shirogakucho-web3.com/event/jZ7wxfoOunBs/confirm | U65: 110.66.122.165 | V65: 解除済 | W65: 45911.586
A66: 1Y9EPRJzL79Y | B66: RHMsKMq1Hico | C66: b94a3c984a089fd49953b89c20741928 | D66: sakata | E66: 坂田 剛士 | F66: tuyosaka13@gmail.com | G66: 坂田 | H66: 剛士 | J66: 8042305093 | P66: 45922.833 | R66: 45903.494 | S66: 45903.494 | T66: https://sub.shirogakucho-web3.com/event/jZ7wxfoOunBs/confirm | U66: 118.241.249.198 | V66: 購読中
A67: XKcNjRmyfHXu | B67: 1JSN7BqATzQ5 | C67: a0004b387698e55941e63f31e1323968 | D67: 藤巻健司 | E67: 藤巻 健司 | F67: ken964fu@ezweb.ne.jp | G67: 藤巻 | H67: 健司 | J67: 9081141629 | P67: 45922.458 | R67: 45903.875 | S67: 45903.875 | T67: https://sub.shirogakucho-web3.com/event/jZ7wxfoOunBs/confirm | U67: 2001:268:98f0:8cfe:5176:3d74:a24e:8b6f | V67: 購読中
A68: 1hkZhZCwD4s1 | B68: vxQufk7l17Gy | C68: 34b8bae1a973ba9e6ca834dc561259ae | D68: Akira Ota (Miguel) | E68: 太田 明 | F68: miguel.akira.ota@gmail.com | G68: 太田 | H68: 明 | J68: 524623091922 | P68: 45924.5 | R68: 45904.316 | S68: 45904.316 | T68: https://sub.shirogakucho-web3.com/event/jZ7wxfoOunBs/confirm | U68: 200.68.183.175 | V68: 解除済 | W68: 45924.466
A69: e5bzaimJ0oCm | B69: QobJHz86zqGy | C69: 603ac8f03210242416dda698e3dba6f7 | D69: かず | E69: 小高 和博 | F69: odaka_kazuhiro@yahoo.co.jp | G69: 小高 | H69: 和博 | J69: 7084316398 | P69: 45921.833 | R69: 45904.611 | S69: 45904.611 | T69: https://sub.shirogakucho-web3.com/event/jZ7wxfoOunBs/confirm | U69: 240b:c010:640:e11b:0:2f:2fba:1101 | V69: 購読中
A70: SchzTwE0N0x3 | B70: kgXcqTzFZscN | C70: a22831f4abf5f30120ce50de99f31ecf | D70: 片平好郎 | E70: 片平 好郎 | F70: yoshiro19801225@gmail.com | G70: 片平 | H70: 好郎 | J70: 9025028912 | P70: 45927.833 | R70: 45904.888 | S70: 45904.888 | T70: https://sub.shirogakucho-web3.com/event/jZ7wxfoOunBs/confirm | U70: 110.54.98.188 | V70: 購読中
A71: VwPh1zFlvuvB | B71: pMwpyh7TmWQt | C71: 3aef5f27bfa37e8430d0325e63ba2df6 | D71: tak | E71: 塚田 卓弥 | F71: takuya.tsukada@icloud.com | G71: 塚田 | H71: 卓弥 | J71: 090-3420-3176 | P71: 45907.667 | R71: 45904.901 | S71: 45904.901 | T71: https://sub.shirogakucho-web3.com/event/jZ7wxfoOunBs/confirm | U71: 240a:61:4032:1665:65da:b813:5540:62ec | V71: 購読中
A72: Gk0JZSuYsQT7 | B72: k1YplBZYyQtj | C72: 9c18f7a443255fbed918b4856f9dee60 | D72: Miki Takada | E72: 髙田 美樹 | F72: sakuboo85@gmail.con | G72: 髙田 | H72: 美樹 | J72: 9086185577 | P72: 45921.75 | R72: 45904.906 | S72: 45904.906 | T72: https://sub.shirogakucho-web3.com/event/jZ7wxfoOunBs/confirm | U72: 14.15.65.252 | V72: 購読中/配信エラー
A73: ZjU6iYmhH9xK | B73: ggOadJ62lkOn | C73: a02ebe9cb5d4fd92e0b630871a4a723f | D73: 150㌢?? | E73: 山本 瞳 | F73: hitomimakeup0130@icloud.com | G73: 山本 | H73: 瞳 | J73: 8010258293 | P73: 45923.625 | R73: 45906.617 | S73: 45906.617 | T73: https://sub.shirogakucho-web3.com/event/jZ7wxfoOunBs/confirm | U73: 118.87.44.138 | V73: 購読中/配信エラー
A74: IQD9JgSfp9tB | B74: dV5TkDQ9WOHV | C74: 458a6d95c86451c5db26d3dc2f737029 | D74: Nasu Michiko | E74: 那須 道子 | F74: nasutomato93@gmail.com | G74: 那須 | H74: 道子 | J74: 9061740651 | P74: 45924.583 | R74: 45906.753 | S74: 45906.753 | T74: https://sub.shirogakucho-web3.com/event/jZ7wxfoOunBs/confirm | U74: 240f:30:dc3:1:8c97:ce3c:5ff:b63a | V74: 購読中
A75: s6POhSd4Zhao | B75: Wgw54gVsaV6t | C75: 321aaf9e588d858063902bdb6f319e29 | D75: Tomi.Yoshimura | E75: 吉村 富幸 | F75: tomiguma@gmail.com | G75: 吉村 | H75: 富幸 | J75: 9099080853 | P75: 45924.812 | R75: 45906.899 | S75: 45906.899 | T75: https://sub.shirogakucho-web3.com/event/jZ7wxfoOunBs/confirm | U75: 2402:6b00:f315:ae00:e0d8:ae96:57e0:b90e | V75: 購読中
A76: hQ4TwjsverNH | B76: 94ZJ16u0hl5l | C76: 8b073b858e01f381032a7352e0d588f6 | D76: ＨＩＲＯ | E76: 鈴木 宏一 | F76: h-suzuki@daiwack.co.jp | G76: 鈴木 | H76: 宏一 | J76: 9033816577 | P76: 45923.771 | R76: 45907.63 | S76: 45907.63 | T76: https://sub.shirogakucho-web3.com/event/jZ7wxfoOunBs/confirm | U76: 183.77.56.18 | V76: 購読中
A77: N9VEZ019B9im | E77: 西宮 敏子 | F77: koufuk0322@gmail.com | G77: 西宮 | H77: 敏子 | J77: 7083243019 | P77: 45930.417 | R77: 45909.758 | S77: 45909.758 | T77: https://sub.shirogakucho-web3.com/event/jZ7wxfoOunBs/confirm | U77: 2400:2410:31a2:c100:b6ba:1ea7:cc24:da85 | V77: 購読中
A78: rebwWSYWrMfe | B78: rXoPbiUp0YuB | C78: c452e0259109160958b68b8db2b0f742 | D78: 外山広行 | E78: 外山広行 トヤマヒロユキ | F78: toyaman23-2525@docomo.ne.jp | G78: 外山広行 | H78: トヤマヒロユキ | J78: 9021745990 | P78: 45921.5 | R78: 45909.892 | S78: 45909.892 | T78: https://sub.shirogakucho-web3.com/event/jZ7wxfoOunBs/confirm | U78: 2a09:bac2:4366:efa::17e:13f | V78: 購読中
A79: zNnG2qs9dilx | B79: eX1ld6IYwoZV | C79: 76d6e6b950006ea2889faaed20b76db9 | D79: まりこ | E79: 朝川 まりこ まり子 | F79: mariconb371@gmail.com | G79: 朝川 まりこ | H79: まり子 | J79: 7092276405 | P79: 45921.667 | R79: 45909.97 | S79: 45909.97 | T79: https://sub.shirogakucho-web3.com/event/jZ7wxfoOunBs/confirm | U79: 240b:c020:600:953c:0:26:4b11:3a01 | V79: 購読中
A80: e0GyhemJLizd | B80: KWbu1wK8hPon | C80: 1da2c9b5ceca69903ed135be964b8d7f | D80: igory | E80: 船元 竹文 | F80: kyonbokun0509@gmail.com | G80: 船元 | H80: 竹文 | J80: 9054120213 | P80: 45931.458 | R80: 45911.018 | S80: 45911.018 | T80: https://sub.shirogakucho-web3.com/event/jZ7wxfoOunBs/confirm | U80: 122.30.2.230 | V80: 購読中
A81: TllJMv4INfZr | B81: znieTIWhoyIe | C81: 4745124a6fab280d500d5b5bc0436c18 | D81: soulword | E81: 吉田 隆 | F81: ty11055yoshi@gmail.com | G81: 吉田 | H81: 隆 | J81: 9056342118 | P81: 45922.75 | R81: 45911.229 | S81: 45911.229 | T81: https://sub.shirogakucho-web3.com/event/jZ7wxfoOunBs/confirm | U81: 129.227.238.147 | V81: 購読中
A82: 6h5hfHc1kBfM | B82: hBvvDKFH6U7G | C82: 1f387100fc84124595837be9200a172f | D82: えみ | E82: 正木 晃 | F82: akira.36.2994@gmail.com | G82: 正木 | H82: 晃 | J82: 9089183189 | P82: 45925.75 | R82: 45911.635 | S82: 45911.635 | T82: https://sub.shirogakucho-web3.com/event/jZ7wxfoOunBs/confirm | U82: 110.66.122.165 | V82: 購読中
A83: c3mV2WrTOWzN | B83: n4xvM0A0bqhM | C83: 3cc9706e96f040fd96016cfdca6c4d78 | D83: 0RENJER29 | E83: 松村 博敏 | F83: h.m29.yuimaru39@gmail.com | G83: 松村 | H83: 博敏 | J83: 7091917758 | P83: 45929.833 | R83: 45912.395 | S83: 45912.395 | T83: https://sub.shirogakucho-web3.com/event/jZ7wxfoOunBs/confirm | U83: 126.23.225.125 | V83: 購読中
A84: Y1BylZ3V6h5L | B84: Ut01IEn22jkp | C84: 6551a361c2b683f4d66cbb960b3d8627 | D84: 武田 賢一 | E84: 武田 賢一 | F84: acotarou@icloud.com | G84: 武田 | H84: 賢一 | J84: 9038150823 | P84: 45924.729 | R84: 45912.424 | S84: 45912.424 | T84: https://sub.shirogakucho-web3.com/event/jZ7wxfoOunBs/confirm | U84: 2400:2412:28e0:f900:dd74:1ea5:404a:99ab | V84: 購読中/配信エラー
A85: Mdxuw65xdEzn | B85: c1JRKQXIUD5g | C85: 610b80fc2f5a81beec829db0f792fa32 | D85: 深野博美 | E85: 深野 博美 | F85: hiro6170836@yahoo.co.jp | G85: 深野 | H85: 博美 | J85: 8038356677 | P85: 45934.708 | R85: 45913.743 | S85: 45913.743 | T85: https://sub.shirogakucho-web3.com/event/jZ7wxfoOunBs/confirm | U85: 157.70.174.213 | V85: 購読中
A86: xs4hxc4GwkgZ | B86: GdS9JJ8GXWp1 | C86: 1190edac99bb9d5da3b4eae5de3f5266 | D86: ?Michiko | E86: 富田 美智子 | F86: miko423@yahoo.co.jp | G86: 富田 | H86: 美智子 | J86: 9074284153 | P86: 45925.458 | R86: 45913.949 | S86: 45913.949 | T86: https://sub.shirogakucho-web3.com/event/jZ7wxfoOunBs/confirm | U86: 118.87.205.94 | V86: 購読中
A87: E9oHj50cozJJ | B87: JULHhwtNNhGv | C87: 56cba9111b95c8ee2d1fe0323ecdec6e | D87: 新井 | E87: 新井 健次 | F87: gold.6675@outlook.jp | G87: 新井 | H87: 健次 | J87: 9072089588 | P87: 45934.792 | R87: 45914.326 | S87: 45914.326 | T87: https://sub.shirogakucho-web3.com/event/jZ7wxfoOunBs/confirm | U87: 240b:c010:4b2:d275:fd78:c0ef:adb3:f57f | V87: 購読中/配信エラー
A88: XA6UurlD0tPV | B88: S2iQGhQJAiNb | C88: 6b8df455b7e604ea197d98dc4958a9dd | D88: 西藤 章恵 | E88: 西藤 章恵 | F88: happy.win.1202@gmail.com | G88: 齊藤 | H88: 章恵 | J88: 9040892987 | P88: 45929.625 | R88: 45914.512 | S88: 45914.512 | T88: https://sub.shirogakucho-web3.com/event/jZ7wxfoOunBs/confirm | U88: 60.88.234.85 | V88: 解除済 | W88: 45915.708
A89: VlzCvHmC6xIL | B89: XdUzPE54uZZh | C89: a458d3d4db14f58d40156d11df3754a3 | D89: 奥川 | E89: 奥川 忠洋 | F89: facata0807@outlook.jp | G89: 奥川 | H89: 忠洋 | J89: 8056730807 | P89: 45931.833 | R89: 45914.657 | S89: 45914.657 | T89: https://sub.shirogakucho-web3.com/event/jZ7wxfoOunBs/confirm | U89: 2001:3b0:22:bc8a:2503:1515:d4c0:4837 | V89: 解除済/配信エラー | W89: 45931.416
A90: tCmOy2fwbXJR | B90: pCE2tsGPUMbM | C90: 0c6caf0f21c1ba794a9163834d633a09 | D90: aya hiraguchi | E90: 平口 亜弥 | F90: qnthn159159@gmail.com | G90: 平口 | H90: 亜弥 | J90: 8044845003 | P90: 45929.417 | R90: 45915.406 | S90: 45915.406 | T90: https://sub.shirogakucho-web3.com/event/jZ7wxfoOunBs/confirm | U90: 119.245.112.240 | V90: 購読中
A91: OMMfHeyP3Z4y | B91: lk4ZgEsVQLVR | C91: b4b2a40a275455b719db6827ab34b635 | D91: 聖慈 s.kondo1214 | E91: 近藤 聖慈 | F91: s.kondo@hotmail.com | G91: 近藤 | H91: 聖慈 | J91: 9050052952 | P91: 45936.75 | R91: 45916.382 | S91: 45916.382 | T91: https://sub.shirogakucho-web3.com/event/jZ7wxfoOunBs/confirm | U91: 2400:2200:8d4:8006:68de:9cf6:c0bb:a5f7 | V91: 購読中/配信エラー
A92: LmUqbVAEhZUd | B92: dKt1SjFRsgTV | C92: 748c2167fb49c463b8507c47b2a51203 | D92: 藤田 ルリコ | E92: 藤田 ルリ子 | F92: bitruriko1@gmail.com | G92: 藤田 | H92: ルリ子 | J92: 8029171313 | P92: 45935.542 | R92: 45916.736 | S92: 45916.736 | T92: https://sub.shirogakucho-web3.com/event/jZ7wxfoOunBs/confirm | U92: 2400:4172:3964:ff00:5cde:f807:b52e:2976 | V92: 購読中
A93: AbhohXF4Fxq6 | B93: uIyBAmUxkw5o | C93: e17ef4a7a6ee670b93d3cf56c4d23e56 | D93: 伊藤(山﨑)梢江 | E93: 山崎 こずえ | F93: moderation.to@gmail.com | G93: 山崎 | H93: こずえ | J93: 9010350987 | P93: 45931.542 | R93: 45917.451 | S93: 45917.451 | T93: https://sub.shirogakucho-web3.com/event/jZ7wxfoOunBs/confirm | U93: 2001:268:985d:3a2e:2122:cad5:1551:d70f | V93: 購読中
A94: XA6UurlD0tPV | B94: S2iQGhQJAiNb | C94: 6b8df455b7e604ea197d98dc4958a9dd | D94: 西藤 章恵 | E94: 西藤 章恵 | F94: happy.win.1202@gmail.com | G94: 西藤 | H94: 章恵 | J94: 9040892987 | P94: 45928.771 | R94: 45917.565 | S94: 45917.565 | T94: https://sub.shirogakucho-web3.com/event/jZ7wxfoOunBs/confirm | U94: 60.88.234.85 | V94: 解除済 | W94: 45917.608
A95: XA6UurlD0tPV | B95: S2iQGhQJAiNb | C95: 6b8df455b7e604ea197d98dc4958a9dd | D95: 西藤 章恵 | E95: 西藤 章恵 | F95: happy.win.1202@gmail.com | G95: 西藤 | H95: 章恵 | J95: 9040892987 | P95: 45932.75 | R95: 45917.621 | S95: 45917.621 | T95: https://sub.shirogakucho-web3.com/event/jZ7wxfoOunBs/confirm | U95: 60.88.234.85 | V95: 解除済 | W95: 45934.876
A96: 0fWQWDIoX1ow | B96: Ufqh3RlHmk2v | C96: 51bdea5378694285b6361a9c942e1626 | D96: 上原 和人 | E96: 上原 和人 | F96: tozukarahaeu@yahoo.co.jp | G96: 上原 | H96: 和人 | J96: 9057434276 | P96: 45927.75 | R96: 45918.276 | S96: 45918.276 | T96: https://sub.shirogakucho-web3.com/event/jZ7wxfoOunBs/confirm | U96: 119.244.161.64 | V96: 購読中
A97: ypGdiAl1vR6a | B97: wjYzmhF90OFW | C97: 7344ceb7d5343521280dd3e225ef5579 | D97: 和泉裕規 | E97: 和泉 裕規 | F97: letterizumi@gmail.com | G97: 和泉 | H97: 裕規 | J97: 7014861024 | P97: 45926.583 | R97: 45918.699 | S97: 45918.699 | T97: https://sub.shirogakucho-web3.com/event/jZ7wxfoOunBs/confirm | U97: 2400:4150:3801:5900:f5ee:2005:397c:fc | V97: 購読中
A98: hHYLbjp5DbFT | B98: R4Esgx7zzECD | C98: cbf52d96d3cc6eec41fd744ca603c997 | D98: yui | E98: 小林 唯 | F98: pbwribbon@yahoo.co.jp | G98: 小林 | H98: 唯 | J98: 9046240270 | P98: 45926.792 | R98: 45918.729 | S98: 45918.729 | T98: https://sub.shirogakucho-web3.com/event/jZ7wxfoOunBs/confirm | U98: 240a:61:3ca0:f58:4410:3080:2971:5906 | V98: 購読中
A99: Ob09TlES2e4K | B99: DUDQaSg4OQMo | C99: cc8f039a3547b4ec1397f668aea52b5d | D99: わたなべなおき | E99: 渡部 直樹 | F99: kitanodaijc@yahoo.co.jp | G99: 渡部 | H99: 直樹 | J99: 7026721685 | P99: 45926.667 | R99: 45919.292 | S99: 45919.292 | T99: https://sub.shirogakucho-web3.com/event/jZ7wxfoOunBs/confirm | U99: 240d:1a:18d:8a00:f8f4:2905:2499:fe3d | V99: 購読中
A100: eB2NShnyHEeL | B100: lBJpMJiIewgr | C100: 8fc8eb47a2a70b84d7d1510a532c76ef | D100: ひさし | E100: 角田 寿 | F100: kasudane@gmail.com | G100: 角田 | H100: 寿 | J100: 9029857242 | P100: 45931.708 | R100: 45919.394 | S100: 45919.394 | T100: https://sub.shirogakucho-web3.com/event/jZ7wxfoOunBs/confirm | U100: 153.133.228.196 | V100: 購読中
...
